Workbook
Name _Hlk503351175: WizdomActuals!$I$4
Name _Hlk517339798: Expenses!$B$2

Sheet Forecast
E2: Inflation Rate | F2: 0.03 | H2: Non-zero (CPI or inflation rate) show of money in TODAY'S dollars. Set to zero if future values do not want to account for inflation
E3: Jeff Net Tax Rate | F3: 0.29
E4: Tin Net Tax Rate | F4: 0.19
R5: 60 yrs | Y5: 67 | AG5: 75
D6: 2026 | E6: =D6+1 -> 2027 | F6: =E6+1 -> 2028 | G6: =F6+1 -> 2029 | H6: =G6+1 -> 2030 | I6: =H6+1 -> 2031 | J6: =I6+1 -> 2032 | K6: =J6+1 -> 2033 | L6: =K6+1 -> 2034 | ... AG6: =AF6+1 -> 2055
C7: Net Cashflow | D7: =SUM(D13:D20) -> 66980.625 | E7: =SUM(E13:E32) -> 17535.609 | F7: =SUM(F13:F32) -> 21110.789 | G7: =SUM(G13:G32) -> 14609.613 | H7: =SUM(H13:H32) -> 18198.015 | I7: =SUM(I13:I32) -> 35232.925 | J7: =SUM(J13:J32) -> 57674.492 | K7: =SUM(K13:K32) -> 79574.156 | L7: =SUM(L13:L32) -> 84616.975 | ... AG7: =SUM(AG13:AG32) -> 385420.8
C8: Net Wealth | D8: =D7+SUM(D38:D47)+D33 -> 3623680.6 | E8: =E7+SUM(E38:E47)+E33 -> 1789442.4 | F8: =F7+SUM(F38:F47)+F33 -> 2031405.7 | G8: =G7+SUM(G38:G47)+G33 -> 2277646 | H8: =H7+SUM(H38:H47)+H33 -> 2548873.8 | I8: =I7+SUM(I38:I47)+I33 -> 2846362.5 | J8: =J7+SUM(J38:J47)+J33 -> 3148352.5 | K8: =K7+SUM(K38:K47)+K33 -> 3466639.9 | ... AG8: =AG7+SUM(AG38:AG47)+AG33 -> 16781418
D12: Sum of 2026 | E12: Sum of 2027 | F12: Sum of 2028 | G12: Sum of 2029 | H12: Sum of 2030 | I12: Sum of 2031 | J12: Sum of 2032 | K12: Sum of 2033 | L12: Sum of 2034 | M12: Sum of 2035 | N12: Sum of 2036 | O12: Sum of 2037 | P12: Sum of 2038 | Q12: Sum of 2039 | R12: Sum of 2040 | S12: Sum of 2041 | T12: Sum of 2042 | U12: Sum of 2043 | V12: Sum of 2044 | W12: Sum of 2045 | X12: Sum of 2046 | Y12: Sum of 2047 | Z12: Sum of 2048 | AA12: Sum of 2049 | AB12: Sum of 2050 | AC12: Sum of 2051 | AD12: Sum of 2052 | AE12: Sum of 2053 | AF12: Sum of 2054 | AG12: Sum of 2055
C13: Jeff | D13: 222332.3 | E13: 181833.72 | F13: 189243.46 | G13: 197132.95 | H13: 205142.01 | I13: 239835.84 | J13: 248236.25 | K13: 257127.22 | L13: 266187.12 | M13: 275534.71 | N13: 285082.05 | O13: 295130.64 | P13: 305408.14 | Q13: 316019.89 | R13: 326901.16 | S13: 338293.9 | T13: 349988.76 | U13: 362073.79 | V13: 374513.93 | W13: 387474.77 | X13: 400827.48 | Y13: 414637.94 | Z13: 428845.78 | AA13: 441676.39 | AB13: 453987.91 | AC13: 466648.73 | AD13: 479664.2 | AE13: 493062.44 | AF13: 506773.15 | AG13: 520077.93
C14: Magiting | D14: 41620.8 | E14: -15570.313 | F14: -13528.343 | G14: -11077.196 | H14: -8673.5641 | I14: -6161.2749 | J14: -3683.2492 | K14: -797.51477 | L14: 2075.2832 | M14: 5081.2913 | N14: 8094.5927 | O14: 11512.927 | P14: 14962.038 | Q14: 18575.139 | R14: 22248.18 | S14: 26321.927 | T14: 30481.821 | U14: 34844.397 | V14: 39333.733 | W14: 44217.208 | X14: 49257.098 | Y14: 54548.432 | Z14: 60051.469 | AA14: 65939.075 | AB14: 72072.412 | AC14: 78518.787 | AD14: 85285.01 | AE14: 91863.709 | AF14: 95225.38 | AG14: 98082.142
C15: Tin | D15: 96368.578 | E15: 84442.682 | F15: 87146.865 | G15: 90006.34 | H15: 92909.781 | I15: 95897.048 | J15: 98934.123 | K15: 102131.82 | L15: 105387.35 | M15: 108738.36 | N15: 112154.9 | O15: 115737.7 | P15: 119394.83 | Q15: 123161.11 | R15: 127011.77 | S15: 131034.54 | T15: 135151.43 | U15: 139393.55 | V15: 143742.74 | W15: 148270.08 | X15: 152915.35 | Y15: 157704.89 | Z15: 162628.32 | AA15: 167716.73 | AB15: 172941.58 | AC15: 178331.43 | AD15: 183886.81 | AE15: 189630.9 | AF15: 195488.3 | AG15: 200735.43
C17: Jeff Tax | D17: =-1*$F$3*D13 -> -64476.368 | E17: =-1*$F$3*E13 -> -52731.778 | F17: =-1*$F$3*F13 -> -54880.603 | G17: =-1*$F$3*G13 -> -57168.554 | H17: =-1*$F$3*H13 -> -59491.184 | I17: =-1*$F$3*I13 -> -69552.395 | J17: =-1*$F$3*J13 -> -71988.513 | K17: =-1*$F$3*K13 -> -74566.893 | ... AG17: =-1*$F$3*AG13 -> -150822.6
C18: Tin Tax | D18: =-1*$F$3*D15 -> -27946.888 | E18: =-1*$F$3*E15 -> -24488.378 | F18: =-1*$F$3*F15 -> -25272.591 | G18: =-1*$F$3*G15 -> -26101.839 | H18: =-1*$F$3*H15 -> -26943.837 | I18: =-1*$F$3*I15 -> -27810.144 | J18: =-1*$F$3*J15 -> -28690.896 | K18: =-1*$F$3*K15 -> -29618.228 | ... AG18: =-1*$F$3*AG15 -> -58213.274
C19: Repayments | D19: -105678 | E19: =-1*SUMPRODUCT((E6=Repayments!$AZ$49:$CC$49)*(Repayments!$AZ$50:$CC$50)) -> -47853.327 | F19: =-1*SUMPRODUCT((F6=Repayments!$AZ$49:$CC$49)*(Repayments!$AZ$50:$CC$50)) -> -50558.094 | G19: =-1*SUMPRODUCT((G6=Repayments!$AZ$49:$CC$49)*(Repayments!$AZ$50:$CC$50)) -> -54110.983 | H19: =-1*SUMPRODUCT((H6=Repayments!$AZ$49:$CC$49)*(Repayments!$AZ$50:$CC$50)) -> -57551.961 | I19: =-1*SUMPRODUCT((I6=Repayments!$AZ$49:$CC$49)*(Repayments!$AZ$50:$CC$50)) -> -59567.123 | J19: =-1*SUMPRODUCT((J6=Repayments!$AZ$49:$CC$49)*(Repayments!$AZ$50:$CC$50)) -> -44411.925 | K19: =-1*SUMPRODUCT((K6=Repayments!$AZ$49:$CC$49)*(Repayments!$AZ$50:$CC$50)) -> -47569.306 | L19: =-1*SUMPRODUCT((L6=Repayments!$AZ$49:$CC$49)*(Repayments!$AZ$50:$CC$50)) -> -50629.249 | ... AG19: =-1*SUMPRODUCT((AG6=Repayments!$AZ$49:$CC$49)*(Repayments!$AZ$50:$CC$50)) -> 0
C20: Expenses | D20: =-12*SUMPRODUCT((D6=Expenses!$J$2:$AM$2)*(Expenses!$J$3:$AM$41)) -> -95239.8 | E20: =-12*SUMPRODUCT((E6=Expenses!$J$2:$AM$2)*(Expenses!$J$3:$AM$41)) -> -98096.994 | F20: =-12*SUMPRODUCT((F6=Expenses!$J$2:$AM$2)*(Expenses!$J$3:$AM$41)) -> -101039.9 | G20: =-12*SUMPRODUCT((G6=Expenses!$J$2:$AM$2)*(Expenses!$J$3:$AM$41)) -> -104071.1 | H20: =-12*SUMPRODUCT((H6=Expenses!$J$2:$AM$2)*(Expenses!$J$3:$AM$41)) -> -107193.23 | I20: =-12*SUMPRODUCT((I6=Expenses!$J$2:$AM$2)*(Expenses!$J$3:$AM$41)) -> -110409.03 | J20: =-12*SUMPRODUCT((J6=Expenses!$J$2:$AM$2)*(Expenses!$J$3:$AM$41)) -> -113721.3 | K20: =-12*SUMPRODUCT((K6=Expenses!$J$2:$AM$2)*(Expenses!$J$3:$AM$41)) -> -117132.94 | ... AG20: =-12*SUMPRODUCT((AG6=Expenses!$J$2:$AM$2)*(Expenses!$J$3:$AM$41)) -> -224438.83
B22: Scenarios | C22: Jarvih Uni | E22: -10000 | F22: -10000 | G22: -10000 | H22: -10000 | I22: -7000 | J22: -7000
C23: Jeci Uni | G23: -10000 | H23: -10000 | I23: -10000 | J23: -10000
C24: Aiah Uni | I24: -10000 | J24: -10000 | K24: -10000 | L24: -10000
C25: Jeran Uni
C26: Japan Trip
C27: Fiji Cruise
C33: Liabilities | D33: =-1*SUMPRODUCT((D6=Repayments!$AZ$12:$CC$12)*(Repayments!$AZ$13:$CC$13)) -> 0 | E33: =-1*SUMPRODUCT((E6=Repayments!$AZ$12:$CC$12)*(Repayments!$AZ$13:$CC$13)) -> -1962440.7 | F33: =-1*SUMPRODUCT((F6=Repayments!$AZ$12:$CC$12)*(Repayments!$AZ$13:$CC$13)) -> -1911882.6 | G33: =-1*SUMPRODUCT((G6=Repayments!$AZ$12:$CC$12)*(Repayments!$AZ$13:$CC$13)) -> -1857771.6 | H33: =-1*SUMPRODUCT((H6=Repayments!$AZ$12:$CC$12)*(Repayments!$AZ$13:$CC$13)) -> -1800219.6 | I33: =-1*SUMPRODUCT((I6=Repayments!$AZ$12:$CC$12)*(Repayments!$AZ$13:$CC$13)) -> -1742007.4 | J33: =-1*SUMPRODUCT((J6=Repayments!$AZ$12:$CC$12)*(Repayments!$AZ$13:$CC$13)) -> -1697595.4 | K33: =-1*SUMPRODUCT((K6=Repayments!$AZ$12:$CC$12)*(Repayments!$AZ$13:$CC$13)) -> -1650026.1 | ... AG33: =-1*SUMPRODUCT((AG6=Repayments!$AZ$12:$CC$12)*(Repayments!$AZ$13:$CC$13)) -> 0
B37: Owner | C37: Type | D37: Sum of 2026 | E37: Sum of 2027 | F37: Sum of 2028 | G37: Sum of 2029 | H37: Sum of 2030 | I37: Sum of 2031 | J37: Sum of 2032 | K37: Sum of 2033 | L37: Sum of 2034 | M37: Sum of 2035 | N37: Sum of 2036 | O37: Sum of 2037 | P37: Sum of 2038 | Q37: Sum of 2039 | R37: Sum of 2040 | S37: Sum of 2041 | T37: Sum of 2042 | U37: Sum of 2043 | V37: Sum of 2045 | W37: Sum of 2044 | X37: Sum of 2046 | Y37: Sum of 2047 | Z37: Sum of 2048 | AA37: Sum of 2049 | AB37: Sum of 2050 | AC37: Sum of 2051 | AD37: Sum of 2052 | AE37: Sum of 2053 | AF37: Sum of 2054 | AG37: Sum of 2055
B38: Jeff | C38: Super | D38: 426700 | E38: 457422.4 | F38: 490356.81 | G38: 525662.5 | H38: 563510.2 | I38: 604082.94 | J38: 647576.91 | K38: 694202.45 | L38: 744185.02 | M38: 797766.35 | N38: 855205.52 | O38: 916780.32 | P38: 982788.5 | Q38: 1053549.3 | R38: 1129404.8 | S38: 1210722 | T38: 1297894 | U38: 1391342.3 | V38: 1598908.3 | W38: 1491519 | X38: 1714029.7 | Y38: 1837439.9 | Z38: 1969735.5 | AA38: 2111556.5 | AB38: 2263588.6 | AC38: 2426566.9 | AD38: 2601279.8 | AE38: 2788571.9 | AF38: 2989349.1 | AG38: 3204582.2
B39: Joint | C39: Property | D39: 1930000 | E39: 2004925 | F39: 2083500.6 | G39: 2165926.3 | H39: 2252412.9 | I39: 2343183.4 | J39: 2438473.6 | K39: 2538533.1 | L39: 2643625.8 | M39: 2754030.6 | N39: 2870043 | O39: 2991975.4 | P39: 3120158.1 | Q39: 3254941 | R39: 3396694.1 | S39: 3545808.8 | T39: 3702699.6 | U39: 3867804.9 | V39: 4224542.4 | W39: 4041588.8 | X39: 4417185.5 | Y39: 4620068.4 | Z39: 4833773.5 | AA39: 5058917.4 | AB39: 5296152.5 | AC39: 5546169.9 | AD39: 5809700.9 | AE39: 6087520 | AF39: 6380447 | AG39: 6689349.9
B40: Magiting | C40: Property | D40: 1200000 | E40: 1272000 | F40: 1348320 | G40: 1429219.2 | H40: 1514972.4 | I40: 1605870.7 | J40: 1702222.9 | K40: 1804356.3 | L40: 1912617.7 | M40: 2027374.8 | N40: 2149017.2 | O40: 2277958.3 | P40: 2414635.8 | Q40: 2559513.9 | R40: 2713084.7 | S40: 2875869.8 | T40: 3048422 | U40: 3231327.3 | V40: 3630719.4 | W40: 3425207 | X40: 3848562.6 | Y40: 4079476.3 | Z40: 4324244.9 | AA40: 4583699.6 | AB40: 4858721.6 | AC40: 5150244.9 | AD40: 5459259.6 | AE40: 5786815.1 | AF40: 6134024 | AG40: 6502065.5

Sheet Income
V1: 60 yrs | AC1: 67 | AK1: 75
B2: Owner | C2: % Own | D2: Type | E2: Name | F2: Annual | G2: Growth | H2: 2026 | I2: =H2+1 -> 2027 | J2: =I2+1 -> 2028 | K2: =J2+1 -> 2029 | L2: =K2+1 -> 2030 | M2: =L2+1 -> 2031 | N2: =M2+1 -> 2032 | O2: =N2+1 -> 2033 | P2: =O2+1 -> 2034 | ... AK2: =AJ2+1 -> 2055
B3: Jeff | C3: 1 | D3: PAYG | E3: PAYG | F3: 190026 | G3: 0.025 | H3: =F3 -> 190026 | I3: =H3*(1+$G3) -> 194776.65 | J3: =I3*(1+$G3) -> 199646.07 | K3: =J3*(1+$G3) -> 204637.22 | L3: =K3*(1+$G3) -> 209753.15 | M3: =L3*(1+$G3) -> 214996.98 | N3: =M3*(1+$G3) -> 220371.9 | O3: =N3*(1+$G3) -> 225881.2 | P3: =O3*(1+$G3) -> 231528.23 | ... AK3: =AJ3*(1+$G3) -> 388870.61
B4: Tin | C4: 1 | D4: PAYG | E4: PAYG | F4: 85000 | G4: 0.025 | H4: =F4 -> 85000 | I4: =H4*(1+$G4) -> 87125 | J4: =I4*(1+$G4) -> 89303.125 | K4: =J4*(1+$G4) -> 91535.703 | L4: =K4*(1+$G4) -> 93824.096 | M4: =L4*(1+$G4) -> 96169.698 | N4: =M4*(1+$G4) -> 98573.941 | O4: =N4*(1+$G4) -> 101038.29 | P4: =O4*(1+$G4) -> 103564.25 | ... AK4: =AJ4*(1+$G4) -> 173944.63
B5: Jeff | C5: 1 | D5: PAYG | E5: Jeff - STVR 2025 | F5: 23287.5 | G5: 0.025 | H5: =F5 -> 23287.5 | I5: =H5*(1+$G5) -> 23869.687 | J5: =I5*(1+$G5) -> 24466.43 | K5: =J5*(1+$G5) -> 25078.09 | L5: =K5*(1+$G5) -> 25705.043 | M5: =L5*(1+$G5) -> 26347.669 | N5: =M5*(1+$G5) -> 27006.36 | O5: =N5*(1+$G5) -> 27681.519 | P5: =O5*(1+$G5) -> 28373.557 | ... AK5: =AJ5*(1+$G5) -> 47655.712
B6: Jeff | C6: 0.5 | D6: Rental Income | E6: Black Diamond | F6: =620*52*C6 -> 16120 | G6: 0.03 | H6: =F6 -> 16120 | I6: =H6*(1+$G6) -> 16603.6 | J6: =I6*(1+$G6) -> 17101.708 | K6: =J6*(1+$G6) -> 17614.759 | L6: =K6*(1+$G6) -> 18143.202 | M6: =L6*(1+$G6) -> 18687.498 | N6: =M6*(1+$G6) -> 19248.123 | O6: =N6*(1+$G6) -> 19825.567 | P6: =O6*(1+$G6) -> 20420.334 | ... AK6: =AJ6*(1+$G6) -> 37987.836
B7: Tin | C7: 0.5 | D7: Rental Income | E7: Black Diamond | F7: =620*52*C7 -> 16120 | G7: 0.03 | H7: =F7 -> 16120 | I7: =H7*(1+$G7) -> 16603.6 | J7: =I7*(1+$G7) -> 17101.708 | K7: =J7*(1+$G7) -> 17614.759 | L7: =K7*(1+$G7) -> 18143.202 | M7: =L7*(1+$G7) -> 18687.498 | N7: =M7*(1+$G7) -> 19248.123 | O7: =N7*(1+$G7) -> 19825.567 | P7: =O7*(1+$G7) -> 20420.334 | ... AK7: =AJ7*(1+$G7) -> 37987.836
B8: Jeff | C8: 0.99 | D8: Rental Income | E8: Wentworthville | F8: =685*52*C8 -> 35263.8 | G8: 0.03 | H8: =F8 -> 35263.8 | I8: =H8*(1+$G8) -> 36321.714 | J8: =I8*(1+$G8) -> 37411.365 | K8: =J8*(1+$G8) -> 38533.706 | L8: =K8*(1+$G8) -> 39689.718 | M8: =L8*(1+$G8) -> 40880.409 | N8: =M8*(1+$G8) -> 42106.821 | O8: =N8*(1+$G8) -> 43370.026 | P8: =O8*(1+$G8) -> 44671.127 | ... AK8: =AJ8*(1+$G8) -> 83101.455
B9: Tin | C9: 0.01 | D9: Rental Income | E9: Wentworthville | F9: =685*52*C9 -> 356.2 | G9: 0.03 | H9: =F9 -> 356.2 | I9: =H9*(1+$G9) -> 366.886 | J9: =I9*(1+$G9) -> 377.89258 | K9: =J9*(1+$G9) -> 389.22936 | L9: =K9*(1+$G9) -> 400.90624 | M9: =L9*(1+$G9) -> 412.93343 | N9: =M9*(1+$G9) -> 425.32143 | O9: =N9*(1+$G9) -> 438.08107 | P9: =O9*(1+$G9) -> 451.2235 | ... AK9: =AJ9*(1+$G9) -> 839.40863
B10: Jeff | C10: 1 | D10: SG Fleet Lease | E10: Carnival | F10: =-52*((436.56+580.21)/2) -> -26436.02 | H10: =$F$10 -> -26436.02 | I10: =$F$10 -> -26436.02 | J10: =$F$10 -> -26436.02 | K10: =$F$10 -> -26436.02 | L10: =$F$10 -> -26436.02
B11: Jeff | C11: -0.5 | D11: Rental Running Costs | E11: Black Diamond | F11: =620*52*C11*0.31 -> -4997.2 | G11: 0.03 | H11: =F11 -> -4997.2 | I11: =H11*(1+$G11) -> -5147.116 | J11: =I11*(1+$G11) -> -5301.5295 | K11: =J11*(1+$G11) -> -5460.5754 | L11: =K11*(1+$G11) -> -5624.3926 | M11: =L11*(1+$G11) -> -5793.1244 | N11: =M11*(1+$G11) -> -5966.9181 | O11: =N11*(1+$G11) -> -6145.9257 | P11: =O11*(1+$G11) -> -6330.3035 | ... AK11: =AJ11*(1+$G11) -> -11776.229
B12: Tin | C12: -0.5 | D12: Rental Running Costs | E12: Black Diamond | F12: =620*52*C12*0.31 -> -4997.2 | G12: 0.03 | H12: =F12 -> -4997.2 | I12: =H12*(1+$G12) -> -5147.116 | J12: =I12*(1+$G12) -> -5301.5295 | K12: =J12*(1+$G12) -> -5460.5754 | L12: =K12*(1+$G12) -> -5624.3926 | M12: =L12*(1+$G12) -> -5793.1244 | N12: =M12*(1+$G12) -> -5966.9181 | O12: =N12*(1+$G12) -> -6145.9257 | P12: =O12*(1+$G12) -> -6330.3035 | ... AK12: =AJ12*(1+$G12) -> -11776.229
B13: Jeff | C13: -0.99 | D13: Rental Running Costs | E13: Wentworthville | F13: =685*52*C13*0.31 -> -10931.778 | G13: 0.03 | H13: =F13 -> -10931.778 | I13: =H13*(1+$G13) -> -11259.731 | J13: =I13*(1+$G13) -> -11597.523 | K13: =J13*(1+$G13) -> -11945.449 | L13: =K13*(1+$G13) -> -12303.812 | M13: =L13*(1+$G13) -> -12672.927 | N13: =M13*(1+$G13) -> -13053.115 | O13: =N13*(1+$G13) -> -13444.708 | P13: =O13*(1+$G13) -> -13848.049 | ... AK13: =AJ13*(1+$G13) -> -25761.451
B14: Tin | C14: -0.01 | D14: Rental Running Costs | E14: Wentworthville | F14: =685*52*C14*0.31 -> -110.422 | G14: 0.03 | H14: =F14 -> -110.422 | I14: =H14*(1+$G14) -> -113.73466 | J14: =I14*(1+$G14) -> -117.1467 | K14: =J14*(1+$G14) -> -120.6611 | L14: =K14*(1+$G14) -> -124.28093 | M14: =L14*(1+$G14) -> -128.00936 | N14: =M14*(1+$G14) -> -131.84964 | O14: =N14*(1+$G14) -> -135.80513 | P14: =O14*(1+$G14) -> -139.87929 | ... AK14: =AJ14*(1+$G14) -> -260.21668
B15: Jeff | C15: -0.5 | D15: Rental Interest Expense | E15: Black Diamond | H15: =Forecast!$F$3*$C15*SUMPRODUCT((H$2=Repayments!$AZ$37:$CC$37)*(Repayments!$AZ$38:$CC$38)) -> 0 | I15: =$C15*SUMPRODUCT((I$2=Repayments!$AZ$37:$CC$37)*(Repayments!$AZ$38:$CC$38)) -> -14060.289 | J15: =$C15*SUMPRODUCT((J$2=Repayments!$AZ$37:$CC$37)*(Repayments!$AZ$38:$CC$38)) -> -13892.39 | K15: =$C15*SUMPRODUCT((K$2=Repayments!$AZ$37:$CC$37)*(Repayments!$AZ$38:$CC$38)) -> -13636.435 | L15: =$C15*SUMPRODUCT((L$2=Repayments!$AZ$37:$CC$37)*(Repayments!$AZ$38:$CC$38)) -> -13402.86 | M15: =$C15*SUMPRODUCT((M$2=Repayments!$AZ$37:$CC$37)*(Repayments!$AZ$38:$CC$38)) -> -13154.41 | N15: =$C15*SUMPRODUCT((N$2=Repayments!$AZ$37:$CC$37)*(Repayments!$AZ$38:$CC$38)) -> -12926.102 | O15: =$C15*SUMPRODUCT((O$2=Repayments!$AZ$37:$CC$37)*(Repayments!$AZ$38:$CC$38)) -> -12611.323 | P15: =$C15*SUMPRODUCT((P$2=Repayments!$AZ$37:$CC$37)*(Repayments!$AZ$38:$CC$38)) -> -12312.463 | ... AK15: =$C15*SUMPRODUCT((AK$2=Repayments!$AZ$37:$CC$37)*(Repayments!$AZ$38:$CC$38)) -> 0
B16: Tin | C16: -0.5 | D16: Rental Interest Expense | E16: Black Diamond | H16: =Forecast!$F$3*$C16*SUMPRODUCT((H$2=Repayments!$AZ$37:$CC$37)*(Repayments!$AZ$38:$CC$38)) -> 0 | I16: =$C16*SUMPRODUCT((I$2=Repayments!$AZ$37:$CC$37)*(Repayments!$AZ$38:$CC$38)) -> -14060.289 | J16: =$C16*SUMPRODUCT((J$2=Repayments!$AZ$37:$CC$37)*(Repayments!$AZ$38:$CC$38)) -> -13892.39 | K16: =$C16*SUMPRODUCT((K$2=Repayments!$AZ$37:$CC$37)*(Repayments!$AZ$38:$CC$38)) -> -13636.435 | L16: =$C16*SUMPRODUCT((L$2=Repayments!$AZ$37:$CC$37)*(Repayments!$AZ$38:$CC$38)) -> -13402.86 | M16: =$C16*SUMPRODUCT((M$2=Repayments!$AZ$37:$CC$37)*(Repayments!$AZ$38:$CC$38)) -> -13154.41 | N16: =$C16*SUMPRODUCT((N$2=Repayments!$AZ$37:$CC$37)*(Repayments!$AZ$38:$CC$38)) -> -12926.102 | O16: =$C16*SUMPRODUCT((O$2=Repayments!$AZ$37:$CC$37)*(Repayments!$AZ$38:$CC$38)) -> -12611.323 | P16: =$C16*SUMPRODUCT((P$2=Repayments!$AZ$37:$CC$37)*(Repayments!$AZ$38:$CC$38)) -> -12312.463 | ... AK16: =$C16*SUMPRODUCT((AK$2=Repayments!$AZ$37:$CC$37)*(Repayments!$AZ$38:$CC$38)) -> 0
B17: Jeff | C17: -0.99 | D17: Rental Interest Expense | E17: Wentworthville | H17: =Forecast!$F$3*$C17*SUMPRODUCT((H$2=Repayments!$AZ$31:$CC$31)*(Repayments!$AZ$32:$CC$32)) -> 0 | I17: =$C17*SUMPRODUCT((I$2=Repayments!$AZ$31:$CC$31)*(Repayments!$AZ$32:$CC$32)) -> -32834.778 | J17: =$C17*SUMPRODUCT((J$2=Repayments!$AZ$31:$CC$31)*(Repayments!$AZ$32:$CC$32)) -> -32154.646 | K17: =$C17*SUMPRODUCT((K$2=Repayments!$AZ$31:$CC$31)*(Repayments!$AZ$32:$CC$32)) -> -31252.349 | L17: =$C17*SUMPRODUCT((L$2=Repayments!$AZ$31:$CC$31)*(Repayments!$AZ$32:$CC$32)) -> -30382.012 | M17: =$C17*SUMPRODUCT((M$2=Repayments!$AZ$31:$CC$31)*(Repayments!$AZ$32:$CC$32)) -> -29456.247 | N17: =$C17*SUMPRODUCT((N$2=Repayments!$AZ$31:$CC$31)*(Repayments!$AZ$32:$CC$32)) -> -28550.818 | O17: =$C17*SUMPRODUCT((O$2=Repayments!$AZ$31:$CC$31)*(Repayments!$AZ$32:$CC$32)) -> -27429.136 | P17: =$C17*SUMPRODUCT((P$2=Repayments!$AZ$31:$CC$31)*(Repayments!$AZ$32:$CC$32)) -> -26315.313 | ... AK17: =$C17*SUMPRODUCT((AK$2=Repayments!$AZ$31:$CC$31)*(Repayments!$AZ$32:$CC$32)) -> 0
B18: Tin | C18: -0.01 | D18: Rental Interest Expense | E18: Wentworthville | H18: =Forecast!$F$3*$C18*SUMPRODUCT((H$2=Repayments!$AZ$31:$CC$31)*(Repayments!$AZ$32:$CC$32)) -> 0 | I18: =$C18*SUMPRODUCT((I$2=Repayments!$AZ$31:$CC$31)*(Repayments!$AZ$32:$CC$32)) -> -331.66442 | J18: =$C18*SUMPRODUCT((J$2=Repayments!$AZ$31:$CC$31)*(Repayments!$AZ$32:$CC$32)) -> -324.79441 | K18: =$C18*SUMPRODUCT((K$2=Repayments!$AZ$31:$CC$31)*(Repayments!$AZ$32:$CC$32)) -> -315.68029 | L18: =$C18*SUMPRODUCT((L$2=Repayments!$AZ$31:$CC$31)*(Repayments!$AZ$32:$CC$32)) -> -306.88901 | M18: =$C18*SUMPRODUCT((M$2=Repayments!$AZ$31:$CC$31)*(Repayments!$AZ$32:$CC$32)) -> -297.53785 | N18: =$C18*SUMPRODUCT((N$2=Repayments!$AZ$31:$CC$31)*(Repayments!$AZ$32:$CC$32)) -> -288.39211 | O18: =$C18*SUMPRODUCT((O$2=Repayments!$AZ$31:$CC$31)*(Repayments!$AZ$32:$CC$32)) -> -277.06198 | P18: =$C18*SUMPRODUCT((P$2=Repayments!$AZ$31:$CC$31)*(Repayments!$AZ$32:$CC$32)) -> -265.81124 | ... AK18: =$C18*SUMPRODUCT((AK$2=Repayments!$AZ$31:$CC$31)*(Repayments!$AZ$32:$CC$32)) -> 0
B19: Magiting | C19: 1 | D19: Rental Income | E19: Shane St (Main) | F19: =700*52*C19 -> 36400 | G19: 0.03 | H19: =F19 -> 36400 | I19: =H19*(1+$G19) -> 37492 | J19: =I19*(1+$G19) -> 38616.76 | K19: =J19*(1+$G19) -> 39775.263 | L19: =K19*(1+$G19) -> 40968.521 | M19: =L19*(1+$G19) -> 42197.576 | N19: =M19*(1+$G19) -> 43463.504 | O19: =N19*(1+$G19) -> 44767.409 | P19: =O19*(1+$G19) -> 46110.431 | ... AK19: =AJ19*(1+$G19) -> 85778.984
B20: Magiting | C20: 1 | D20: Rental Income | E20: Shane St (Granny) | F20: =460*52*C20 -> 23920 | G20: 0.03 | H20: =F20 -> 23920 | I20: =H20*(1+$G20) -> 24637.6 | J20: =I20*(1+$G20) -> 25376.728 | K20: =J20*(1+$G20) -> 26138.03 | L20: =K20*(1+$G20) -> 26922.171 | M20: =L20*(1+$G20) -> 27729.836 | N20: =M20*(1+$G20) -> 28561.731 | O20: =N20*(1+$G20) -> 29418.583 | P20: =O20*(1+$G20) -> 30301.14 | ... AK20: =AJ20*(1+$G20) -> 56369.047
B21: Hernandez Accountants | C21: 1 | D21: Self Employed Income | E21: F1 Tax - Company Income | F21: =40000*C21 -> 40000 | G21: 0.05 | H21: =F21 -> 40000 | I21: =H21*(1+$G21) -> 42000 | J21: =I21*(1+$G21) -> 44100 | K21: =J21*(1+$G21) -> 46305 | L21: =K21*(1+$G21) -> 48620.25 | M21: =L21*(1+$G21) -> 51051.263 | N21: =M21*(1+$G21) -> 53603.826 | O21: =N21*(1+$G21) -> 56284.017 | P21: =O21*(1+$G21) -> 59098.218 | ... AK21: =AJ21*(1+$G21) -> 164645.42
B22: Hernandez Accountants | C22: 0.33 | D22: Self Employed Income | E22: Gravitax - Company Income | F22: =40000*C22 -> 13200 | G22: 0.05 | H22: =F22 -> 13200 | I22: =H22*(1+$G22) -> 13860 | J22: =I22*(1+$G22) -> 14553 | K22: =J22*(1+$G22) -> 15280.65 | L22: =K22*(1+$G22) -> 16044.683 | M22: =L22*(1+$G22) -> 16846.917 | N22: =M22*(1+$G22) -> 17689.262 | O22: =N22*(1+$G22) -> 18573.726 | P22: =O22*(1+$G22) -> 19502.412 | ... AK22: =AJ22*(1+$G22) -> 54332.99
B23: Magiting | C23: -1 | D23: Rental Running Costs | E23: Shane St (Main) | F23: =700*52*C23*0.31 -> -11284 | G23: 0.03 | H23: =F23 -> -11284 | I23: =H23*(1+$G23) -> -11622.52 | J23: =I23*(1+$G23) -> -11971.196 | K23: =J23*(1+$G23) -> -12330.331 | L23: =K23*(1+$G23) -> -12700.241 | M23: =L23*(1+$G23) -> -13081.249 | N23: =M23*(1+$G23) -> -13473.686 | O23: =N23*(1+$G23) -> -13877.897 | P23: =O23*(1+$G23) -> -14294.234 | ... AK23: =AJ23*(1+$G23) -> -26591.485
B24: Magiting | C24: -1 | D24: Rental Running Costs | E24: Shane St (Granny) | F24: =460*52*C24*0.31 -> -7415.2 | G24: 0.03 | H24: =F24 -> -7415.2 | I24: =H24*(1+$G24) -> -7637.656 | J24: =I24*(1+$G24) -> -7866.7857 | K24: =J24*(1+$G24) -> -8102.7893 | L24: =K24*(1+$G24) -> -8345.8729 | M24: =L24*(1+$G24) -> -8596.2491 | N24: =M24*(1+$G24) -> -8854.1366 | O24: =N24*(1+$G24) -> -9119.7607 | P24: =O24*(1+$G24) -> -9393.3535 | ... AK24: =AJ24*(1+$G24) -> -17474.405
B25: Magiting | C25: -1 | D25: Rental Interest Expense | E25: Shane St | H25: =$C25*SUMPRODUCT((H$2=Repayments!$AZ$43:$CC$43)*(Repayments!$AZ$44:$CC$44)) -> 0 | I25: =$C25*SUMPRODUCT((I$2=Repayments!$AZ$43:$CC$43)*(Repayments!$AZ$44:$CC$44)) -> -58439.737 | J25: =$C25*SUMPRODUCT((J$2=Repayments!$AZ$43:$CC$43)*(Repayments!$AZ$44:$CC$44)) -> -57683.85 | K25: =$C25*SUMPRODUCT((K$2=Repayments!$AZ$43:$CC$43)*(Repayments!$AZ$44:$CC$44)) -> -56557.368 | L25: =$C25*SUMPRODUCT((L$2=Repayments!$AZ$43:$CC$43)*(Repayments!$AZ$44:$CC$44)) -> -55518.141 | M25: =$C25*SUMPRODUCT((M$2=Repayments!$AZ$43:$CC$43)*(Repayments!$AZ$44:$CC$44)) -> -54411.189 | N25: =$C25*SUMPRODUCT((N$2=Repayments!$AZ$43:$CC$43)*(Repayments!$AZ$44:$CC$44)) -> -53380.661 | O25: =$C25*SUMPRODUCT((O$2=Repayments!$AZ$43:$CC$43)*(Repayments!$AZ$44:$CC$44)) -> -51985.849 | ... AK25: =$C25*SUMPRODUCT((AK$2=Repayments!$AZ$43:$CC$43)*(Repayments!$AZ$44:$CC$44)) -> 0

Sheet Assets
V1: 60 yrs | AC1: 67 | AK1: 75
B2: Owner | C2: Type | D2: Name | E2: Acquire Value | F2: Current Value | G2: Value Growth | H2: 2026 | I2: =H2+1 -> 2027 | J2: =I2+1 -> 2028 | K2: =J2+1 -> 2029 | L2: =K2+1 -> 2030 | M2: =L2+1 -> 2031 | N2: =M2+1 -> 2032 | O2: =N2+1 -> 2033 | P2: =O2+1 -> 2034 | ... AK2: =AJ2+1 -> 2055
B3: Jeff | C3: Super | D3: Mercer | F3: 213500 | G3: 0.072 | H3: =F3 -> 213500 | I3: =H3*(1+$G3) -> 228872 | J3: =I3*(1+$G3) -> 245350.78 | K3: =J3*(1+$G3) -> 263016.04 | L3: =K3*(1+$G3) -> 281953.2 | M3: =L3*(1+$G3) -> 302253.83 | N3: =M3*(1+$G3) -> 324016.1 | O3: =N3*(1+$G3) -> 347345.26 | P3: =O3*(1+$G3) -> 372354.12 | ... AK3: =AJ3*(1+$G3) -> 1603417.6
B4: Jeff | C4: Super | D4: ART | F4: 213200 | G4: 0.072 | H4: =F4 -> 213200 | I4: =H4*(1+$G4) -> 228550.4 | J4: =I4*(1+$G4) -> 245006.03 | K4: =J4*(1+$G4) -> 262646.46 | L4: =K4*(1+$G4) -> 281557.01 | M4: =L4*(1+$G4) -> 301829.11 | N4: =M4*(1+$G4) -> 323560.81 | O4: =N4*(1+$G4) -> 346857.19 | P4: =O4*(1+$G4) -> 371830.9 | ... AK4: =AJ4*(1+$G4) -> 1601164.6
B5: Joint | C5: SMSF | F5: 10888 | G5: 0.06 | H5: =F5 -> 10888 | I5: =H5*(1+$G5) -> 11541.28 | J5: =I5*(1+$G5) -> 12233.757 | K5: =J5*(1+$G5) -> 12967.782 | L5: =K5*(1+$G5) -> 13745.849 | M5: =L5*(1+$G5) -> 14570.6 | N5: =M5*(1+$G5) -> 15444.836 | O5: =N5*(1+$G5) -> 16371.526 | P5: =O5*(1+$G5) -> 17353.818 | ... AK5: =AJ5*(1+$G5) -> 58995.407
B6: Joint | C6: Property | D6: 4/10 Abraham Street, Rooty Hill, New South Wales, 2766 | E6: =405000+17000+1500+1000 -> 424500 | F6: 850000 | G6: 0.06 | H6: =F6 -> 850000 | I6: =H6*(1+$G6) -> 901000 | J6: =I6*(1+$G6) -> 955060 | K6: =J6*(1+$G6) -> 1012363.6 | L6: =K6*(1+$G6) -> 1073105.4 | M6: =L6*(1+$G6) -> 1137491.7 | N6: =M6*(1+$G6) -> 1205741.2 | O6: =N6*(1+$G6) -> 1278085.7 | P6: =O6*(1+$G6) -> 1354770.9 | ... AK6: =AJ6*(1+$G6) -> 4605629.7
B7: Joint | C7: Property | D7: 4/304 Great Western Highway Way, Wentworthville, New South Wales, 2145 | E7: =590000+24000+2000+1500 -> 617500 | F7: 565000 | G7: 0.015 | H7: =F7 -> 565000 | I7: =H7*(1+$G7) -> 573475 | J7: =I7*(1+$G7) -> 582077.12 | K7: =J7*(1+$G7) -> 590808.28 | L7: =K7*(1+$G7) -> 599670.41 | M7: =L7*(1+$G7) -> 608665.46 | N7: =M7*(1+$G7) -> 617795.44 | O7: =N7*(1+$G7) -> 627062.38 | P7: =O7*(1+$G7) -> 636468.31 | ... AK7: =AJ7*(1+$G7) -> 870088.99
B8: Joint | C8: Property | D8: 403/335 Anketell Street, Greenway, Australian Capital Territory, 2900 | E8: =489000+11500+2500+3000 -> 506000 | F8: 515000 | G8: 0.03 | H8: =F8 -> 515000 | I8: =H8*(1+$G8) -> 530450 | J8: =I8*(1+$G8) -> 546363.5 | K8: =J8*(1+$G8) -> 562754.41 | L8: =K8*(1+$G8) -> 579637.04 | M8: =L8*(1+$G8) -> 597026.15 | N8: =M8*(1+$G8) -> 614936.93 | O8: =N8*(1+$G8) -> 633385.04 | P8: =O8*(1+$G8) -> 652386.59 | ... AK8: =AJ8*(1+$G8) -> 1213631.2
B9: Magiting | C9: Property | D9: 8 Shane Street, Colyton, New South Wales, 2760 | E9: =920000+37000+3000+1500 -> 961500 | F9: 1200000 | G9: 0.06 | H9: =F9 -> 1200000 | I9: =H9*(1+$G9) -> 1272000 | J9: =I9*(1+$G9) -> 1348320 | K9: =J9*(1+$G9) -> 1429219.2 | L9: =K9*(1+$G9) -> 1514972.4 | M9: =L9*(1+$G9) -> 1605870.7 | N9: =M9*(1+$G9) -> 1702222.9 | O9: =N9*(1+$G9) -> 1804356.3 | P9: =O9*(1+$G9) -> 1912617.7 | ... AK9: =AJ9*(1+$G9) -> 6502065.5
B10: Jeff | C10: Bank Account | D10: Jeff Offset WW xx9474 | F10: 38331.49
B11: Joint | C11: Bank Account | D11: RH Offset xx5182 | F11: 60679.23
B12: Joint | C12: Bank Account | D12: RH Offset xx5190 | F12: 21747.04
B13: Tin | C13: Bank Account | D13: Tin - Cash xx5865 | F13: 936.68
B14: Tin | C14: Bank Account | D14: Tin - Rent and Salary xx1575 | F14: 3323
B15: Joint | C15: Bank Account | D15: WW Offset xx6867 | F15: 47864.37
B16: Joint | C16: Bank Account | D16: BD Offset xx1893 | F16: 36081.46
B17: Magiting | C17: Bank Account | D17: Magiting Inv Trustee xx2243 | F17: 979.42
B18: Jeff | C18: Shares | D18: WBC Shares (Tradeable) | F18: 6617
B19: Jeff | C19: Shares | D19: CBA Shares (ESS) | F19: 30123
B20: Jeff | C20: Shares | D20: CBA Shares (Renounceable Rights Allotment) | F20: 325
B21: Joint | C21: Managed Fund | D21: Futurity / ASG Education Bond Fund xx3689 | F21: 51148.45

Sheet Liabilities
A1: Snapshot as of June 30, 2026
A2: Property | B2: Owner | C2: Type | D2: Name | E2: Owing | F2: Limit | G2: Interest Rate | H2: Monthly Repayment
A3: 4/10 Abraham Street, Rooty Hill, New South Wales, 2766 | B3: Jeffrey Hernandez, Cristina Hernandez | C3: Property Loan | D3: RH Fixed Loan xx5182 | E3: 60679.23 | F3: 343000 | G3: 0.0603 | H3: 1469
A4: 4/10 Abraham Street, Rooty Hill, New South Wales, 2766 | B4: Jeffrey Hernandez, Cristina Hernandez | C4: Property Loan | D4: RH Loan x5190 | E4: 21747.04 | F4: 29000 | G4: 0.0603 | H4: 169
A5: 4/10 Abraham Street, Rooty Hill, New South Wales, 2766 | B5: Jeffrey Hernandez, Cristina Hernandez | C5: Property Loan | D5: WW RH xx4508 Top-up | E5: 22942.48 | F5: 30000 | G5: 0.0612 | H5: 167
A6: 4/10 Abraham Street, Rooty Hill, New South Wales, 2766 | B6: Jeffrey Hernandez, Cristina Hernandez | C6: Property Loan | D6: BD RH xx1893 Top-up | E6: 35595.46 | F6: 39500 | G6: 0.0619 | H6: 243
A7: 4/10 Abraham Street, Rooty Hill, New South Wales, 2766 | B7: Cristina Hernandez, Jeffrey Hernandez | C7: Property Loan | D7: WW RH xx6867 Top-up | E7: 98748.05 | F7: 113500 | G7: 0.0619 | H7: 690
A8: 4/10 Abraham Street, Rooty Hill, New South Wales, 2766 | B8: Jeffrey Hernandez, Cristina Hernandez | C8: Property Loan | D8: SH RH xx9773 Top-up | E8: 216411.23 | F8: 224000 | G8: 0.0608 | H8: 1340
A9: 403/335 Anketell Street, Greenway, Australian Capital Territory, 2900 | B9: Jeffrey Hernandez, Cristina Hernandez | C9: Property Loan | D9: BD xx4741 | E9: 421568.8 | F9: 440500 | G9: 0.0619 | H9: 2641
A10: 4/304 Great Western Highway Way, Wentworthville, New South Wales, 2145 | B10: Jeffrey Hernandez, Cristina Hernandez | C10: Property Loan | D10: WW xx9474 | E10: 419560.91 | F10: 472000 | G10: 0.0619 | H10: 2924
A11: 8 Shane Street, Colyton, New South Wales, 2760 | B11: Magiting Investments Pty Ltd | C11: Property Loan | D11: SH xx4901 | E11: 713040.78 | F11: 735787 | G11: 0.0633 | H11: 4702
C12: Lease | D12: SG Fleet | E12: 74171 | F12: 0 | G12: 0.0613 | H12: 1303
B13: Jeffrey Hernandez, Cristina Hernandez | C13: Credit Card or Store Card | D13: CBA Ultimate Awards | E13: 0 | F13: 12000 | G13: 0 | H13: 0

Sheet Expenses
X1: 60 yrs | AE1: 67 | AM1: 75
B2: Type | C2: Description | D2: Amount | E2: Frequency | F2: Monthly Total | J2: 2026 | K2: =J2+1 -> 2027 | L2: =K2+1 -> 2028 | M2: =L2+1 -> 2029 | N2: =M2+1 -> 2030 | O2: =N2+1 -> 2031 | P2: =O2+1 -> 2032 | Q2: =P2+1 -> 2033 | R2: =Q2+1 -> 2034 | ... AM2: =AL2+1 -> 2055
B3: Food Expenses | J3: =F3 -> 0 | K3: =J3*(1+Forecast!$F$2) -> 0 | L3: =K3*(1+Forecast!$F$2) -> 0 | M3: =L3*(1+Forecast!$F$2) -> 0 | N3: =M3*(1+Forecast!$F$2) -> 0 | O3: =N3*(1+Forecast!$F$2) -> 0 | P3: =O3*(1+Forecast!$F$2) -> 0 | Q3: =P3*(1+Forecast!$F$2) -> 0 | R3: =Q3*(1+Forecast!$F$2) -> 0 | ... AM3: =AL3*(1+Forecast!$F$2) -> 0
C4: Food & Supermarket | D4: 580 | E4: Weekly | F4: 2513.33 | J4: =F4 -> 2513.33 | K4: =J4*(1+Forecast!$F$2) -> 2588.7299 | L4: =K4*(1+Forecast!$F$2) -> 2666.3918 | M4: =L4*(1+Forecast!$F$2) -> 2746.3836 | N4: =M4*(1+Forecast!$F$2) -> 2828.7751 | O4: =N4*(1+Forecast!$F$2) -> 2913.6383 | P4: =O4*(1+Forecast!$F$2) -> 3001.0475 | Q4: =P4*(1+Forecast!$F$2) -> 3091.0789 | R4: =Q4*(1+Forecast!$F$2) -> 3183.8112 | ... AM4: =AL4*(1+Forecast!$F$2) -> 5922.8268
C5: Coffees, lunches & takeaways | D5: 560 | E5: Monthly | F5: 560 | J5: =F5 -> 560 | K5: =J5*(1+Forecast!$F$2) -> 576.8 | L5: =K5*(1+Forecast!$F$2) -> 594.104 | M5: =L5*(1+Forecast!$F$2) -> 611.92712 | N5: =M5*(1+Forecast!$F$2) -> 630.28493 | O5: =N5*(1+Forecast!$F$2) -> 649.19348 | P5: =O5*(1+Forecast!$F$2) -> 668.66929 | Q5: =P5*(1+Forecast!$F$2) -> 688.72936 | R5: =Q5*(1+Forecast!$F$2) -> 709.39125 | ... AM5: =AL5*(1+Forecast!$F$2) -> 1319.6767
C6: Cigarettes & alcohol | D6: 0 | E6: 0 | F6: 0 | J6: =F6 -> 0 | K6: =J6*(1+Forecast!$F$2) -> 0 | L6: =K6*(1+Forecast!$F$2) -> 0 | M6: =L6*(1+Forecast!$F$2) -> 0 | N6: =M6*(1+Forecast!$F$2) -> 0 | O6: =N6*(1+Forecast!$F$2) -> 0 | P6: =O6*(1+Forecast!$F$2) -> 0 | Q6: =P6*(1+Forecast!$F$2) -> 0 | R6: =Q6*(1+Forecast!$F$2) -> 0 | ... AM6: =AL6*(1+Forecast!$F$2) -> 0
B7: Discretionary Expenses | J7: =F7 -> 0 | K7: =J7*(1+Forecast!$F$2) -> 0 | L7: =K7*(1+Forecast!$F$2) -> 0 | M7: =L7*(1+Forecast!$F$2) -> 0 | N7: =M7*(1+Forecast!$F$2) -> 0 | O7: =N7*(1+Forecast!$F$2) -> 0 | P7: =O7*(1+Forecast!$F$2) -> 0 | Q7: =P7*(1+Forecast!$F$2) -> 0 | R7: =Q7*(1+Forecast!$F$2) -> 0 | ... AM7: =AL7*(1+Forecast!$F$2) -> 0
C8: Entertainment | D8: 500 | E8: Annually | F8: 41.67 | J8: =F8 -> 41.67 | K8: =J8*(1+Forecast!$F$2) -> 42.9201 | L8: =K8*(1+Forecast!$F$2) -> 44.207703 | M8: =L8*(1+Forecast!$F$2) -> 45.533934 | N8: =M8*(1+Forecast!$F$2) -> 46.899952 | O8: =N8*(1+Forecast!$F$2) -> 48.306951 | P8: =O8*(1+Forecast!$F$2) -> 49.756159 | Q8: =P8*(1+Forecast!$F$2) -> 51.248844 | R8: =Q8*(1+Forecast!$F$2) -> 52.786309 | ... AM8: =AL8*(1+Forecast!$F$2) -> 98.198085
C9: Domestic holidays | D9: 8500 | E9: Annually | F9: 708.33 | J9: =F9 -> 708.33 | K9: =J9*(1+Forecast!$F$2) -> 729.5799 | L9: =K9*(1+Forecast!$F$2) -> 751.4673 | M9: =L9*(1+Forecast!$F$2) -> 774.01132 | N9: =M9*(1+Forecast!$F$2) -> 797.23166 | O9: =N9*(1+Forecast!$F$2) -> 821.14861 | P9: =O9*(1+Forecast!$F$2) -> 845.78306 | Q9: =P9*(1+Forecast!$F$2) -> 871.15656 | R9: =Q9*(1+Forecast!$F$2) -> 897.29125 | ... AM9: =AL9*(1+Forecast!$F$2) -> 1669.226
C10: Clothing, shoes & accessories | D10: 0 | E10: Annually | F10: 0 | J10: =F10 -> 0 | K10: =J10*(1+Forecast!$F$2) -> 0 | L10: =K10*(1+Forecast!$F$2) -> 0 | M10: =L10*(1+Forecast!$F$2) -> 0 | N10: =M10*(1+Forecast!$F$2) -> 0 | O10: =N10*(1+Forecast!$F$2) -> 0 | P10: =O10*(1+Forecast!$F$2) -> 0 | Q10: =P10*(1+Forecast!$F$2) -> 0 | R10: =Q10*(1+Forecast!$F$2) -> 0 | ... AM10: =AL10*(1+Forecast!$F$2) -> 0
C11: Hairdressing & grooming | D11: 800 | E11: Annually | F11: 66.67 | J11: =F11 -> 66.67 | K11: =J11*(1+Forecast!$F$2) -> 68.6701 | L11: =K11*(1+Forecast!$F$2) -> 70.730203 | M11: =L11*(1+Forecast!$F$2) -> 72.852109 | N11: =M11*(1+Forecast!$F$2) -> 75.037672 | O11: =N11*(1+Forecast!$F$2) -> 77.288803 | P11: =O11*(1+Forecast!$F$2) -> 79.607467 | Q11: =P11*(1+Forecast!$F$2) -> 81.995691 | R11: =Q11*(1+Forecast!$F$2) -> 84.455561 | ... AM11: =AL11*(1+Forecast!$F$2) -> 157.11222
C12: Phone, Internet & pay TV | D12: 240 | E12: Monthly | F12: 240 | J12: =F12 -> 240 | K12: =J12*(1+Forecast!$F$2) -> 247.2 | L12: =K12*(1+Forecast!$F$2) -> 254.616 | M12: =L12*(1+Forecast!$F$2) -> 262.25448 | N12: =M12*(1+Forecast!$F$2) -> 270.12211 | O12: =N12*(1+Forecast!$F$2) -> 278.22578 | P12: =O12*(1+Forecast!$F$2) -> 286.57255 | Q12: =P12*(1+Forecast!$F$2) -> 295.16973 | R12: =Q12*(1+Forecast!$F$2) -> 304.02482 | ... AM12: =AL12*(1+Forecast!$F$2) -> 565.57572
C13: Media streaming & subscription services | D13: 20 | E13: Monthly | F13: 20 | J13: =F13 -> 20 | K13: =J13*(1+Forecast!$F$2) -> 20.6 | L13: =K13*(1+Forecast!$F$2) -> 21.218 | M13: =L13*(1+Forecast!$F$2) -> 21.85454 | N13: =M13*(1+Forecast!$F$2) -> 22.510176 | O13: =N13*(1+Forecast!$F$2) -> 23.185481 | P13: =O13*(1+Forecast!$F$2) -> 23.881046 | Q13: =P13*(1+Forecast!$F$2) -> 24.597477 | R13: =Q13*(1+Forecast!$F$2) -> 25.335402 | ... AM13: =AL13*(1+Forecast!$F$2) -> 47.13131
C14: Gifts & celebrations | D14: 1000 | E14: Annually | F14: 83.33 | J14: =F14 -> 83.33 | K14: =J14*(1+Forecast!$F$2) -> 85.8299 | L14: =K14*(1+Forecast!$F$2) -> 88.404797 | M14: =L14*(1+Forecast!$F$2) -> 91.056941 | N14: =M14*(1+Forecast!$F$2) -> 93.788649 | O14: =N14*(1+Forecast!$F$2) -> 96.602309 | P14: =O14*(1+Forecast!$F$2) -> 99.500378 | Q14: =P14*(1+Forecast!$F$2) -> 102.48539 | R14: =Q14*(1+Forecast!$F$2) -> 105.55995 | ... AM14: =AL14*(1+Forecast!$F$2) -> 196.3726
C15: Other discretionary expenses | D15: 0 | E15: Annually | F15: 0 | J15: =F15 -> 0 | K15: =J15*(1+Forecast!$F$2) -> 0 | L15: =K15*(1+Forecast!$F$2) -> 0 | M15: =L15*(1+Forecast!$F$2) -> 0 | N15: =M15*(1+Forecast!$F$2) -> 0 | O15: =N15*(1+Forecast!$F$2) -> 0 | P15: =O15*(1+Forecast!$F$2) -> 0 | Q15: =P15*(1+Forecast!$F$2) -> 0 | R15: =Q15*(1+Forecast!$F$2) -> 0 | ... AM15: =AL15*(1+Forecast!$F$2) -> 0
C16: Pets | D16: 0 | E16: 0 | F16: 0 | J16: =F16 -> 0 | K16: =J16*(1+Forecast!$F$2) -> 0 | L16: =K16*(1+Forecast!$F$2) -> 0 | M16: =L16*(1+Forecast!$F$2) -> 0 | N16: =M16*(1+Forecast!$F$2) -> 0 | O16: =N16*(1+Forecast!$F$2) -> 0 | P16: =O16*(1+Forecast!$F$2) -> 0 | Q16: =P16*(1+Forecast!$F$2) -> 0 | R16: =Q16*(1+Forecast!$F$2) -> 0 | ... AM16: =AL16*(1+Forecast!$F$2) -> 0
B17: Children and Education Expenses | J17: =F17 -> 0 | K17: =J17*(1+Forecast!$F$2) -> 0 | L17: =K17*(1+Forecast!$F$2) -> 0 | M17: =L17*(1+Forecast!$F$2) -> 0 | N17: =M17*(1+Forecast!$F$2) -> 0 | O17: =N17*(1+Forecast!$F$2) -> 0 | P17: =O17*(1+Forecast!$F$2) -> 0 | Q17: =P17*(1+Forecast!$F$2) -> 0 | R17: =Q17*(1+Forecast!$F$2) -> 0 | ... AM17: =AL17*(1+Forecast!$F$2) -> 0
C18: Public education costs | D18: 1600 | E18: Annually | F18: 133.33 | J18: =F18 -> 133.33 | K18: =J18*(1+Forecast!$F$2) -> 137.3299 | L18: =K18*(1+Forecast!$F$2) -> 141.4498 | M18: =L18*(1+Forecast!$F$2) -> 145.69329 | N18: =M18*(1+Forecast!$F$2) -> 150.06409 | O18: =N18*(1+Forecast!$F$2) -> 154.56601 | P18: =O18*(1+Forecast!$F$2) -> 159.20299 | Q18: =P18*(1+Forecast!$F$2) -> 163.97908 | R18: =Q18*(1+Forecast!$F$2) -> 168.89845 | ... AM18: =AL18*(1+Forecast!$F$2) -> 314.20088
C19: Private education costs | D19: 15640 | E19: Annually | F19: 1303.33 | J19: =F19 -> 1303.33 | K19: =J19*(1+Forecast!$F$2) -> 1342.4299 | L19: =K19*(1+Forecast!$F$2) -> 1382.7028 | M19: =L19*(1+Forecast!$F$2) -> 1424.1839 | N19: =M19*(1+Forecast!$F$2) -> 1466.9094 | O19: =N19*(1+Forecast!$F$2) -> 1510.9167 | P19: =O19*(1+Forecast!$F$2) -> 1556.2442 | Q19: =P19*(1+Forecast!$F$2) -> 1602.9315 | R19: =Q19*(1+Forecast!$F$2) -> 1651.0195 | ... AM19: =AL19*(1+Forecast!$F$2) -> 3071.3825
C20: Tertiary & vocational education | D20: 820 | E20: Monthly | F20: 820 | J20: =F20 -> 820 | K20: =J20*(1+Forecast!$F$2) -> 844.6 | L20: =K20*(1+Forecast!$F$2) -> 869.938 | M20: =L20*(1+Forecast!$F$2) -> 896.03614 | N20: =M20*(1+Forecast!$F$2) -> 922.91722 | O20: =N20*(1+Forecast!$F$2) -> 950.60474 | P20: =O20*(1+Forecast!$F$2) -> 979.12288 | Q20: =P20*(1+Forecast!$F$2) -> 1008.4966 | R20: =Q20*(1+Forecast!$F$2) -> 1038.7515 | ... AM20: =AL20*(1+Forecast!$F$2) -> 1932.3837
C21: Childcare | D21: 0 | E21: 0 | F21: 0 | J21: =F21 -> 0 | K21: =J21*(1+Forecast!$F$2) -> 0 | L21: =K21*(1+Forecast!$F$2) -> 0 | M21: =L21*(1+Forecast!$F$2) -> 0 | N21: =M21*(1+Forecast!$F$2) -> 0 | O21: =N21*(1+Forecast!$F$2) -> 0 | P21: =O21*(1+Forecast!$F$2) -> 0 | Q21: =P21*(1+Forecast!$F$2) -> 0 | R21: =Q21*(1+Forecast!$F$2) -> 0 | ... AM21: =AL21*(1+Forecast!$F$2) -> 0
B22: Health and Wellness Expenses | J22: =F22 -> 0 | K22: =J22*(1+Forecast!$F$2) -> 0 | L22: =K22*(1+Forecast!$F$2) -> 0 | M22: =L22*(1+Forecast!$F$2) -> 0 | N22: =M22*(1+Forecast!$F$2) -> 0 | O22: =N22*(1+Forecast!$F$2) -> 0 | P22: =O22*(1+Forecast!$F$2) -> 0 | Q22: =P22*(1+Forecast!$F$2) -> 0 | R22: =Q22*(1+Forecast!$F$2) -> 0 | ... AM22: =AL22*(1+Forecast!$F$2) -> 0
C23: Gym fees, sport, other health & wellness | D23: 1100 | E23: Annually | F23: 91.67 | J23: =F23 -> 91.67 | K23: =J23*(1+Forecast!$F$2) -> 94.4201 | L23: =K23*(1+Forecast!$F$2) -> 97.252703 | M23: =L23*(1+Forecast!$F$2) -> 100.17028 | N23: =M23*(1+Forecast!$F$2) -> 103.17539 | O23: =N23*(1+Forecast!$F$2) -> 106.27065 | P23: =O23*(1+Forecast!$F$2) -> 109.45877 | Q23: =P23*(1+Forecast!$F$2) -> 112.74254 | R23: =Q23*(1+Forecast!$F$2) -> 116.12481 | ... AM23: =AL23*(1+Forecast!$F$2) -> 216.02636
C24: Private health insurance | D24: 580 | E24: Monthly | F24: 580 | J24: =F24 -> 580 | K24: =J24*(1+Forecast!$F$2) -> 597.4 | L24: =K24*(1+Forecast!$F$2) -> 615.322 | M24: =L24*(1+Forecast!$F$2) -> 633.78166 | N24: =M24*(1+Forecast!$F$2) -> 652.79511 | O24: =N24*(1+Forecast!$F$2) -> 672.37896 | P24: =O24*(1+Forecast!$F$2) -> 692.55033 | Q24: =P24*(1+Forecast!$F$2) -> 713.32684 | R24: =Q24*(1+Forecast!$F$2) -> 734.72665 | ... AM24: =AL24*(1+Forecast!$F$2) -> 1366.808
C25: Doctor, Dentist, Pharmacy, glasses | D25: 1800 | E25: Annually | F25: 150 | J25: =F25 -> 150 | K25: =J25*(1+Forecast!$F$2) -> 154.5 | L25: =K25*(1+Forecast!$F$2) -> 159.135 | M25: =L25*(1+Forecast!$F$2) -> 163.90905 | N25: =M25*(1+Forecast!$F$2) -> 168.82632 | O25: =N25*(1+Forecast!$F$2) -> 173.89111 | P25: =O25*(1+Forecast!$F$2) -> 179.10784 | Q25: =P25*(1+Forecast!$F$2) -> 184.48108 | R25: =Q25*(1+Forecast!$F$2) -> 190.01551 | ... AM25: =AL25*(1+Forecast!$F$2) -> 353.48483
C26: Life, trauma, income insurance | D26: 2200 | E26: Annually | F26: 183.33 | J26: =F26 -> 183.33 | K26: =J26*(1+Forecast!$F$2) -> 188.8299 | L26: =K26*(1+Forecast!$F$2) -> 194.4948 | M26: =L26*(1+Forecast!$F$2) -> 200.32964 | N26: =M26*(1+Forecast!$F$2) -> 206.33953 | O26: =N26*(1+Forecast!$F$2) -> 212.52972 | P26: =O26*(1+Forecast!$F$2) -> 218.90561 | Q26: =P26*(1+Forecast!$F$2) -> 225.47278 | R26: =Q26*(1+Forecast!$F$2) -> 232.23696 | ... AM26: =AL26*(1+Forecast!$F$2) -> 432.02915
B27: Transport Expenses | J27: =F27 -> 0 | K27: =J27*(1+Forecast!$F$2) -> 0 | L27: =K27*(1+Forecast!$F$2) -> 0 | M27: =L27*(1+Forecast!$F$2) -> 0 | N27: =M27*(1+Forecast!$F$2) -> 0 | O27: =N27*(1+Forecast!$F$2) -> 0 | P27: =O27*(1+Forecast!$F$2) -> 0 | Q27: =P27*(1+Forecast!$F$2) -> 0 | R27: =Q27*(1+Forecast!$F$2) -> 0 | ... AM27: =AL27*(1+Forecast!$F$2) -> 0
C28: Recreational vehicle running costs | D28: 0 | E28: 0 | F28: 0 | J28: =F28 -> 0 | K28: =J28*(1+Forecast!$F$2) -> 0 | L28: =K28*(1+Forecast!$F$2) -> 0 | M28: =L28*(1+Forecast!$F$2) -> 0 | N28: =M28*(1+Forecast!$F$2) -> 0 | O28: =N28*(1+Forecast!$F$2) -> 0 | P28: =O28*(1+Forecast!$F$2) -> 0 | Q28: =P28*(1+Forecast!$F$2) -> 0 | R28: =Q28*(1+Forecast!$F$2) -> 0 | ... AM28: =AL28*(1+Forecast!$F$2) -> 0
C29: Essential vehicle running cost | D29: 0 | E29: Annually | F29: 0 | J29: =F29 -> 0 | K29: =J29*(1+Forecast!$F$2) -> 0 | L29: =K29*(1+Forecast!$F$2) -> 0 | M29: =L29*(1+Forecast!$F$2) -> 0 | N29: =M29*(1+Forecast!$F$2) -> 0 | O29: =N29*(1+Forecast!$F$2) -> 0 | P29: =O29*(1+Forecast!$F$2) -> 0 | Q29: =P29*(1+Forecast!$F$2) -> 0 | R29: =Q29*(1+Forecast!$F$2) -> 0 | ... AM29: =AL29*(1+Forecast!$F$2) -> 0
C30: Public transport, taxis & ride share, commuting airfares | D30: 1200 | E30: Annually | F30: 100 | J30: =F30 -> 100 | K30: =J30*(1+Forecast!$F$2) -> 103 | L30: =K30*(1+Forecast!$F$2) -> 106.09 | M30: =L30*(1+Forecast!$F$2) -> 109.2727 | N30: =M30*(1+Forecast!$F$2) -> 112.55088 | O30: =N30*(1+Forecast!$F$2) -> 115.92741 | P30: =O30*(1+Forecast!$F$2) -> 119.40523 | Q30: =P30*(1+Forecast!$F$2) -> 122.98739 | R30: =Q30*(1+Forecast!$F$2) -> 126.67701 | ... AM30: =AL30*(1+Forecast!$F$2) -> 235.65655
C31: Essential vehicle insurance | D31: 0 | E31: Annually | F31: 0 | J31: =F31 -> 0 | K31: =J31*(1+Forecast!$F$2) -> 0 | L31: =K31*(1+Forecast!$F$2) -> 0 | M31: =L31*(1+Forecast!$F$2) -> 0 | N31: =M31*(1+Forecast!$F$2) -> 0 | O31: =N31*(1+Forecast!$F$2) -> 0 | P31: =O31*(1+Forecast!$F$2) -> 0 | Q31: =P31*(1+Forecast!$F$2) -> 0 | R31: =Q31*(1+Forecast!$F$2) -> 0 | ... AM31: =AL31*(1+Forecast!$F$2) -> 0
B32: Property Expenses | J32: =F32 -> 0 | K32: =J32*(1+Forecast!$F$2) -> 0 | L32: =K32*(1+Forecast!$F$2) -> 0 | M32: =L32*(1+Forecast!$F$2) -> 0 | N32: =M32*(1+Forecast!$F$2) -> 0 | O32: =N32*(1+Forecast!$F$2) -> 0 | P32: =O32*(1+Forecast!$F$2) -> 0 | Q32: =P32*(1+Forecast!$F$2) -> 0 | R32: =Q32*(1+Forecast!$F$2) -> 0 | ... AM32: =AL32*(1+Forecast!$F$2) -> 0
C33: Primary residence running costs | D33: 1780 | E33: Annually | F33: 148.33 | J33: =F33 -> 148.33 | K33: =J33*(1+Forecast!$F$2) -> 152.7799 | L33: =K33*(1+Forecast!$F$2) -> 157.3633 | M33: =L33*(1+Forecast!$F$2) -> 162.0842 | N33: =M33*(1+Forecast!$F$2) -> 166.94672 | O33: =N33*(1+Forecast!$F$2) -> 171.95512 | P33: =O33*(1+Forecast!$F$2) -> 177.11378 | Q33: =P33*(1+Forecast!$F$2) -> 182.42719 | R33: =Q33*(1+Forecast!$F$2) -> 187.90001 | ... AM33: =AL33*(1+Forecast!$F$2) -> 349.54936
C34: Primary residence body corp. | D34: 580 | E34: Quarterly | F34: 193.33 | J34: =F34 -> 193.33 | K34: =J34*(1+Forecast!$F$2) -> 199.1299 | L34: =K34*(1+Forecast!$F$2) -> 205.1038 | M34: =L34*(1+Forecast!$F$2) -> 211.25691 | N34: =M34*(1+Forecast!$F$2) -> 217.59462 | O34: =N34*(1+Forecast!$F$2) -> 224.12246 | P34: =O34*(1+Forecast!$F$2) -> 230.84613 | Q34: =P34*(1+Forecast!$F$2) -> 237.77151 | R34: =Q34*(1+Forecast!$F$2) -> 244.90466 | ... AM34: =AL34*(1+Forecast!$F$2) -> 455.59481
C35: Secondary residence running costs | D35: 0 | E35: 0 | F35: 0 | J35: =F35 -> 0 | K35: =J35*(1+Forecast!$F$2) -> 0 | L35: =K35*(1+Forecast!$F$2) -> 0 | M35: =L35*(1+Forecast!$F$2) -> 0 | N35: =M35*(1+Forecast!$F$2) -> 0 | O35: =N35*(1+Forecast!$F$2) -> 0 | P35: =O35*(1+Forecast!$F$2) -> 0 | Q35: =P35*(1+Forecast!$F$2) -> 0 | R35: =Q35*(1+Forecast!$F$2) -> 0 | ... AM35: =AL35*(1+Forecast!$F$2) -> 0
C36: Secondary residence body corp. | D36: 0 | E36: 0 | F36: 0 | J36: =F36 -> 0 | K36: =J36*(1+Forecast!$F$2) -> 0 | L36: =K36*(1+Forecast!$F$2) -> 0 | M36: =L36*(1+Forecast!$F$2) -> 0 | N36: =M36*(1+Forecast!$F$2) -> 0 | O36: =N36*(1+Forecast!$F$2) -> 0 | P36: =O36*(1+Forecast!$F$2) -> 0 | Q36: =P36*(1+Forecast!$F$2) -> 0 | R36: =Q36*(1+Forecast!$F$2) -> 0 | ... AM36: =AL36*(1+Forecast!$F$2) -> 0
C37: Investment property running costs | D37: 0 | E37: Annually | F37: =D37/12 -> 0 | J37: =F37 -> 0 | K37: =J37*(1+Forecast!$F$2) -> 0 | L37: =K37*(1+Forecast!$F$2) -> 0 | M37: =L37*(1+Forecast!$F$2) -> 0 | N37: =M37*(1+Forecast!$F$2) -> 0 | O37: =N37*(1+Forecast!$F$2) -> 0 | P37: =O37*(1+Forecast!$F$2) -> 0 | Q37: =P37*(1+Forecast!$F$2) -> 0 | R37: =Q37*(1+Forecast!$F$2) -> 0 | ... AM37: =AL37*(1+Forecast!$F$2) -> 0
B38: Other Commitments | J38: =F38 -> 0 | K38: =J38*(1+Forecast!$F$2) -> 0 | L38: =K38*(1+Forecast!$F$2) -> 0 | M38: =L38*(1+Forecast!$F$2) -> 0 | N38: =M38*(1+Forecast!$F$2) -> 0 | O38: =N38*(1+Forecast!$F$2) -> 0 | P38: =O38*(1+Forecast!$F$2) -> 0 | Q38: =P38*(1+Forecast!$F$2) -> 0 | R38: =Q38*(1+Forecast!$F$2) -> 0 | ... AM38: =AL38*(1+Forecast!$F$2) -> 0
C39: Child or spousal maintenance | D39: 0 | E39: 0 | F39: 0 | J39: =F39 -> 0 | K39: =J39*(1+Forecast!$F$2) -> 0 | L39: =K39*(1+Forecast!$F$2) -> 0 | M39: =L39*(1+Forecast!$F$2) -> 0 | N39: =M39*(1+Forecast!$F$2) -> 0 | O39: =N39*(1+Forecast!$F$2) -> 0 | P39: =O39*(1+Forecast!$F$2) -> 0 | Q39: =P39*(1+Forecast!$F$2) -> 0 | R39: =Q39*(1+Forecast!$F$2) -> 0 | ... AM39: =AL39*(1+Forecast!$F$2) -> 0
C40: Current rent expense | D40: 0 | E40: 0 | F40: 0 | J40: =F40 -> 0 | K40: =J40*(1+Forecast!$F$2) -> 0 | L40: =K40*(1+Forecast!$F$2) -> 0 | M40: =L40*(1+Forecast!$F$2) -> 0 | N40: =M40*(1+Forecast!$F$2) -> 0 | O40: =N40*(1+Forecast!$F$2) -> 0 | P40: =O40*(1+Forecast!$F$2) -> 0 | Q40: =P40*(1+Forecast!$F$2) -> 0 | R40: =Q40*(1+Forecast!$F$2) -> 0 | ... AM40: =AL40*(1+Forecast!$F$2) -> 0
C41: Ongoing board expense | D41: 0 | E41: 0 | F41: 0 | J41: =F41 -> 0 | K41: =J41*(1+Forecast!$F$2) -> 0 | L41: =K41*(1+Forecast!$F$2) -> 0 | M41: =L41*(1+Forecast!$F$2) -> 0 | N41: =M41*(1+Forecast!$F$2) -> 0 | O41: =N41*(1+Forecast!$F$2) -> 0 | P41: =O41*(1+Forecast!$F$2) -> 0 | Q41: =P41*(1+Forecast!$F$2) -> 0 | R41: =Q41*(1+Forecast!$F$2) -> 0 | ... AM41: =AL41*(1+Forecast!$F$2) -> 0
B42: Total Monthly | F42: =SUM(F3:F41) -> 7936.65 | J42: =SUM(J3:J41) -> 7936.65 | K42: =SUM(K3:K41) -> 8174.7495 | L42: =SUM(L3:L41) -> 8419.992 | M42: =SUM(M3:M41) -> 8672.5917 | N42: =SUM(N3:N41) -> 8932.7695 | O42: =SUM(O3:O41) -> 9200.7526 | P42: =SUM(P3:P41) -> 9476.7752 | Q42: =SUM(Q3:Q41) -> 9761.0784 | ... AM42: =SUM(AM3:AM41) -> 18703.236

Sheet Repayments
J2: Principal | K2: =Liabilities!E3+Liabilities!E4 -> 82426.27 | Q2: Principal | R2: =Liabilities!E10+Liabilities!E5+Liabilities!E7 -> 541251.44 | S2: All 308 loans, including top-ups on RH | X2: Principal | Y2: =Liabilities!E6+Liabilities!E9 -> 457164.26 | AE2: Principal | AF2: =Liabilities!E8+Liabilities!E11 -> 929452.01
J3: Interest rate | K3: 0.0603 | Q3: Interest rate | R3: =Liabilities!G10 -> 0.0619 | X3: Interest rate | Y3: =Liabilities!G9 -> 0.0619 | AE3: Interest rate | AF3: =Liabilities!G11 -> 0.0633
J4: Loan Term | K4: =30*12 -> 360 | Q4: Loan Term | R4: =30*12 -> 360 | X4: Loan Term | Y4: =30*12 -> 360 | AE4: Loan Term | AF4: =30*12 -> 360
D5: Start Payment | E5: 46203 | J5: Compound Periods per Year | K5: 12 | Q5: Annual compounding periods | R5: 12 | X5: Annual compounding periods | Y5: 12 | AE5: Annual compounding periods | AF5: 12
J6: Monthly Repayment | K6: =Liabilities!H3+Liabilities!H4 -> 1638 | Q6: Monthly Repayment | R6: =Liabilities!H10+Liabilities!H7+Liabilities!H5 -> 3781 | X6: Monthly Repayment | Y6: =Liabilities!H6+Liabilities!H9 -> 2884 | AE6: Monthly Repayment | AF6: =Liabilities!H8+Liabilities!H11 -> 6042 | AP6: Monthly Repayment | AQ6: =K6+R6+Y6 -> 8303
I7: PPOR | P7: Wentworthville | W7: Black Diamond | AD7: Shane St
D8: Payment # | E8: Financial Year | F8: Payment Date | G8: Month | H8: # of Days | I8: Loan Type | J8: Starting Balance | K8: Monthly Interest | L8: Monthly Principal | M8: Offset | N8: Ending Balance | P8: Loan Type | Q8: Starting Balance | R8: Monthly Interest | S8: Monthly Principal | T8: Offset | U8: Ending Balance | W8: Loan Type | X8: Starting Balance | Y8: Monthly Interest | Z8: Monthly Principal | AA8: Offset | AB8: Ending Balance | AD8: Loan Type | AE8: Starting Balance | AF8: Monthly Interest | AG8: Monthly Principal | AH8: Offset | AI8: Ending Balance | AK8: Financial Year | AL8: Calendar Month | AM8: 308 Interest | AN8: BD Interest | AO8: Shane Interest | AP8: Personal Interest | AQ8: Personal Repayments | AR8: Personal Owing | AS8: Total Interest | AT8: Total Principal | AU8: Total Repayments | AV8: Total Owing
D9: 1 | E9: =IF(MONTH(EDATE($E$5,D9))<7,YEAR(EDATE($E$5,D9)),YEAR(EDATE($E$5,D9))+1) -> 2027 | F9: =EDATE($E$5,D9) -> 46233 | G9: =MONTH(F9) -> 7 | H9: =DAY(EOMONTH(F9,0)) -> 31 | I9: PI | J9: =K2 -> 82426.27 | K9: =(IF(I9="PI",J9,IF(ISNUMBER(N8),N8,J9))*$K$3/365*$H9*IF(J9>0,1,0)) -> 422.13542 | L9: =IF(I9="IO",0,$K$6-K9)*IF(J9>0,1,0) -> 1215.8646 | M9: =IF(I9="IO",$K$6-K9+IF(ISNUMBER(M8),M8,0),IF(ISNUMBER(M8),M8,0)) -> 0 | N9: =(J9+K9-$K$6-IF(I9="PI",0,M9))*IF(J9>0,1,0) -> 81210.405 | P9: PI | Q9: =R2 -> 541251.44 | R9: =(IF(P9="PI",Q9,IF(ISNUMBER(U8),U8,Q9))*$R$3/365*$H9*IF(Q9>0,1,0)) -> 2845.4997 | S9: =IF(P9="IO",0,$R$6-R9)*IF(Q9>0,1,0) -> 935.50031 | T9: =IF(P9="IO",$R$6-R9+IF(ISNUMBER(T8),T8,0),IF(ISNUMBER(T8),T8,0)) -> 0 | U9: =(Q9+R9-$R$6-IF(P9="PI",0,T9))*IF(Q9>0,1,0) -> 540315.94 | W9: PI | X9: =Y2 -> 457164.26 | Y9: =(IF(W9="PI",X9,IF(ISNUMBER(AB8),AB8,X9))*$Y$3/365*$H9*IF(X9>0,1,0)) -> 2403.4315 | Z9: =IF(W9="IO",0,$Y$6-Y9)*IF(X9>0,1,0) -> 480.5685 | AA9: =IF(W9="IO",$Y$6-Y9+IF(ISNUMBER(AA8),AA8,0),IF(ISNUMBER(AA8),AA8,0)) -> 0 | AB9: =(X9+Y9-$Y$6-IF(W9="PI",0,AA9))*IF(X9>0,1,0) -> 456683.69 | AD9: PI | AE9: =AF2 -> 929452.01 | AF9: =(IF(AD9="PI",AE9,IF(ISNUMBER(AI8),AI8,AE9))*$AF$3/365*$H9*IF(AE9>0,1,0)) -> 4996.8868 | AG9: =IF(AD9="IO",0,$AF$6-AF9)*IF(AE9>0,1,0) -> 1045.1132 | AH9: =IF(AD9="IO",$AF$6-AF9+IF(ISNUMBER(AH8),AH8,0),IF(ISNUMBER(AH8),AH8,0)) -> 0 | AI9: =(AE9+AF9-$AF$6-IF(AD9="PI",0,AH9))*IF(AE9>0,1,0) -> 928406.9 | AK9: =E9 -> 2027 | AL9: =G9 -> 7 | AM9: =R9 -> 2845.4997 | AN9: =Y9 -> 2403.4315 | AO9: =AF9 -> 4996.8868 | AP9: =AM9+AN9 -> 5248.9312 | AQ9: =K6+R6+Y6 -> 8303 | AR9: =N9+U9+AB9 -> 1078210 | AS9: =AP9+AO9 -> 10245.818 | AT9: =L9+S9+Z9+AG9 -> 3677.0466 | AU9: =AS9+AT9 -> 13922.865 | AV9: =N9+U9+AB9+AI9 -> 2006616.9 | AY9: Calendar Month | AZ9: 6
D10: =D9+1 -> 2 | E10: =IF(MONTH(EDATE($E$5,D10))<7,YEAR(EDATE($E$5,D10)),YEAR(EDATE($E$5,D10))+1) -> 2027 | F10: =EDATE($E$5,D10) -> 46264 | G10: =MONTH(F10) -> 8 | H10: =DAY(EOMONTH(F10,0)) -> 31 | I10: PI | J10: =IF(I10="PI",IF(N9<=0,0,N9),(IF(I10="IO",J9,"")))*IF(N9<=0,0,1) -> 81210.405 | K10: =(IF(I10="PI",J10,IF(ISNUMBER(N9),N9,J10))*$K$3/365*$H10*IF(J10>0,1,0)) -> 415.90852 | L10: =IF(I10="IO",0,$K$6-K10)*IF(J10>0,1,0) -> 1222.0915 | M10: =IF(I10="IO",$K$6-K10+IF(ISNUMBER(M9),M9,0),IF(ISNUMBER(M9),M9,0)) -> 0 | N10: =(J10+K10-$K$6-IF(I10="PI",0,M10))*IF(J10>0,1,0) -> 79988.314 | P10: PI | Q10: =IF(P10="PI",IF(U9<=0,0,U9),(IF(P10="IO",Q9,"")))*IF(U9<=0,0,1) -> 540315.94 | R10: =(IF(P10="PI",Q10,IF(ISNUMBER(U9),U9,Q10))*$R$3/365*$H10*IF(Q10>0,1,0)) -> 2840.5815 | S10: =IF(P10="IO",0,$R$6-R10)*IF(Q10>0,1,0) -> 940.41847 | T10: =IF(P10="IO",$R$6-R10+IF(ISNUMBER(T9),T9,0),IF(ISNUMBER(T9),T9,0)) -> 0 | U10: =(Q10+R10-$R$6-IF(P10="PI",0,T10))*IF(Q10>0,1,0) -> 539375.52 | W10: PI | X10: =IF(W10="PI",IF(AB9<=0,0,AB9),(IF(W10="IO",X9,"")))*IF(AB9<=0,0,1) -> 456683.69 | Y10: =(IF(W10="PI",X10,IF(ISNUMBER(AB9),AB9,X10))*$Y$3/365*$H10*IF(X10>0,1,0)) -> 2400.905 | Z10: =IF(W10="IO",0,$Y$6-Y10)*IF(X10>0,1,0) -> 483.09497 | AA10: =IF(W10="IO",$Y$6-Y10+IF(ISNUMBER(AA9),AA9,0),IF(ISNUMBER(AA9),AA9,0)) -> 0 | AB10: =(X10+Y10-$Y$6-IF(W10="PI",0,AA10))*IF(X10>0,1,0) -> 456200.6 | AD10: PI | AE10: =IF(AD10="PI",IF(AI9<=0,0,AI9),(IF(AD10="IO",AE9,"")))*IF(AI9<=0,0,1) -> 928406.9 | AF10: =(IF(AD10="PI",AE10,IF(ISNUMBER(AI9),AI9,AE10))*$AF$3/365*$H10*IF(AE10>0,1,0)) -> 4991.2681 | AG10: =IF(AD10="IO",0,$AF$6-AF10)*IF(AE10>0,1,0) -> 1050.7319 | AH10: =IF(AD10="IO",$AF$6-AF10+IF(ISNUMBER(AH9),AH9,0),IF(ISNUMBER(AH9),AH9,0)) -> 0 | AI10: =(AE10+AF10-$AF$6-IF(AD10="PI",0,AH10))*IF(AE10>0,1,0) -> 927356.16 | AK10: =E10 -> 2027 | AL10: =G10 -> 8 | AM10: =IF($AK10=$AK9,R10+AM9,R10) -> 5686.0812 | AN10: =IF($AK10=$AK9,Y10+AN9,Y10) -> 4804.3365 | AO10: =IF($AK10=$AK9,AF10+AO9,AF10) -> 9988.1549 | AP10: =AM10+AN10 -> 10490.418 | AQ10: =IF(AK10=AK9,AQ9,0)+ IF(J10>0,$K$6,0)+ IF(Q10>0,$R$6,0)+ IF(X10>0,$Y$6,0) -> 16606 | AR10: =N10+U10+AB10 -> 1075564.4 | AS10: =AP10+AO10 -> 20478.573 | AT10: =IF(AK10=AK9,AT9,0)+ IF(J10>0,L10,0)+ IF(Q10>0,S10,0)+ IF(X10>0,Z10,0)+ IF(AE10>0,AG10,0) -> 7373.3834 | AU10: =AS10+AT10 -> 27851.956 | AV10: =N10+U10+AB10+AI10 -> 2002920.6
D11: =D10+1 -> 3 | E11: =IF(MONTH(EDATE($E$5,D11))<7,YEAR(EDATE($E$5,D11)),YEAR(EDATE($E$5,D11))+1) -> 2027 | F11: =EDATE($E$5,D11) -> 46295 | G11: =MONTH(F11) -> 9 | H11: =DAY(EOMONTH(F11,0)) -> 30 | I11: PI | J11: =IF(I11="PI",IF(N10<=0,0,N10),(IF(I11="IO",J10,"")))*IF(N10<=0,0,1) -> 79988.314 | K11: =(IF(I11="PI",J11,IF(ISNUMBER(N10),N10,J11))*$K$3/365*$H11*IF(J11>0,1,0)) -> 396.43523 | L11: =IF(I11="IO",0,$K$6-K11)*IF(J11>0,1,0) -> 1241.5648 | M11: =IF(I11="IO",$K$6-K11+IF(ISNUMBER(M10),M10,0),IF(ISNUMBER(M10),M10,0)) -> 0 | N11: =(J11+K11-$K$6-IF(I11="PI",0,M11))*IF(J11>0,1,0) -> 78746.749 | P11: PI | Q11: =IF(P11="PI",IF(U10<=0,0,U10),(IF(P11="IO",Q10,"")))*IF(U10<=0,0,1) -> 539375.52 | R11: =(IF(P11="PI",Q11,IF(ISNUMBER(U10),U10,Q11))*$R$3/365*$H11*IF(Q11>0,1,0)) -> 2744.1653 | S11: =IF(P11="IO",0,$R$6-R11)*IF(Q11>0,1,0) -> 1036.8347 | T11: =IF(P11="IO",$R$6-R11+IF(ISNUMBER(T10),T10,0),IF(ISNUMBER(T10),T10,0)) -> 0 | U11: =(Q11+R11-$R$6-IF(P11="PI",0,T11))*IF(Q11>0,1,0) -> 538338.69 | W11: PI | X11: =IF(W11="PI",IF(AB10<=0,0,AB10),(IF(W11="IO",X10,"")))*IF(AB10<=0,0,1) -> 456200.6 | Y11: =(IF(W11="PI",X11,IF(ISNUMBER(AB10),AB10,X11))*$Y$3/365*$H11*IF(X11>0,1,0)) -> 2320.9987 | Z11: =IF(W11="IO",0,$Y$6-Y11)*IF(X11>0,1,0) -> 563.00135 | AA11: =IF(W11="IO",$Y$6-Y11+IF(ISNUMBER(AA10),AA10,0),IF(ISNUMBER(AA10),AA10,0)) -> 0 | AB11: =(X11+Y11-$Y$6-IF(W11="PI",0,AA11))*IF(X11>0,1,0) -> 455637.6 | AD11: PI | AE11: =IF(AD11="PI",IF(AI10<=0,0,AI10),(IF(AD11="IO",AE10,"")))*IF(AI10<=0,0,1) -> 927356.16 | AF11: =(IF(AD11="PI",AE11,IF(ISNUMBER(AI10),AI10,AE11))*$AF$3/365*$H11*IF(AE11>0,1,0)) -> 4824.7928 | AG11: =IF(AD11="IO",0,$AF$6-AF11)*IF(AE11>0,1,0) -> 1217.2072 | AH11: =IF(AD11="IO",$AF$6-AF11+IF(ISNUMBER(AH10),AH10,0),IF(ISNUMBER(AH10),AH10,0)) -> 0 | AI11: =(AE11+AF11-$AF$6-IF(AD11="PI",0,AH11))*IF(AE11>0,1,0) -> 926138.96 | AK11: =E11 -> 2027 | AL11: =G11 -> 9 | AM11: =IF($AK11=$AK10,R11+AM10,R11) -> 8430.2465 | AN11: =IF($AK11=$AK10,Y11+AN10,Y11) -> 7125.3352 | AO11: =IF($AK11=$AK10,AF11+AO10,AF11) -> 14812.948 | AP11: =AM11+AN11 -> 15555.582 | AQ11: =IF(AK11=AK10,AQ10,0)+ IF(J11>0,$K$6,0)+ IF(Q11>0,$R$6,0)+ IF(X11>0,$Y$6,0) -> 24909 | AR11: =N11+U11+AB11 -> 1072723 | AS11: =AM11+AN11+AO11 -> 30368.529 | AT11: =IF(AK11=AK10,AT10,0)+ IF(J11>0,L11,0)+ IF(Q11>0,S11,0)+ IF(X11>0,Z11,0)+ IF(AE11>0,AG11,0) -> 11431.991 | AU11: =AS11+AT11 -> 41800.521 | AV11: =N11+U11+AB11+AI11 -> 1998862 | AZ11: Column Labels
D12: =D11+1 -> 4 | E12: =IF(MONTH(EDATE($E$5,D12))<7,YEAR(EDATE($E$5,D12)),YEAR(EDATE($E$5,D12))+1) -> 2027 | F12: =EDATE($E$5,D12) -> 46325 | G12: =MONTH(F12) -> 10 | H12: =DAY(EOMONTH(F12,0)) -> 31 | I12: PI | J12: =IF(I12="PI",IF(N11<=0,0,N11),(IF(I12="IO",J11,"")))*IF(N11<=0,0,1) -> 78746.749 | K12: =(IF(I12="PI",J12,IF(ISNUMBER(N11),N11,J12))*$K$3/365*$H12*IF(J12>0,1,0)) -> 403.29123 | L12: =IF(I12="IO",0,$K$6-K12)*IF(J12>0,1,0) -> 1234.7088 | M12: =IF(I12="IO",$K$6-K12+IF(ISNUMBER(M11),M11,0),IF(ISNUMBER(M11),M11,0)) -> 0 | N12: =(J12+K12-$K$6-IF(I12="PI",0,M12))*IF(J12>0,1,0) -> 77512.04 | P12: PI | Q12: =IF(P12="PI",IF(U11<=0,0,U11),(IF(P12="IO",Q11,"")))*IF(U11<=0,0,1) -> 538338.69 | R12: =(IF(P12="PI",Q12,IF(ISNUMBER(U11),U11,Q12))*$R$3/365*$H12*IF(Q12>0,1,0)) -> 2830.1866 | S12: =IF(P12="IO",0,$R$6-R12)*IF(Q12>0,1,0) -> 950.81341 | T12: =IF(P12="IO",$R$6-R12+IF(ISNUMBER(T11),T11,0),IF(ISNUMBER(T11),T11,0)) -> 0 | U12: =(Q12+R12-$R$6-IF(P12="PI",0,T12))*IF(Q12>0,1,0) -> 537387.87 | W12: PI | X12: =IF(W12="PI",IF(AB11<=0,0,AB11),(IF(W12="IO",X11,"")))*IF(AB11<=0,0,1) -> 455637.6 | Y12: =(IF(W12="PI",X12,IF(ISNUMBER(AB11),AB11,X12))*$Y$3/365*$H12*IF(X12>0,1,0)) -> 2395.4054 | Z12: =IF(W12="IO",0,$Y$6-Y12)*IF(X12>0,1,0) -> 488.59457 | AA12: =IF(W12="IO",$Y$6-Y12+IF(ISNUMBER(AA11),AA11,0),IF(ISNUMBER(AA11),AA11,0)) -> 0 | AB12: =(X12+Y12-$Y$6-IF(W12="PI",0,AA12))*IF(X12>0,1,0) -> 455149 | AD12: PI | AE12: =IF(AD12="PI",IF(AI11<=0,0,AI11),(IF(AD12="IO",AE11,"")))*IF(AI11<=0,0,1) -> 926138.96 | AF12: =(IF(AD12="PI",AE12,IF(ISNUMBER(AI11),AI11,AE12))*$AF$3/365*$H12*IF(AE12>0,1,0)) -> 4979.0753 | AG12: =IF(AD12="IO",0,$AF$6-AF12)*IF(AE12>0,1,0) -> 1062.9247 | AH12: =IF(AD12="IO",$AF$6-AF12+IF(ISNUMBER(AH11),AH11,0),IF(ISNUMBER(AH11),AH11,0)) -> 0 | AI12: =(AE12+AF12-$AF$6-IF(AD12="PI",0,AH12))*IF(AE12>0,1,0) -> 925076.03 | AK12: =E12 -> 2027 | AL12: =G12 -> 10 | AM12: =IF($AK12=$AK11,R12+AM11,R12) -> 11260.433 | AN12: =IF($AK12=$AK11,Y12+AN11,Y12) -> 9520.7406 | AO12: =IF($AK12=$AK11,AF12+AO11,AF12) -> 19792.023 | AP12: =AM12+AN12 -> 20781.174 | AQ12: =IF(AK12=AK11,AQ11,0)+ IF(J12>0,$K$6,0)+ IF(Q12>0,$R$6,0)+ IF(X12>0,$Y$6,0) -> 33212 | AR12: =N12+U12+AB12 -> 1070048.9 | AS12: =IF($AK12=$AK11,AF12+AP11,AP11) -> 20534.657 | AT12: =IF(AK12=AK11,AT11,0)+ IF(J12>0,L12,0)+ IF(Q12>0,S12,0)+ IF(X12>0,Z12,0)+ IF(AE12>0,AG12,0) -> 15169.033 | AU12: =AS12+AT12 -> 35703.69 | AV12: =N12+U12+AB12+AI12 -> 1995124.9 | AZ12: 2027 | BA12: 2028 | BB12: 2029 | BC12: 2030 | BD12: 2031 | BE12: 2032 | BF12: 2033 | BG12: 2034 | BH12: 2035 | BI12: 2036 | BJ12: 2037 | BK12: 2038 | BL12: 2039 | BM12: 2040 | BN12: 2041 | BO12: 2042 | BP12: 2043 | BQ12: 2044 | BR12: 2045 | BS12: 2046 | BT12: 2047 | BU12: 2048 | BV12: 2049 | BW12: 2050 | BX12: 2051 | BY12: 2052 | BZ12: 2053 | CA12: 2054 | CB12: 2055
D13: =D12+1 -> 5 | E13: =IF(MONTH(EDATE($E$5,D13))<7,YEAR(EDATE($E$5,D13)),YEAR(EDATE($E$5,D13))+1) -> 2027 | F13: =EDATE($E$5,D13) -> 46356 | G13: =MONTH(F13) -> 11 | H13: =DAY(EOMONTH(F13,0)) -> 30 | I13: PI | J13: =IF(I13="PI",IF(N12<=0,0,N12),(IF(I13="IO",J12,"")))*IF(N12<=0,0,1) -> 77512.04 | K13: =(IF(I13="PI",J13,IF(ISNUMBER(N12),N12,J13))*$K$3/365*$H13*IF(J13>0,1,0)) -> 384.16241 | L13: =IF(I13="IO",0,$K$6-K13)*IF(J13>0,1,0) -> 1253.8376 | M13: =IF(I13="IO",$K$6-K13+IF(ISNUMBER(M12),M12,0),IF(ISNUMBER(M12),M12,0)) -> 0 | N13: =(J13+K13-$K$6-IF(I13="PI",0,M13))*IF(J13>0,1,0) -> 76258.203 | P13: PI | Q13: =IF(P13="PI",IF(U12<=0,0,U12),(IF(P13="IO",Q12,"")))*IF(U12<=0,0,1) -> 537387.87 | R13: =(IF(P13="PI",Q13,IF(ISNUMBER(U12),U12,Q13))*$R$3/365*$H13*IF(Q13>0,1,0)) -> 2734.0528 | S13: =IF(P13="IO",0,$R$6-R13)*IF(Q13>0,1,0) -> 1046.9472 | T13: =IF(P13="IO",$R$6-R13+IF(ISNUMBER(T12),T12,0),IF(ISNUMBER(T12),T12,0)) -> 0 | U13: =(Q13+R13-$R$6-IF(P13="PI",0,T13))*IF(Q13>0,1,0) -> 536340.93 | W13: PI | X13: =IF(W13="PI",IF(AB12<=0,0,AB12),(IF(W13="IO",X12,"")))*IF(AB12<=0,0,1) -> 455149 | Y13: =(IF(W13="PI",X13,IF(ISNUMBER(AB12),AB12,X13))*$Y$3/365*$H13*IF(X13>0,1,0)) -> 2315.6485 | Z13: =IF(W13="IO",0,$Y$6-Y13)*IF(X13>0,1,0) -> 568.35152 | AA13: =IF(W13="IO",$Y$6-Y13+IF(ISNUMBER(AA12),AA12,0),IF(ISNUMBER(AA12),AA12,0)) -> 0 | AB13: =(X13+Y13-$Y$6-IF(W13="PI",0,AA13))*IF(X13>0,1,0) -> 454580.65 | AD13: PI | AE13: =IF(AD13="PI",IF(AI12<=0,0,AI12),(IF(AD13="IO",AE12,"")))*IF(AI12<=0,0,1) -> 925076.03 | AF13: =(IF(AD13="PI",AE13,IF(ISNUMBER(AI12),AI12,AE13))*$AF$3/365*$H13*IF(AE13>0,1,0)) -> 4812.9298 | AG13: =IF(AD13="IO",0,$AF$6-AF13)*IF(AE13>0,1,0) -> 1229.0702 | AH13: =IF(AD13="IO",$AF$6-AF13+IF(ISNUMBER(AH12),AH12,0),IF(ISNUMBER(AH12),AH12,0)) -> 0 | AI13: =(AE13+AF13-$AF$6-IF(AD13="PI",0,AH13))*IF(AE13>0,1,0) -> 923846.96 | AK13: =E13 -> 2027 | AL13: =G13 -> 11 | AM13: =IF($AK13=$AK12,R13+AM12,R13) -> 13994.486 | AN13: =IF($AK13=$AK12,Y13+AN12,Y13) -> 11836.389 | AO13: =IF($AK13=$AK12,AF13+AO12,AF13) -> 24604.953 | AP13: =AM13+AN13 -> 25830.875 | AQ13: =IF(AK13=AK12,AQ12,0)+ IF(J13>0,$K$6,0)+ IF(Q13>0,$R$6,0)+ IF(X13>0,$Y$6,0) -> 41515 | AR13: =N13+U13+AB13 -> 1067179.8 | AS13: =AP13+AO13 -> 50435.828 | AT13: =IF(AK13=AK12,AT12,0)+ IF(J13>0,L13,0)+ IF(Q13>0,S13,0)+ IF(X13>0,Z13,0)+ IF(AE13>0,AG13,0) -> 19267.239 | AU13: =AS13+AT13 -> 69703.067 | AV13: =N13+U13+AB13+AI13 -> 1991026.7 | AX13: Owing | AY13: Sum of Total Owing | AZ13: 1962440.7 | BA13: 1911882.6 | BB13: 1857771.6 | BC13: 1800219.6 | BD13: 1742007.4 | BE13: 1697595.4 | BF13: 1650026.1 | BG13: 1599396.9 | BH13: 1545510.8 | BI13: 1488423.4 | BJ13: 1427398.7 | BK13: 1362448.5 | BL13: 1293320.1 | BM13: 1219964 | BN13: 1141669.7 | BO13: 1058338.7 | BP13: 969647.02 | BQ13: 875410.19 | BR13: 774950.51 | BS13: 668028.05 | BT13: 554227 | BU13: 444938.04 | BV13: 363453.3 | BW13: 276695.62 | BX13: 184323.74 | BY13: 85996.68 | BZ13: 20593.323 | CA13: 0 | CB13: 0
D14: =D13+1 -> 6 | E14: =IF(MONTH(EDATE($E$5,D14))<7,YEAR(EDATE($E$5,D14)),YEAR(EDATE($E$5,D14))+1) -> 2027 | F14: =EDATE($E$5,D14) -> 46386 | G14: =MONTH(F14) -> 12 | H14: =DAY(EOMONTH(F14,0)) -> 31 | I14: PI | J14: =IF(I14="PI",IF(N13<=0,0,N13),(IF(I14="IO",J13,"")))*IF(N13<=0,0,1) -> 76258.203 | K14: =(IF(I14="PI",J14,IF(ISNUMBER(N13),N13,J14))*$K$3/365*$H14*IF(J14>0,1,0)) -> 390.54646 | L14: =IF(I14="IO",0,$K$6-K14)*IF(J14>0,1,0) -> 1247.4535 | M14: =IF(I14="IO",$K$6-K14+IF(ISNUMBER(M13),M13,0),IF(ISNUMBER(M13),M13,0)) -> 0 | N14: =(J14+K14-$K$6-IF(I14="PI",0,M14))*IF(J14>0,1,0) -> 75010.749 | P14: PI | Q14: =IF(P14="PI",IF(U13<=0,0,U13),(IF(P14="IO",Q13,"")))*IF(U13<=0,0,1) -> 536340.93 | R14: =(IF(P14="PI",Q14,IF(ISNUMBER(U13),U13,Q14))*$R$3/365*$H14*IF(Q14>0,1,0)) -> 2819.6838 | S14: =IF(P14="IO",0,$R$6-R14)*IF(Q14>0,1,0) -> 961.31616 | T14: =IF(P14="IO",$R$6-R14+IF(ISNUMBER(T13),T13,0),IF(ISNUMBER(T13),T13,0)) -> 0 | U14: =(Q14+R14-$R$6-IF(P14="PI",0,T14))*IF(Q14>0,1,0) -> 535379.61 | W14: PI | X14: =IF(W14="PI",IF(AB13<=0,0,AB13),(IF(W14="IO",X13,"")))*IF(AB13<=0,0,1) -> 454580.65 | Y14: =(IF(W14="PI",X14,IF(ISNUMBER(AB13),AB13,X14))*$Y$3/365*$H14*IF(X14>0,1,0)) -> 2389.8488 | Z14: =IF(W14="IO",0,$Y$6-Y14)*IF(X14>0,1,0) -> 494.15121 | AA14: =IF(W14="IO",$Y$6-Y14+IF(ISNUMBER(AA13),AA13,0),IF(ISNUMBER(AA13),AA13,0)) -> 0 | AB14: =(X14+Y14-$Y$6-IF(W14="PI",0,AA14))*IF(X14>0,1,0) -> 454086.5 | AD14: PI | AE14: =IF(AD14="PI",IF(AI13<=0,0,AI13),(IF(AD14="IO",AE13,"")))*IF(AI13<=0,0,1) -> 923846.96 | AF14: =(IF(AD14="PI",AE14,IF(ISNUMBER(AI13),AI13,AE14))*$AF$3/365*$H14*IF(AE14>0,1,0)) -> 4966.7531 | AG14: =IF(AD14="IO",0,$AF$6-AF14)*IF(AE14>0,1,0) -> 1075.2469 | AH14: =IF(AD14="IO",$AF$6-AF14+IF(ISNUMBER(AH13),AH13,0),IF(ISNUMBER(AH13),AH13,0)) -> 0 | AI14: =(AE14+AF14-$AF$6-IF(AD14="PI",0,AH14))*IF(AE14>0,1,0) -> 922771.72 | AK14: =E14 -> 2027 | AL14: =G14 -> 12 | AM14: =IF($AK14=$AK13,R14+AM13,R14) -> 16814.17 | AN14: =IF($AK14=$AK13,Y14+AN13,Y14) -> 14226.238 | AO14: =IF($AK14=$AK13,AF14+AO13,AF14) -> 29571.706 | AP14: =AM14+AN14 -> 31040.408 | AQ14: =IF(AK14=AK13,AQ13,0)+ IF(J14>0,$K$6,0)+ IF(Q14>0,$R$6,0)+ IF(X14>0,$Y$6,0) -> 49818 | AR14: =N14+U14+AB14 -> 1064476.9 | AS14: =AP14+AO14 -> 60612.114 | AT14: =IF(AK14=AK13,AT13,0)+ IF(J14>0,L14,0)+ IF(Q14>0,S14,0)+ IF(X14>0,Z14,0)+ IF(AE14>0,AG14,0) -> 23045.407 | AU14: =AS14+AT14 -> 83657.521 | AV14: =N14+U14+AB14+AI14 -> 1987248.6
D15: =D14+1 -> 7 | E15: =IF(MONTH(EDATE($E$5,D15))<7,YEAR(EDATE($E$5,D15)),YEAR(EDATE($E$5,D15))+1) -> 2027 | F15: =EDATE($E$5,D15) -> 46417 | G15: =MONTH(F15) -> 1 | H15: =DAY(EOMONTH(F15,0)) -> 31 | I15: PI | J15: =IF(I15="PI",IF(N14<=0,0,N14),(IF(I15="IO",J14,"")))*IF(N14<=0,0,1) -> 75010.749 | K15: =(IF(I15="PI",J15,IF(ISNUMBER(N14),N14,J15))*$K$3/365*$H15*IF(J15>0,1,0)) -> 384.15779 | L15: =IF(I15="IO",0,$K$6-K15)*IF(J15>0,1,0) -> 1253.8422 | M15: =IF(I15="IO",$K$6-K15+IF(ISNUMBER(M14),M14,0),IF(ISNUMBER(M14),M14,0)) -> 0 | N15: =(J15+K15-$K$6-IF(I15="PI",0,M15))*IF(J15>0,1,0) -> 73756.907 | P15: PI | Q15: =IF(P15="PI",IF(U14<=0,0,U14),(IF(P15="IO",Q14,"")))*IF(U14<=0,0,1) -> 535379.61 | R15: =(IF(P15="PI",Q15,IF(ISNUMBER(U14),U14,Q15))*$R$3/365*$H15*IF(Q15>0,1,0)) -> 2814.63 | S15: =IF(P15="IO",0,$R$6-R15)*IF(Q15>0,1,0) -> 966.37005 | T15: =IF(P15="IO",$R$6-R15+IF(ISNUMBER(T14),T14,0),IF(ISNUMBER(T14),T14,0)) -> 0 | U15: =(Q15+R15-$R$6-IF(P15="PI",0,T15))*IF(Q15>0,1,0) -> 534413.24 | W15: PI | X15: =IF(W15="PI",IF(AB14<=0,0,AB14),(IF(W15="IO",X14,"")))*IF(AB14<=0,0,1) -> 454086.5 | Y15: =(IF(W15="PI",X15,IF(ISNUMBER(AB14),AB14,X15))*$Y$3/365*$H15*IF(X15>0,1,0)) -> 2387.2509 | Z15: =IF(W15="IO",0,$Y$6-Y15)*IF(X15>0,1,0) -> 496.74909 | AA15: =IF(W15="IO",$Y$6-Y15+IF(ISNUMBER(AA14),AA14,0),IF(ISNUMBER(AA14),AA14,0)) -> 0 | AB15: =(X15+Y15-$Y$6-IF(W15="PI",0,AA15))*IF(X15>0,1,0) -> 453589.75 | AD15: PI | AE15: =IF(AD15="PI",IF(AI14<=0,0,AI14),(IF(AD15="IO",AE14,"")))*IF(AI14<=0,0,1) -> 922771.72 | AF15: =(IF(AD15="PI",AE15,IF(ISNUMBER(AI14),AI14,AE15))*$AF$3/365*$H15*IF(AE15>0,1,0)) -> 4960.9724 | AG15: =IF(AD15="IO",0,$AF$6-AF15)*IF(AE15>0,1,0) -> 1081.0276 | AH15: =IF(AD15="IO",$AF$6-AF15+IF(ISNUMBER(AH14),AH14,0),IF(ISNUMBER(AH14),AH14,0)) -> 0 | AI15: =(AE15+AF15-$AF$6-IF(AD15="PI",0,AH15))*IF(AE15>0,1,0) -> 921690.69 | AK15: =E15 -> 2027 | AL15: =G15 -> 1 | AM15: =IF($AK15=$AK14,R15+AM14,R15) -> 19628.8 | AN15: =IF($AK15=$AK14,Y15+AN14,Y15) -> 16613.489 | AO15: =IF($AK15=$AK14,AF15+AO14,AF15) -> 34532.678 | AP15: =AM15+AN15 -> 36242.289 | AQ15: =IF(AK15=AK14,AQ14,0)+ IF(J15>0,$K$6,0)+ IF(Q15>0,$R$6,0)+ IF(X15>0,$Y$6,0) -> 58121 | AR15: =N15+U15+AB15 -> 1061759.9 | AS15: =AP15+AO15 -> 70774.967 | AT15: =IF(AK15=AK14,AT14,0)+ IF(J15>0,L15,0)+ IF(Q15>0,S15,0)+ IF(X15>0,Z15,0)+ IF(AE15>0,AG15,0) -> 26843.396 | AU15: =AS15+AT15 -> 97618.363 | AV15: =N15+U15+AB15+AI15 -> 1983450.6 | AY15: Calendar Month | AZ15: 6
D16: =D15+1 -> 8 | E16: =IF(MONTH(EDATE($E$5,D16))<7,YEAR(EDATE($E$5,D16)),YEAR(EDATE($E$5,D16))+1) -> 2027 | F16: =EDATE($E$5,D16) -> 46446 | G16: =MONTH(F16) -> 2 | H16: =DAY(EOMONTH(F16,0)) -> 28 | I16: PI | J16: =IF(I16="PI",IF(N15<=0,0,N15),(IF(I16="IO",J15,"")))*IF(N15<=0,0,1) -> 73756.907 | K16: =(IF(I16="PI",J16,IF(ISNUMBER(N15),N15,J16))*$K$3/365*$H16*IF(J16>0,1,0)) -> 341.18127 | L16: =IF(I16="IO",0,$K$6-K16)*IF(J16>0,1,0) -> 1296.8187 | M16: =IF(I16="IO",$K$6-K16+IF(ISNUMBER(M15),M15,0),IF(ISNUMBER(M15),M15,0)) -> 0 | N16: =(J16+K16-$K$6-IF(I16="PI",0,M16))*IF(J16>0,1,0) -> 72460.088 | P16: PI | Q16: =IF(P16="PI",IF(U15<=0,0,U15),(IF(P16="IO",Q15,"")))*IF(U15<=0,0,1) -> 534413.24 | R16: =(IF(P16="PI",Q16,IF(ISNUMBER(U15),U15,Q16))*$R$3/365*$H16*IF(Q16>0,1,0)) -> 2537.6576 | S16: =IF(P16="IO",0,$R$6-R16)*IF(Q16>0,1,0) -> 1243.3424 | T16: =IF(P16="IO",$R$6-R16+IF(ISNUMBER(T15),T15,0),IF(ISNUMBER(T15),T15,0)) -> 0 | U16: =(Q16+R16-$R$6-IF(P16="PI",0,T16))*IF(Q16>0,1,0) -> 533169.9 | W16: PI | X16: =IF(W16="PI",IF(AB15<=0,0,AB15),(IF(W16="IO",X15,"")))*IF(AB15<=0,0,1) -> 453589.75 | Y16: =(IF(W16="PI",X16,IF(ISNUMBER(AB15),AB15,X16))*$Y$3/365*$H16*IF(X16>0,1,0)) -> 2153.8678 | Z16: =IF(W16="IO",0,$Y$6-Y16)*IF(X16>0,1,0) -> 730.13218 | AA16: =IF(W16="IO",$Y$6-Y16+IF(ISNUMBER(AA15),AA15,0),IF(ISNUMBER(AA15),AA15,0)) -> 0 | AB16: =(X16+Y16-$Y$6-IF(W16="PI",0,AA16))*IF(X16>0,1,0) -> 452859.62 | AD16: PI | AE16: =IF(AD16="PI",IF(AI15<=0,0,AI15),(IF(AD16="IO",AE15,"")))*IF(AI15<=0,0,1) -> 921690.69 | AF16: =(IF(AD16="PI",AE16,IF(ISNUMBER(AI15),AI15,AE16))*$AF$3/365*$H16*IF(AE16>0,1,0)) -> 4475.629 | AG16: =IF(AD16="IO",0,$AF$6-AF16)*IF(AE16>0,1,0) -> 1566.371 | AH16: =IF(AD16="IO",$AF$6-AF16+IF(ISNUMBER(AH15),AH15,0),IF(ISNUMBER(AH15),AH15,0)) -> 0 | AI16: =(AE16+AF16-$AF$6-IF(AD16="PI",0,AH16))*IF(AE16>0,1,0) -> 920124.32 | AK16: =E16 -> 2027 | AL16: =G16 -> 2 | AM16: =IF($AK16=$AK15,R16+AM15,R16) -> 22166.457 | AN16: =IF($AK16=$AK15,Y16+AN15,Y16) -> 18767.357 | AO16: =IF($AK16=$AK15,AF16+AO15,AF16) -> 39008.307 | AP16: =AM16+AN16 -> 40933.814 | AQ16: =IF(AK16=AK15,AQ15,0)+ IF(J16>0,$K$6,0)+ IF(Q16>0,$R$6,0)+ IF(X16>0,$Y$6,0) -> 66424 | AR16: =N16+U16+AB16 -> 1058489.6 | AS16: =AP16+AO16 -> 79942.121 | AT16: =IF(AK16=AK15,AT15,0)+ IF(J16>0,L16,0)+ IF(Q16>0,S16,0)+ IF(X16>0,Z16,0)+ IF(AE16>0,AG16,0) -> 31680.06 | AU16: =AS16+AT16 -> 111622.18 | AV16: =N16+U16+AB16+AI16 -> 1978613.9
D17: =D16+1 -> 9 | E17: =IF(MONTH(EDATE($E$5,D17))<7,YEAR(EDATE($E$5,D17)),YEAR(EDATE($E$5,D17))+1) -> 2027 | F17: =EDATE($E$5,D17) -> 46476 | G17: =MONTH(F17) -> 3 | H17: =DAY(EOMONTH(F17,0)) -> 31 | I17: PI | J17: =IF(I17="PI",IF(N16<=0,0,N16),(IF(I17="IO",J16,"")))*IF(N16<=0,0,1) -> 72460.088 | K17: =(IF(I17="PI",J17,IF(ISNUMBER(N16),N16,J17))*$K$3/365*$H17*IF(J17>0,1,0)) -> 371.09491 | L17: =IF(I17="IO",0,$K$6-K17)*IF(J17>0,1,0) -> 1266.9051 | M17: =IF(I17="IO",$K$6-K17+IF(ISNUMBER(M16),M16,0),IF(ISNUMBER(M16),M16,0)) -> 0 | N17: =(J17+K17-$K$6-IF(I17="PI",0,M17))*IF(J17>0,1,0) -> 71193.183 | P17: PI | Q17: =IF(P17="PI",IF(U16<=0,0,U16),(IF(P17="IO",Q16,"")))*IF(U16<=0,0,1) -> 533169.9 | R17: =(IF(P17="PI",Q17,IF(ISNUMBER(U16),U16,Q17))*$R$3/365*$H17*IF(Q17>0,1,0)) -> 2803.0129 | S17: =IF(P17="IO",0,$R$6-R17)*IF(Q17>0,1,0) -> 977.98708 | T17: =IF(P17="IO",$R$6-R17+IF(ISNUMBER(T16),T16,0),IF(ISNUMBER(T16),T16,0)) -> 0 | U17: =(Q17+R17-$R$6-IF(P17="PI",0,T17))*IF(Q17>0,1,0) -> 532191.91 | W17: PI | X17: =IF(W17="PI",IF(AB16<=0,0,AB16),(IF(W17="IO",X16,"")))*IF(AB16<=0,0,1) -> 452859.62 | Y17: =(IF(W17="PI",X17,IF(ISNUMBER(AB16),AB16,X17))*$Y$3/365*$H17*IF(X17>0,1,0)) -> 2380.8009 | Z17: =IF(W17="IO",0,$Y$6-Y17)*IF(X17>0,1,0) -> 503.19913 | AA17: =IF(W17="IO",$Y$6-Y17+IF(ISNUMBER(AA16),AA16,0),IF(ISNUMBER(AA16),AA16,0)) -> 0 | AB17: =(X17+Y17-$Y$6-IF(W17="PI",0,AA17))*IF(X17>0,1,0) -> 452356.42 | AD17: PI | AE17: =IF(AD17="PI",IF(AI16<=0,0,AI16),(IF(AD17="IO",AE16,"")))*IF(AI16<=0,0,1) -> 920124.32 | AF17: =(IF(AD17="PI",AE17,IF(ISNUMBER(AI16),AI16,AE17))*$AF$3/365*$H17*IF(AE17>0,1,0)) -> 4946.7396 | AG17: =IF(AD17="IO",0,$AF$6-AF17)*IF(AE17>0,1,0) -> 1095.2604 | AH17: =IF(AD17="IO",$AF$6-AF17+IF(ISNUMBER(AH16),AH16,0),IF(ISNUMBER(AH16),AH16,0)) -> 0 | AI17: =(AE17+AF17-$AF$6-IF(AD17="PI",0,AH17))*IF(AE17>0,1,0) -> 919029.06 | AK17: =E17 -> 2027 | AL17: =G17 -> 3 | AM17: =IF($AK17=$AK16,R17+AM16,R17) -> 24969.47 | AN17: =IF($AK17=$AK16,Y17+AN16,Y17) -> 21148.157 | AO17: =IF($AK17=$AK16,AF17+AO16,AF17) -> 43955.047 | AP17: =AM17+AN17 -> 46117.628 | AQ17: =IF(AK17=AK16,AQ16,0)+ IF(J17>0,$K$6,0)+ IF(Q17>0,$R$6,0)+ IF(X17>0,$Y$6,0) -> 74727 | AR17: =N17+U17+AB17 -> 1055741.5 | AS17: =AP17+AO17 -> 90072.675 | AT17: =IF(AK17=AK16,AT16,0)+ IF(J17>0,L17,0)+ IF(Q17>0,S17,0)+ IF(X17>0,Z17,0)+ IF(AE17>0,AG17,0) -> 35523.412 | AU17: =AS17+AT17 -> 125596.09 | AV17: =N17+U17+AB17+AI17 -> 1974770.6 | AZ17: Column Labels
D18: =D17+1 -> 10 | E18: =IF(MONTH(EDATE($E$5,D18))<7,YEAR(EDATE($E$5,D18)),YEAR(EDATE($E$5,D18))+1) -> 2027 | F18: =EDATE($E$5,D18) -> 46507 | G18: =MONTH(F18) -> 4 | H18: =DAY(EOMONTH(F18,0)) -> 30 | I18: PI | J18: =IF(I18="PI",IF(N17<=0,0,N17),(IF(I18="IO",J17,"")))*IF(N17<=0,0,1) -> 71193.183 | K18: =(IF(I18="PI",J18,IF(ISNUMBER(N17),N17,J18))*$K$3/365*$H18*IF(J18>0,1,0)) -> 352.84512 | L18: =IF(I18="IO",0,$K$6-K18)*IF(J18>0,1,0) -> 1285.1549 | M18: =IF(I18="IO",$K$6-K18+IF(ISNUMBER(M17),M17,0),IF(ISNUMBER(M17),M17,0)) -> 0 | N18: =(J18+K18-$K$6-IF(I18="PI",0,M18))*IF(J18>0,1,0) -> 69908.028 | P18: PI | Q18: =IF(P18="PI",IF(U17<=0,0,U17),(IF(P18="IO",Q17,"")))*IF(U17<=0,0,1) -> 532191.91 | R18: =(IF(P18="PI",Q18,IF(ISNUMBER(U17),U17,Q18))*$R$3/365*$H18*IF(Q18>0,1,0)) -> 2707.6175 | S18: =IF(P18="IO",0,$R$6-R18)*IF(Q18>0,1,0) -> 1073.3825 | T18: =IF(P18="IO",$R$6-R18+IF(ISNUMBER(T17),T17,0),IF(ISNUMBER(T17),T17,0)) -> 0 | U18: =(Q18+R18-$R$6-IF(P18="PI",0,T18))*IF(Q18>0,1,0) -> 531118.53 | W18: PI | X18: =IF(W18="PI",IF(AB17<=0,0,AB17),(IF(W18="IO",X17,"")))*IF(AB17<=0,0,1) -> 452356.42 | Y18: =(IF(W18="PI",X18,IF(ISNUMBER(AB17),AB17,X18))*$Y$3/365*$H18*IF(X18>0,1,0)) -> 2301.4407 | Z18: =IF(W18="IO",0,$Y$6-Y18)*IF(X18>0,1,0) -> 582.55927 | AA18: =IF(W18="IO",$Y$6-Y18+IF(ISNUMBER(AA17),AA17,0),IF(ISNUMBER(AA17),AA17,0)) -> 0 | AB18: =(X18+Y18-$Y$6-IF(W18="PI",0,AA18))*IF(X18>0,1,0) -> 451773.86 | AD18: PI | AE18: =IF(AD18="PI",IF(AI17<=0,0,AI17),(IF(AD18="IO",AE17,"")))*IF(AI17<=0,0,1) -> 919029.06 | AF18: =(IF(AD18="PI",AE18,IF(ISNUMBER(AI17),AI17,AE18))*$AF$3/365*$H18*IF(AE18>0,1,0)) -> 4781.469 | AG18: =IF(AD18="IO",0,$AF$6-AF18)*IF(AE18>0,1,0) -> 1260.531 | AH18: =IF(AD18="IO",$AF$6-AF18+IF(ISNUMBER(AH17),AH17,0),IF(ISNUMBER(AH17),AH17,0)) -> 0 | AI18: =(AE18+AF18-$AF$6-IF(AD18="PI",0,AH18))*IF(AE18>0,1,0) -> 917768.53 | AK18: =E18 -> 2027 | AL18: =G18 -> 4 | AM18: =IF($AK18=$AK17,R18+AM17,R18) -> 27677.088 | AN18: =IF($AK18=$AK17,Y18+AN17,Y18) -> 23449.598 | AO18: =IF($AK18=$AK17,AF18+AO17,AF18) -> 48736.516 | AP18: =AM18+AN18 -> 51126.686 | AQ18: =IF(AK18=AK17,AQ17,0)+ IF(J18>0,$K$6,0)+ IF(Q18>0,$R$6,0)+ IF(X18>0,$Y$6,0) -> 83030 | AR18: =N18+U18+AB18 -> 1052800.4 | AS18: =AP18+AO18 -> 99863.202 | AT18: =IF(AK18=AK17,AT17,0)+ IF(J18>0,L18,0)+ IF(Q18>0,S18,0)+ IF(X18>0,Z18,0)+ IF(AE18>0,AG18,0) -> 39725.04 | AU18: =AS18+AT18 -> 139588.24 | AV18: =N18+U18+AB18+AI18 -> 1970568.9 | AZ18: 2027 | BA18: 2028 | BB18: 2029 | BC18: 2030 | BD18: 2031 | BE18: 2032 | BF18: 2033 | BG18: 2034 | BH18: 2035 | BI18: 2036 | BJ18: 2037 | BK18: 2038 | BL18: 2039 | BM18: 2040 | BN18: 2041 | BO18: 2042 | BP18: 2043 | BQ18: 2044 | BR18: 2045 | BS18: 2046 | BT18: 2047 | BU18: 2048 | BV18: 2049 | BW18: 2050 | BX18: 2051 | BY18: 2052 | BZ18: 2053 | CA18: 2054 | CB18: 2055
D19: =D18+1 -> 11 | E19: =IF(MONTH(EDATE($E$5,D19))<7,YEAR(EDATE($E$5,D19)),YEAR(EDATE($E$5,D19))+1) -> 2027 | F19: =EDATE($E$5,D19) -> 46537 | G19: =MONTH(F19) -> 5 | H19: =DAY(EOMONTH(F19,0)) -> 31 | I19: PI | J19: =IF(I19="PI",IF(N18<=0,0,N18),(IF(I19="IO",J18,"")))*IF(N18<=0,0,1) -> 69908.028 | K19: =(IF(I19="PI",J19,IF(ISNUMBER(N18),N18,J19))*$K$3/365*$H19*IF(J19>0,1,0)) -> 358.02487 | L19: =IF(I19="IO",0,$K$6-K19)*IF(J19>0,1,0) -> 1279.9751 | M19: =IF(I19="IO",$K$6-K19+IF(ISNUMBER(M18),M18,0),IF(ISNUMBER(M18),M18,0)) -> 0 | N19: =(J19+K19-$K$6-IF(I19="PI",0,M19))*IF(J19>0,1,0) -> 68628.053 | P19: PI | Q19: =IF(P19="PI",IF(U18<=0,0,U18),(IF(P19="IO",Q18,"")))*IF(U18<=0,0,1) -> 531118.53 | R19: =(IF(P19="PI",Q19,IF(ISNUMBER(U18),U18,Q19))*$R$3/365*$H19*IF(Q19>0,1,0)) -> 2792.2283 | S19: =IF(P19="IO",0,$R$6-R19)*IF(Q19>0,1,0) -> 988.77166 | T19: =IF(P19="IO",$R$6-R19+IF(ISNUMBER(T18),T18,0),IF(ISNUMBER(T18),T18,0)) -> 0 | U19: =(Q19+R19-$R$6-IF(P19="PI",0,T19))*IF(Q19>0,1,0) -> 530129.76 | W19: PI | X19: =IF(W19="PI",IF(AB18<=0,0,AB18),(IF(W19="IO",X18,"")))*IF(AB18<=0,0,1) -> 451773.86 | Y19: =(IF(W19="PI",X19,IF(ISNUMBER(AB18),AB18,X19))*$Y$3/365*$H19*IF(X19>0,1,0)) -> 2375.0928 | Z19: =IF(W19="IO",0,$Y$6-Y19)*IF(X19>0,1,0) -> 508.90724 | AA19: =IF(W19="IO",$Y$6-Y19+IF(ISNUMBER(AA18),AA18,0),IF(ISNUMBER(AA18),AA18,0)) -> 0 | AB19: =(X19+Y19-$Y$6-IF(W19="PI",0,AA19))*IF(X19>0,1,0) -> 451264.95 | AD19: PI | AE19: =IF(AD19="PI",IF(AI18<=0,0,AI18),(IF(AD19="IO",AE18,"")))*IF(AI18<=0,0,1) -> 917768.53 | AF19: =(IF(AD19="PI",AE19,IF(ISNUMBER(AI18),AI18,AE19))*$AF$3/365*$H19*IF(AE19>0,1,0)) -> 4934.0745 | AG19: =IF(AD19="IO",0,$AF$6-AF19)*IF(AE19>0,1,0) -> 1107.9255 | AH19: =IF(AD19="IO",$AF$6-AF19+IF(ISNUMBER(AH18),AH18,0),IF(ISNUMBER(AH18),AH18,0)) -> 0 | AI19: =(AE19+AF19-$AF$6-IF(AD19="PI",0,AH19))*IF(AE19>0,1,0) -> 916660.6 | AK19: =E19 -> 2027 | AL19: =G19 -> 5 | AM19: =IF($AK19=$AK18,R19+AM18,R19) -> 30469.316 | AN19: =IF($AK19=$AK18,Y19+AN18,Y19) -> 25824.691 | AO19: =IF($AK19=$AK18,AF19+AO18,AF19) -> 53670.59 | AP19: =AM19+AN19 -> 56294.007 | AQ19: =IF(AK19=AK18,AQ18,0)+ IF(J19>0,$K$6,0)+ IF(Q19>0,$R$6,0)+ IF(X19>0,$Y$6,0) -> 91333 | AR19: =N19+U19+AB19 -> 1050022.8 | AS19: =AP19+AO19 -> 109964.6 | AT19: =IF(AK19=AK18,AT18,0)+ IF(J19>0,L19,0)+ IF(Q19>0,S19,0)+ IF(X19>0,Z19,0)+ IF(AE19>0,AG19,0) -> 43610.619 | AU19: =AS19+AT19 -> 153575.22 | AV19: =N19+U19+AB19+AI19 -> 1966683.4 | AX19: Repayments | AY19: Sum of Total Repayments | AZ19: 167580.08 | BA19: 168506.17 | BB19: 169509.25 | BC19: 170564.72 | BD19: 170040.92 | BE19: 152484 | BF19: 152484 | BG19: 152484 | BH19: 152484 | BI19: 152484 | BJ19: 152484 | BK19: 152484 | BL19: 152484 | BM19: 152484 | BN19: 152484 | BO19: 152484 | BP19: 152484 | BQ19: 152484 | BR19: 152484 | BS19: 152484 | BT19: 152484 | BU19: 141141 | BV19: 107112 | BW19: 107112 | BX19: 107112 | BY19: 107112 | BZ19: 70860 | CA19: 23072 | CB19: 0
D20: =D19+1 -> 12 | E20: =IF(MONTH(EDATE($E$5,D20))<7,YEAR(EDATE($E$5,D20)),YEAR(EDATE($E$5,D20))+1) -> 2027 | F20: =EDATE($E$5,D20) -> 46568 | G20: =MONTH(F20) -> 6 | H20: =DAY(EOMONTH(F20,0)) -> 30 | I20: PI | J20: =IF(I20="PI",IF(N19<=0,0,N19),(IF(I20="IO",J19,"")))*IF(N19<=0,0,1) -> 68628.053 | K20: =(IF(I20="PI",J20,IF(ISNUMBER(N19),N19,J20))*$K$3/365*$H20*IF(J20>0,1,0)) -> 340.13191 | L20: =IF(I20="IO",0,$K$6-K20)*IF(J20>0,1,0) -> 1297.8681 | M20: =IF(I20="IO",$K$6-K20+IF(ISNUMBER(M19),M19,0),IF(ISNUMBER(M19),M19,0)) -> 0 | N20: =(J20+K20-$K$6-IF(I20="PI",0,M20))*IF(J20>0,1,0) -> 67330.185 | P20: PI | Q20: =IF(P20="PI",IF(U19<=0,0,U19),(IF(P20="IO",Q19,"")))*IF(U19<=0,0,1) -> 530129.76 | R20: =(IF(P20="PI",Q20,IF(ISNUMBER(U19),U19,Q20))*$R$3/365*$H20*IF(Q20>0,1,0)) -> 2697.1259 | S20: =IF(P20="IO",0,$R$6-R20)*IF(Q20>0,1,0) -> 1083.8741 | T20: =IF(P20="IO",$R$6-R20+IF(ISNUMBER(T19),T19,0),IF(ISNUMBER(T19),T19,0)) -> 0 | U20: =(Q20+R20-$R$6-IF(P20="PI",0,T20))*IF(Q20>0,1,0) -> 529045.88 | W20: PI | X20: =IF(W20="PI",IF(AB19<=0,0,AB19),(IF(W20="IO",X19,"")))*IF(AB19<=0,0,1) -> 451264.95 | Y20: =(IF(W20="PI",X20,IF(ISNUMBER(AB19),AB19,X20))*$Y$3/365*$H20*IF(X20>0,1,0)) -> 2295.8877 | Z20: =IF(W20="IO",0,$Y$6-Y20)*IF(X20>0,1,0) -> 588.11229 | AA20: =IF(W20="IO",$Y$6-Y20+IF(ISNUMBER(AA19),AA19,0),IF(ISNUMBER(AA19),AA19,0)) -> 0 | AB20: =(X20+Y20-$Y$6-IF(W20="PI",0,AA20))*IF(X20>0,1,0) -> 450676.84 | AD20: PI | AE20: =IF(AD20="PI",IF(AI19<=0,0,AI19),(IF(AD20="IO",AE19,"")))*IF(AI19<=0,0,1) -> 916660.6 | AF20: =(IF(AD20="PI",AE20,IF(ISNUMBER(AI19),AI19,AE20))*$AF$3/365*$H20*IF(AE20>0,1,0)) -> 4769.1465 | AG20: =IF(AD20="IO",0,$AF$6-AF20)*IF(AE20>0,1,0) -> 1272.8535 | AH20: =IF(AD20="IO",$AF$6-AF20+IF(ISNUMBER(AH19),AH19,0),IF(ISNUMBER(AH19),AH19,0)) -> 0 | AI20: =(AE20+AF20-$AF$6-IF(AD20="PI",0,AH20))*IF(AE20>0,1,0) -> 915387.75 | AK20: =E20 -> 2027 | AL20: =G20 -> 6 | AM20: =IF($AK20=$AK19,R20+AM19,R20) -> 33166.442 | AN20: =IF($AK20=$AK19,Y20+AN19,Y20) -> 28120.579 | AO20: =IF($AK20=$AK19,AF20+AO19,AF20) -> 58439.737 | AP20: =AM20+AN20 -> 61287.021 | AQ20: =IF(AK20=AK19,AQ19,0)+ IF(J20>0,$K$6,0)+ IF(Q20>0,$R$6,0)+ IF(X20>0,$Y$6,0) -> 99636 | AR20: =N20+U20+AB20 -> 1047052.9 | AS20: =AP20+AO20 -> 119726.76 | AT20: =IF(AK20=AK19,AT19,0)+ IF(J20>0,L20,0)+ IF(Q20>0,S20,0)+ IF(X20>0,Z20,0)+ IF(AE20>0,AG20,0) -> 47853.327 | AU20: =AS20+AT20 -> 167580.08 | AV20: =N20+U20+AB20+AI20 -> 1962440.7
D21: =D20+1 -> 13 | E21: =IF(MONTH(EDATE($E$5,D21))<7,YEAR(EDATE($E$5,D21)),YEAR(EDATE($E$5,D21))+1) -> 2028 | F21: =EDATE($E$5,D21) -> 46598 | G21: =MONTH(F21) -> 7 | H21: =DAY(EOMONTH(F21,0)) -> 31 | I21: PI | J21: =IF(I21="PI",IF(N20<=0,0,N20),(IF(I21="IO",J20,"")))*IF(N20<=0,0,1) -> 67330.185 | K21: =(IF(I21="PI",J21,IF(ISNUMBER(N20),N20,J21))*$K$3/365*$H21*IF(J21>0,1,0)) -> 344.82278 | L21: =IF(I21="IO",0,$K$6-K21)*IF(J21>0,1,0) -> 1293.1772 | M21: =IF(I21="IO",$K$6-K21+IF(ISNUMBER(M20),M20,0),IF(ISNUMBER(M20),M20,0)) -> 0 | N21: =(J21+K21-$K$6-IF(I21="PI",0,M21))*IF(J21>0,1,0) -> 66037.008 | P21: PI | Q21: =IF(P21="PI",IF(U20<=0,0,U20),(IF(P21="IO",Q20,"")))*IF(U20<=0,0,1) -> 529045.88 | R21: =(IF(P21="PI",Q21,IF(ISNUMBER(U20),U20,Q21))*$R$3/365*$H21*IF(Q21>0,1,0)) -> 2781.3319 | S21: =IF(P21="IO",0,$R$6-R21)*IF(Q21>0,1,0) -> 999.6681 | T21: =IF(P21="IO",$R$6-R21+IF(ISNUMBER(T20),T20,0),IF(ISNUMBER(T20),T20,0)) -> 0 | U21: =(Q21+R21-$R$6-IF(P21="PI",0,T21))*IF(Q21>0,1,0) -> 528046.21 | W21: PI | X21: =IF(W21="PI",IF(AB20<=0,0,AB20),(IF(W21="IO",X20,"")))*IF(AB20<=0,0,1) -> 450676.84 | Y21: =(IF(W21="PI",X21,IF(ISNUMBER(AB20),AB20,X21))*$Y$3/365*$H21*IF(X21>0,1,0)) -> 2369.3254 | Z21: =IF(W21="IO",0,$Y$6-Y21)*IF(X21>0,1,0) -> 514.67456 | AA21: =IF(W21="IO",$Y$6-Y21+IF(ISNUMBER(AA20),AA20,0),IF(ISNUMBER(AA20),AA20,0)) -> 0 | AB21: =(X21+Y21-$Y$6-IF(W21="PI",0,AA21))*IF(X21>0,1,0) -> 450162.16 | AD21: PI | AE21: =IF(AD21="PI",IF(AI20<=0,0,AI20),(IF(AD21="IO",AE20,"")))*IF(AI20<=0,0,1) -> 915387.75 | AF21: =(IF(AD21="PI",AE21,IF(ISNUMBER(AI20),AI20,AE21))*$AF$3/365*$H21*IF(AE21>0,1,0)) -> 4921.275 | AG21: =IF(AD21="IO",0,$AF$6-AF21)*IF(AE21>0,1,0) -> 1120.725 | AH21: =IF(AD21="IO",$AF$6-AF21+IF(ISNUMBER(AH20),AH20,0),IF(ISNUMBER(AH20),AH20,0)) -> 0 | AI21: =(AE21+AF21-$AF$6-IF(AD21="PI",0,AH21))*IF(AE21>0,1,0) -> 914267.02 | AK21: =E21 -> 2028 | AL21: =G21 -> 7 | AM21: =IF($AK21=$AK20,R21+AM20,R21) -> 2781.3319 | AN21: =IF($AK21=$AK20,Y21+AN20,Y21) -> 2369.3254 | AO21: =IF($AK21=$AK20,AF21+AO20,AF21) -> 4921.275 | AP21: =AM21+AN21 -> 5150.6573 | AQ21: =IF(AK21=AK20,AQ20,0)+ IF(J21>0,$K$6,0)+ IF(Q21>0,$R$6,0)+ IF(X21>0,$Y$6,0) -> 8303 | AR21: =N21+U21+AB21 -> 1044245.4 | AS21: =AP21+AO21 -> 10071.932 | AT21: =IF(AK21=AK20,AT20,0)+ IF(J21>0,L21,0)+ IF(Q21>0,S21,0)+ IF(X21>0,Z21,0)+ IF(AE21>0,AG21,0) -> 3928.2449 | AU21: =AS21+AT21 -> 14000.177 | AV21: =N21+U21+AB21+AI21 -> 1958512.4
D22: =D21+1 -> 14 | E22: =IF(MONTH(EDATE($E$5,D22))<7,YEAR(EDATE($E$5,D22)),YEAR(EDATE($E$5,D22))+1) -> 2028 | F22: =EDATE($E$5,D22) -> 46629 | G22: =MONTH(F22) -> 8 | H22: =DAY(EOMONTH(F22,0)) -> 31 | I22: PI | J22: =IF(I22="PI",IF(N21<=0,0,N21),(IF(I22="IO",J21,"")))*IF(N21<=0,0,1) -> 66037.008 | K22: =(IF(I22="PI",J22,IF(ISNUMBER(N21),N21,J22))*$K$3/365*$H22*IF(J22>0,1,0)) -> 338.19994 | L22: =IF(I22="IO",0,$K$6-K22)*IF(J22>0,1,0) -> 1299.8001 | M22: =IF(I22="IO",$K$6-K22+IF(ISNUMBER(M21),M21,0),IF(ISNUMBER(M21),M21,0)) -> 0 | N22: =(J22+K22-$K$6-IF(I22="PI",0,M22))*IF(J22>0,1,0) -> 64737.208 | P22: PI | Q22: =IF(P22="PI",IF(U21<=0,0,U21),(IF(P22="IO",Q21,"")))*IF(U21<=0,0,1) -> 528046.21 | R22: =(IF(P22="PI",Q22,IF(ISNUMBER(U21),U21,Q22))*$R$3/365*$H22*IF(Q22>0,1,0)) -> 2776.0764 | S22: =IF(P22="IO",0,$R$6-R22)*IF(Q22>0,1,0) -> 1004.9236 | T22: =IF(P22="IO",$R$6-R22+IF(ISNUMBER(T21),T21,0),IF(ISNUMBER(T21),T21,0)) -> 0 | U22: =(Q22+R22-$R$6-IF(P22="PI",0,T22))*IF(Q22>0,1,0) -> 527041.29 | W22: PI | X22: =IF(W22="PI",IF(AB21<=0,0,AB21),(IF(W22="IO",X21,"")))*IF(AB21<=0,0,1) -> 450162.16 | Y22: =(IF(W22="PI",X22,IF(ISNUMBER(AB21),AB21,X22))*$Y$3/365*$H22*IF(X22>0,1,0)) -> 2366.6197 | Z22: =IF(W22="IO",0,$Y$6-Y22)*IF(X22>0,1,0) -> 517.38034 | AA22: =IF(W22="IO",$Y$6-Y22+IF(ISNUMBER(AA21),AA21,0),IF(ISNUMBER(AA21),AA21,0)) -> 0 | AB22: =(X22+Y22-$Y$6-IF(W22="PI",0,AA22))*IF(X22>0,1,0) -> 449644.78 | AD22: PI | AE22: =IF(AD22="PI",IF(AI21<=0,0,AI21),(IF(AD22="IO",AE21,"")))*IF(AI21<=0,0,1) -> 914267.02 | AF22: =(IF(AD22="PI",AE22,IF(ISNUMBER(AI21),AI21,AE22))*$AF$3/365*$H22*IF(AE22>0,1,0)) -> 4915.2498 | AG22: =IF(AD22="IO",0,$AF$6-AF22)*IF(AE22>0,1,0) -> 1126.7502 | AH22: =IF(AD22="IO",$AF$6-AF22+IF(ISNUMBER(AH21),AH21,0),IF(ISNUMBER(AH21),AH21,0)) -> 0 | AI22: =(AE22+AF22-$AF$6-IF(AD22="PI",0,AH22))*IF(AE22>0,1,0) -> 913140.27 | AK22: =E22 -> 2028 | AL22: =G22 -> 8 | AM22: =IF($AK22=$AK21,R22+AM21,R22) -> 5557.4083 | AN22: =IF($AK22=$AK21,Y22+AN21,Y22) -> 4735.9451 | AO22: =IF($AK22=$AK21,AF22+AO21,AF22) -> 9836.5248 | AP22: =AM22+AN22 -> 10293.353 | AQ22: =IF(AK22=AK21,AQ21,0)+ IF(J22>0,$K$6,0)+ IF(Q22>0,$R$6,0)+ IF(X22>0,$Y$6,0) -> 16606 | AR22: =N22+U22+AB22 -> 1041423.3 | AS22: =AP22+AO22 -> 20129.878 | AT22: =IF(AK22=AK21,AT21,0)+ IF(J22>0,L22,0)+ IF(Q22>0,S22,0)+ IF(X22>0,Z22,0)+ IF(AE22>0,AG22,0) -> 7877.0991 | AU22: =AS22+AT22 -> 28006.977 | AV22: =N22+U22+AB22+AI22 -> 1954563.6 | AY22: Calendar Month | AZ22: 6
D23: =D22+1 -> 15 | E23: =IF(MONTH(EDATE($E$5,D23))<7,YEAR(EDATE($E$5,D23)),YEAR(EDATE($E$5,D23))+1) -> 2028 | F23: =EDATE($E$5,D23) -> 46660 | G23: =MONTH(F23) -> 9 | H23: =DAY(EOMONTH(F23,0)) -> 30 | I23: PI | J23: =IF(I23="PI",IF(N22<=0,0,N22),(IF(I23="IO",J22,"")))*IF(N22<=0,0,1) -> 64737.208 | K23: =(IF(I23="PI",J23,IF(ISNUMBER(N22),N22,J23))*$K$3/365*$H23*IF(J23>0,1,0)) -> 320.84824 | L23: =IF(I23="IO",0,$K$6-K23)*IF(J23>0,1,0) -> 1317.1518 | M23: =IF(I23="IO",$K$6-K23+IF(ISNUMBER(M22),M22,0),IF(ISNUMBER(M22),M22,0)) -> 0 | N23: =(J23+K23-$K$6-IF(I23="PI",0,M23))*IF(J23>0,1,0) -> 63420.056 | P23: PI | Q23: =IF(P23="PI",IF(U22<=0,0,U22),(IF(P23="IO",Q22,"")))*IF(U22<=0,0,1) -> 527041.29 | R23: =(IF(P23="PI",Q23,IF(ISNUMBER(U22),U22,Q23))*$R$3/365*$H23*IF(Q23>0,1,0)) -> 2681.4128 | S23: =IF(P23="IO",0,$R$6-R23)*IF(Q23>0,1,0) -> 1099.5872 | T23: =IF(P23="IO",$R$6-R23+IF(ISNUMBER(T22),T22,0),IF(ISNUMBER(T22),T22,0)) -> 0 | U23: =(Q23+R23-$R$6-IF(P23="PI",0,T23))*IF(Q23>0,1,0) -> 525941.7 | W23: PI | X23: =IF(W23="PI",IF(AB22<=0,0,AB22),(IF(W23="IO",X22,"")))*IF(AB22<=0,0,1) -> 449644.78 | Y23: =(IF(W23="PI",X23,IF(ISNUMBER(AB22),AB22,X23))*$Y$3/365*$H23*IF(X23>0,1,0)) -> 2287.6448 | Z23: =IF(W23="IO",0,$Y$6-Y23)*IF(X23>0,1,0) -> 596.35517 | AA23: =IF(W23="IO",$Y$6-Y23+IF(ISNUMBER(AA22),AA22,0),IF(ISNUMBER(AA22),AA22,0)) -> 0 | AB23: =(X23+Y23-$Y$6-IF(W23="PI",0,AA23))*IF(X23>0,1,0) -> 449048.43 | AD23: PI | AE23: =IF(AD23="PI",IF(AI22<=0,0,AI22),(IF(AD23="IO",AE22,"")))*IF(AI22<=0,0,1) -> 913140.27 | AF23: =(IF(AD23="PI",AE23,IF(ISNUMBER(AI22),AI22,AE23))*$AF$3/365*$H23*IF(AE23>0,1,0)) -> 4750.8312 | AG23: =IF(AD23="IO",0,$AF$6-AF23)*IF(AE23>0,1,0) -> 1291.1688 | AH23: =IF(AD23="IO",$AF$6-AF23+IF(ISNUMBER(AH22),AH22,0),IF(ISNUMBER(AH22),AH22,0)) -> 0 | AI23: =(AE23+AF23-$AF$6-IF(AD23="PI",0,AH23))*IF(AE23>0,1,0) -> 911849.1 | AK23: =E23 -> 2028 | AL23: =G23 -> 9 | AM23: =IF($AK23=$AK22,R23+AM22,R23) -> 8238.8211 | AN23: =IF($AK23=$AK22,Y23+AN22,Y23) -> 7023.5899 | AO23: =IF($AK23=$AK22,AF23+AO22,AF23) -> 14587.356 | AP23: =AM23+AN23 -> 15262.411 | AQ23: =IF(AK23=AK22,AQ22,0)+ IF(J23>0,$K$6,0)+ IF(Q23>0,$R$6,0)+ IF(X23>0,$Y$6,0) -> 24909 | AR23: =N23+U23+AB23 -> 1038410.2 | AS23: =AP23+AO23 -> 29849.767 | AT23: =IF(AK23=AK22,AT22,0)+ IF(J23>0,L23,0)+ IF(Q23>0,S23,0)+ IF(X23>0,Z23,0)+ IF(AE23>0,AG23,0) -> 12181.362 | AU23: =AS23+AT23 -> 42031.129 | AV23: =N23+U23+AB23+AI23 -> 1950259.3
D24: =D23+1 -> 16 | E24: =IF(MONTH(EDATE($E$5,D24))<7,YEAR(EDATE($E$5,D24)),YEAR(EDATE($E$5,D24))+1) -> 2028 | F24: =EDATE($E$5,D24) -> 46690 | G24: =MONTH(F24) -> 10 | H24: =DAY(EOMONTH(F24,0)) -> 31 | I24: PI | J24: =IF(I24="PI",IF(N23<=0,0,N23),(IF(I24="IO",J23,"")))*IF(N23<=0,0,1) -> 63420.056 | K24: =(IF(I24="PI",J24,IF(ISNUMBER(N23),N23,J24))*$K$3/365*$H24*IF(J24>0,1,0)) -> 324.79756 | L24: =IF(I24="IO",0,$K$6-K24)*IF(J24>0,1,0) -> 1313.2024 | M24: =IF(I24="IO",$K$6-K24+IF(ISNUMBER(M23),M23,0),IF(ISNUMBER(M23),M23,0)) -> 0 | N24: =(J24+K24-$K$6-IF(I24="PI",0,M24))*IF(J24>0,1,0) -> 62106.854 | P24: PI | Q24: =IF(P24="PI",IF(U23<=0,0,U23),(IF(P24="IO",Q23,"")))*IF(U23<=0,0,1) -> 525941.7 | R24: =(IF(P24="PI",Q24,IF(ISNUMBER(U23),U23,Q24))*$R$3/365*$H24*IF(Q24>0,1,0)) -> 2765.0124 | S24: =IF(P24="IO",0,$R$6-R24)*IF(Q24>0,1,0) -> 1015.9876 | T24: =IF(P24="IO",$R$6-R24+IF(ISNUMBER(T23),T23,0),IF(ISNUMBER(T23),T23,0)) -> 0 | U24: =(Q24+R24-$R$6-IF(P24="PI",0,T24))*IF(Q24>0,1,0) -> 524925.72 | W24: PI | X24: =IF(W24="PI",IF(AB23<=0,0,AB23),(IF(W24="IO",X23,"")))*IF(AB23<=0,0,1) -> 449048.43 | Y24: =(IF(W24="PI",X24,IF(ISNUMBER(AB23),AB23,X24))*$Y$3/365*$H24*IF(X24>0,1,0)) -> 2360.7645 | Z24: =IF(W24="IO",0,$Y$6-Y24)*IF(X24>0,1,0) -> 523.23554 | AA24: =IF(W24="IO",$Y$6-Y24+IF(ISNUMBER(AA23),AA23,0),IF(ISNUMBER(AA23),AA23,0)) -> 0 | AB24: =(X24+Y24-$Y$6-IF(W24="PI",0,AA24))*IF(X24>0,1,0) -> 448525.19 | AD24: PI | AE24: =IF(AD24="PI",IF(AI23<=0,0,AI23),(IF(AD24="IO",AE23,"")))*IF(AI23<=0,0,1) -> 911849.1 | AF24: =(IF(AD24="PI",AE24,IF(ISNUMBER(AI23),AI23,AE24))*$AF$3/365*$H24*IF(AE24>0,1,0)) -> 4902.2507 | AG24: =IF(AD24="IO",0,$AF$6-AF24)*IF(AE24>0,1,0) -> 1139.7493 | AH24: =IF(AD24="IO",$AF$6-AF24+IF(ISNUMBER(AH23),AH23,0),IF(ISNUMBER(AH23),AH23,0)) -> 0 | AI24: =(AE24+AF24-$AF$6-IF(AD24="PI",0,AH24))*IF(AE24>0,1,0) -> 910709.35 | AK24: =E24 -> 2028 | AL24: =G24 -> 10 | AM24: =IF($AK24=$AK23,R24+AM23,R24) -> 11003.834 | AN24: =IF($AK24=$AK23,Y24+AN23,Y24) -> 9384.3544 | AO24: =IF($AK24=$AK23,AF24+AO23,AF24) -> 19489.607 | AP24: =AM24+AN24 -> 20388.188 | AQ24: =IF(AK24=AK23,AQ23,0)+ IF(J24>0,$K$6,0)+ IF(Q24>0,$R$6,0)+ IF(X24>0,$Y$6,0) -> 33212 | AR24: =N24+U24+AB24 -> 1035557.8 | AS24: =AP24+AO24 -> 39877.795 | AT24: =IF(AK24=AK23,AT23,0)+ IF(J24>0,L24,0)+ IF(Q24>0,S24,0)+ IF(X24>0,Z24,0)+ IF(AE24>0,AG24,0) -> 16173.537 | AU24: =AS24+AT24 -> 56051.331 | AV24: =N24+U24+AB24+AI24 -> 1946267.1 | AZ24: Column Labels
D25: =D24+1 -> 17 | E25: =IF(MONTH(EDATE($E$5,D25))<7,YEAR(EDATE($E$5,D25)),YEAR(EDATE($E$5,D25))+1) -> 2028 | F25: =EDATE($E$5,D25) -> 46721 | G25: =MONTH(F25) -> 11 | H25: =DAY(EOMONTH(F25,0)) -> 30 | I25: PI | J25: =IF(I25="PI",IF(N24<=0,0,N24),(IF(I25="IO",J24,"")))*IF(N24<=0,0,1) -> 62106.854 | K25: =(IF(I25="PI",J25,IF(ISNUMBER(N24),N24,J25))*$K$3/365*$H25*IF(J25>0,1,0)) -> 307.81178 | L25: =IF(I25="IO",0,$K$6-K25)*IF(J25>0,1,0) -> 1330.1882 | M25: =IF(I25="IO",$K$6-K25+IF(ISNUMBER(M24),M24,0),IF(ISNUMBER(M24),M24,0)) -> 0 | N25: =(J25+K25-$K$6-IF(I25="PI",0,M25))*IF(J25>0,1,0) -> 60776.665 | P25: PI | Q25: =IF(P25="PI",IF(U24<=0,0,U24),(IF(P25="IO",Q24,"")))*IF(U24<=0,0,1) -> 524925.72 | R25: =(IF(P25="PI",Q25,IF(ISNUMBER(U24),U24,Q25))*$R$3/365*$H25*IF(Q25>0,1,0)) -> 2670.6495 | S25: =IF(P25="IO",0,$R$6-R25)*IF(Q25>0,1,0) -> 1110.3505 | T25: =IF(P25="IO",$R$6-R25+IF(ISNUMBER(T24),T24,0),IF(ISNUMBER(T24),T24,0)) -> 0 | U25: =(Q25+R25-$R$6-IF(P25="PI",0,T25))*IF(Q25>0,1,0) -> 523815.36 | W25: PI | X25: =IF(W25="PI",IF(AB24<=0,0,AB24),(IF(W25="IO",X24,"")))*IF(AB24<=0,0,1) -> 448525.19 | Y25: =(IF(W25="PI",X25,IF(ISNUMBER(AB24),AB24,X25))*$Y$3/365*$H25*IF(X25>0,1,0)) -> 2281.9487 | Z25: =IF(W25="IO",0,$Y$6-Y25)*IF(X25>0,1,0) -> 602.05128 | AA25: =IF(W25="IO",$Y$6-Y25+IF(ISNUMBER(AA24),AA24,0),IF(ISNUMBER(AA24),AA24,0)) -> 0 | AB25: =(X25+Y25-$Y$6-IF(W25="PI",0,AA25))*IF(X25>0,1,0) -> 447923.14 | AD25: PI | AE25: =IF(AD25="PI",IF(AI24<=0,0,AI24),(IF(AD25="IO",AE24,"")))*IF(AI24<=0,0,1) -> 910709.35 | AF25: =(IF(AD25="PI",AE25,IF(ISNUMBER(AI24),AI24,AE25))*$AF$3/365*$H25*IF(AE25>0,1,0)) -> 4738.1837 | AG25: =IF(AD25="IO",0,$AF$6-AF25)*IF(AE25>0,1,0) -> 1303.8163 | AH25: =IF(AD25="IO",$AF$6-AF25+IF(ISNUMBER(AH24),AH24,0),IF(ISNUMBER(AH24),AH24,0)) -> 0 | AI25: =(AE25+AF25-$AF$6-IF(AD25="PI",0,AH25))*IF(AE25>0,1,0) -> 909405.54 | AK25: =E25 -> 2028 | AL25: =G25 -> 11 | AM25: =IF($AK25=$AK24,R25+AM24,R25) -> 13674.483 | AN25: =IF($AK25=$AK24,Y25+AN24,Y25) -> 11666.303 | AO25: =IF($AK25=$AK24,AF25+AO24,AF25) -> 24227.79 | AP25: =AM25+AN25 -> 25340.786 | AQ25: =IF(AK25=AK24,AQ24,0)+ IF(J25>0,$K$6,0)+ IF(Q25>0,$R$6,0)+ IF(X25>0,$Y$6,0) -> 41515 | AR25: =N25+U25+AB25 -> 1032515.2 | AS25: =AP25+AO25 -> 49568.576 | AT25: =IF(AK25=AK24,AT24,0)+ IF(J25>0,L25,0)+ IF(Q25>0,S25,0)+ IF(X25>0,Z25,0)+ IF(AE25>0,AG25,0) -> 20519.943 | AU25: =AS25+AT25 -> 70088.52 | AV25: =N25+U25+AB25+AI25 -> 1941920.7 | AZ25: 2027 | BA25: 2028 | BB25: 2029 | BC25: 2030 | BD25: 2031 | BE25: 2032 | BF25: 2033 | BG25: 2034 | BH25: 2035 | BI25: 2036 | BJ25: 2037 | BK25: 2038 | BL25: 2039 | BM25: 2040 | BN25: 2041 | BO25: 2042 | BP25: 2043 | BQ25: 2044 | BR25: 2045 | BS25: 2046 | BT25: 2047 | BU25: 2048 | BV25: 2049 | BW25: 2050 | BX25: 2051 | BY25: 2052 | BZ25: 2053 | CA25: 2054 | CB25: 2055
D26: =D25+1 -> 18 | E26: =IF(MONTH(EDATE($E$5,D26))<7,YEAR(EDATE($E$5,D26)),YEAR(EDATE($E$5,D26))+1) -> 2028 | F26: =EDATE($E$5,D26) -> 46751 | G26: =MONTH(F26) -> 12 | H26: =DAY(EOMONTH(F26,0)) -> 31 | I26: PI | J26: =IF(I26="PI",IF(N25<=0,0,N25),(IF(I26="IO",J25,"")))*IF(N25<=0,0,1) -> 60776.665 | K26: =(IF(I26="PI",J26,IF(ISNUMBER(N25),N25,J26))*$K$3/365*$H26*IF(J26>0,1,0)) -> 311.25978 | L26: =IF(I26="IO",0,$K$6-K26)*IF(J26>0,1,0) -> 1326.7402 | M26: =IF(I26="IO",$K$6-K26+IF(ISNUMBER(M25),M25,0),IF(ISNUMBER(M25),M25,0)) -> 0 | N26: =(J26+K26-$K$6-IF(I26="PI",0,M26))*IF(J26>0,1,0) -> 59449.925 | P26: PI | Q26: =IF(P26="PI",IF(U25<=0,0,U25),(IF(P26="IO",Q25,"")))*IF(U25<=0,0,1) -> 523815.36 | R26: =(IF(P26="PI",Q26,IF(ISNUMBER(U25),U25,Q26))*$R$3/365*$H26*IF(Q26>0,1,0)) -> 2753.8337 | S26: =IF(P26="IO",0,$R$6-R26)*IF(Q26>0,1,0) -> 1027.1663 | T26: =IF(P26="IO",$R$6-R26+IF(ISNUMBER(T25),T25,0),IF(ISNUMBER(T25),T25,0)) -> 0 | U26: =(Q26+R26-$R$6-IF(P26="PI",0,T26))*IF(Q26>0,1,0) -> 522788.2 | W26: PI | X26: =IF(W26="PI",IF(AB25<=0,0,AB25),(IF(W26="IO",X25,"")))*IF(AB25<=0,0,1) -> 447923.14 | Y26: =(IF(W26="PI",X26,IF(ISNUMBER(AB25),AB25,X26))*$Y$3/365*$H26*IF(X26>0,1,0)) -> 2354.8485 | Z26: =IF(W26="IO",0,$Y$6-Y26)*IF(X26>0,1,0) -> 529.15146 | AA26: =IF(W26="IO",$Y$6-Y26+IF(ISNUMBER(AA25),AA25,0),IF(ISNUMBER(AA25),AA25,0)) -> 0 | AB26: =(X26+Y26-$Y$6-IF(W26="PI",0,AA26))*IF(X26>0,1,0) -> 447393.99 | AD26: PI | AE26: =IF(AD26="PI",IF(AI25<=0,0,AI25),(IF(AD26="IO",AE25,"")))*IF(AI25<=0,0,1) -> 909405.54 | AF26: =(IF(AD26="PI",AE26,IF(ISNUMBER(AI25),AI25,AE26))*$AF$3/365*$H26*IF(AE26>0,1,0)) -> 4889.1137 | AG26: =IF(AD26="IO",0,$AF$6-AF26)*IF(AE26>0,1,0) -> 1152.8863 | AH26: =IF(AD26="IO",$AF$6-AF26+IF(ISNUMBER(AH25),AH25,0),IF(ISNUMBER(AH25),AH25,0)) -> 0 | AI26: =(AE26+AF26-$AF$6-IF(AD26="PI",0,AH26))*IF(AE26>0,1,0) -> 908252.65 | AK26: =E26 -> 2028 | AL26: =G26 -> 12 | AM26: =IF($AK26=$AK25,R26+AM25,R26) -> 16428.317 | AN26: =IF($AK26=$AK25,Y26+AN25,Y26) -> 14021.152 | AO26: =IF($AK26=$AK25,AF26+AO25,AF26) -> 29116.904 | AP26: =AM26+AN26 -> 30449.468 | AQ26: =IF(AK26=AK25,AQ25,0)+ IF(J26>0,$K$6,0)+ IF(Q26>0,$R$6,0)+ IF(X26>0,$Y$6,0) -> 49818 | AR26: =N26+U26+AB26 -> 1029632.1 | AS26: =AP26+AO26 -> 59566.372 | AT26: =IF(AK26=AK25,AT25,0)+ IF(J26>0,L26,0)+ IF(Q26>0,S26,0)+ IF(X26>0,Z26,0)+ IF(AE26>0,AG26,0) -> 24555.888 | AU26: =AS26+AT26 -> 84122.26 | AV26: =N26+U26+AB26+AI26 -> 1937884.8 | AX26: Interest | AY26: Sum of Personal Interest | AZ26: 61287.021 | BA26: 60264.221 | BB26: 58840.899 | BC26: 57494.622 | BD26: 56062.605 | BE26: 54691.414 | BF26: 52928.845 | BG26: 51206.05 | BH26: 49373.536 | BI26: 47556.283 | BJ26: 45359.36 | BK26: 43154.49 | BL26: 40809.2 | BM26: 38420.833 | BN26: 35667.785 | BO26: 32845.692 | BP26: 29843.87 | BQ26: 26724.278 | BR26: 23259.197 | BS26: 19646.844 | BT26: 15804.432 | BU26: 11812.365 | BV26: 9424.0915 | BW26: 7820.2148 | BX26: 6114.1927 | BY26: 4310.8943 | BZ26: 2370.0011 | CA26: 448.52581 | CB26: 0
D27: =D26+1 -> 19 | E27: =IF(MONTH(EDATE($E$5,D27))<7,YEAR(EDATE($E$5,D27)),YEAR(EDATE($E$5,D27))+1) -> 2028 | F27: =EDATE($E$5,D27) -> 46782 | G27: =MONTH(F27) -> 1 | H27: =DAY(EOMONTH(F27,0)) -> 31 | I27: PI | J27: =IF(I27="PI",IF(N26<=0,0,N26),(IF(I27="IO",J26,"")))*IF(N26<=0,0,1) -> 59449.925 | K27: =(IF(I27="PI",J27,IF(ISNUMBER(N26),N26,J27))*$K$3/365*$H27*IF(J27>0,1,0)) -> 304.46506 | L27: =IF(I27="IO",0,$K$6-K27)*IF(J27>0,1,0) -> 1333.5349 | M27: =IF(I27="IO",$K$6-K27+IF(ISNUMBER(M26),M26,0),IF(ISNUMBER(M26),M26,0)) -> 0 | N27: =(J27+K27-$K$6-IF(I27="PI",0,M27))*IF(J27>0,1,0) -> 58116.39 | P27: PI | Q27: =IF(P27="PI",IF(U26<=0,0,U26),(IF(P27="IO",Q26,"")))*IF(U26<=0,0,1) -> 522788.2 | R27: =(IF(P27="PI",Q27,IF(ISNUMBER(U26),U26,Q27))*$R$3/365*$H27*IF(Q27>0,1,0)) -> 2748.4336 | S27: =IF(P27="IO",0,$R$6-R27)*IF(Q27>0,1,0) -> 1032.5664 | T27: =IF(P27="IO",$R$6-R27+IF(ISNUMBER(T26),T26,0),IF(ISNUMBER(T26),T26,0)) -> 0 | U27: =(Q27+R27-$R$6-IF(P27="PI",0,T27))*IF(Q27>0,1,0) -> 521755.63 | W27: PI | X27: =IF(W27="PI",IF(AB26<=0,0,AB26),(IF(W27="IO",X26,"")))*IF(AB26<=0,0,1) -> 447393.99 | Y27: =(IF(W27="PI",X27,IF(ISNUMBER(AB26),AB26,X27))*$Y$3/365*$H27*IF(X27>0,1,0)) -> 2352.0667 | Z27: =IF(W27="IO",0,$Y$6-Y27)*IF(X27>0,1,0) -> 531.93335 | AA27: =IF(W27="IO",$Y$6-Y27+IF(ISNUMBER(AA26),AA26,0),IF(ISNUMBER(AA26),AA26,0)) -> 0 | AB27: =(X27+Y27-$Y$6-IF(W27="PI",0,AA27))*IF(X27>0,1,0) -> 446862.06 | AD27: PI | AE27: =IF(AD27="PI",IF(AI26<=0,0,AI26),(IF(AD27="IO",AE26,"")))*IF(AI26<=0,0,1) -> 908252.65 | AF27: =(IF(AD27="PI",AE27,IF(ISNUMBER(AI26),AI26,AE27))*$AF$3/365*$H27*IF(AE27>0,1,0)) -> 4882.9156 | AG27: =IF(AD27="IO",0,$AF$6-AF27)*IF(AE27>0,1,0) -> 1159.0844 | AH27: =IF(AD27="IO",$AF$6-AF27+IF(ISNUMBER(AH26),AH26,0),IF(ISNUMBER(AH26),AH26,0)) -> 0 | AI27: =(AE27+AF27-$AF$6-IF(AD27="PI",0,AH27))*IF(AE27>0,1,0) -> 907093.57 | AK27: =E27 -> 2028 | AL27: =G27 -> 1 | AM27: =IF($AK27=$AK26,R27+AM26,R27) -> 19176.75 | AN27: =IF($AK27=$AK26,Y27+AN26,Y27) -> 16373.218 | AO27: =IF($AK27=$AK26,AF27+AO26,AF27) -> 33999.82 | AP27: =AM27+AN27 -> 35549.969 | AQ27: =IF(AK27=AK26,AQ26,0)+ IF(J27>0,$K$6,0)+ IF(Q27>0,$R$6,0)+ IF(X27>0,$Y$6,0) -> 58121 | AR27: =N27+U27+AB27 -> 1026734.1 | AS27: =AP27+AO27 -> 69549.788 | AT27: =IF(AK27=AK26,AT26,0)+ IF(J27>0,L27,0)+ IF(Q27>0,S27,0)+ IF(X27>0,Z27,0)+ IF(AE27>0,AG27,0) -> 28613.007 | AU27: =AS27+AT27 -> 98162.795 | AV27: =N27+U27+AB27+AI27 -> 1933827.6
D28: =D27+1 -> 20 | E28: =IF(MONTH(EDATE($E$5,D28))<7,YEAR(EDATE($E$5,D28)),YEAR(EDATE($E$5,D28))+1) -> 2028 | F28: =EDATE($E$5,D28) -> 46812 | G28: =MONTH(F28) -> 2 | H28: =DAY(EOMONTH(F28,0)) -> 29 | I28: PI | J28: =IF(I28="PI",IF(N27<=0,0,N27),(IF(I28="IO",J27,"")))*IF(N27<=0,0,1) -> 58116.39 | K28: =(IF(I28="PI",J28,IF(ISNUMBER(N27),N27,J28))*$K$3/365*$H28*IF(J28>0,1,0)) -> 278.43324 | L28: =IF(I28="IO",0,$K$6-K28)*IF(J28>0,1,0) -> 1359.5668 | M28: =IF(I28="IO",$K$6-K28+IF(ISNUMBER(M27),M27,0),IF(ISNUMBER(M27),M27,0)) -> 0 | N28: =(J28+K28-$K$6-IF(I28="PI",0,M28))*IF(J28>0,1,0) -> 56756.824 | P28: PI | Q28: =IF(P28="PI",IF(U27<=0,0,U27),(IF(P28="IO",Q27,"")))*IF(U27<=0,0,1) -> 521755.63 | R28: =(IF(P28="PI",Q28,IF(ISNUMBER(U27),U27,Q28))*$R$3/365*$H28*IF(Q28>0,1,0)) -> 2566.0371 | S28: =IF(P28="IO",0,$R$6-R28)*IF(Q28>0,1,0) -> 1214.9629 | T28: =IF(P28="IO",$R$6-R28+IF(ISNUMBER(T27),T27,0),IF(ISNUMBER(T27),T27,0)) -> 0 | U28: =(Q28+R28-$R$6-IF(P28="PI",0,T28))*IF(Q28>0,1,0) -> 520540.67 | W28: PI | X28: =IF(W28="PI",IF(AB27<=0,0,AB27),(IF(W28="IO",X27,"")))*IF(AB27<=0,0,1) -> 446862.06 | Y28: =(IF(W28="PI",X28,IF(ISNUMBER(AB27),AB27,X28))*$Y$3/365*$H28*IF(X28>0,1,0)) -> 2197.7043 | Z28: =IF(W28="IO",0,$Y$6-Y28)*IF(X28>0,1,0) -> 686.29568 | AA28: =IF(W28="IO",$Y$6-Y28+IF(ISNUMBER(AA27),AA27,0),IF(ISNUMBER(AA27),AA27,0)) -> 0 | AB28: =(X28+Y28-$Y$6-IF(W28="PI",0,AA28))*IF(X28>0,1,0) -> 446175.76 | AD28: PI | AE28: =IF(AD28="PI",IF(AI27<=0,0,AI27),(IF(AD28="IO",AE27,"")))*IF(AI27<=0,0,1) -> 907093.57 | AF28: =(IF(AD28="PI",AE28,IF(ISNUMBER(AI27),AI27,AE28))*$AF$3/365*$H28*IF(AE28>0,1,0)) -> 4562.0593 | AG28: =IF(AD28="IO",0,$AF$6-AF28)*IF(AE28>0,1,0) -> 1479.9407 | AH28: =IF(AD28="IO",$AF$6-AF28+IF(ISNUMBER(AH27),AH27,0),IF(ISNUMBER(AH27),AH27,0)) -> 0 | AI28: =(AE28+AF28-$AF$6-IF(AD28="PI",0,AH28))*IF(AE28>0,1,0) -> 905613.63 | AK28: =E28 -> 2028 | AL28: =G28 -> 2 | AM28: =IF($AK28=$AK27,R28+AM27,R28) -> 21742.787 | AN28: =IF($AK28=$AK27,Y28+AN27,Y28) -> 18570.923 | AO28: =IF($AK28=$AK27,AF28+AO27,AF28) -> 38561.879 | AP28: =AM28+AN28 -> 40313.71 | AQ28: =IF(AK28=AK27,AQ27,0)+ IF(J28>0,$K$6,0)+ IF(Q28>0,$R$6,0)+ IF(X28>0,$Y$6,0) -> 66424 | AR28: =N28+U28+AB28 -> 1023473.3 | AS28: =AP28+AO28 -> 78875.589 | AT28: =IF(AK28=AK27,AT27,0)+ IF(J28>0,L28,0)+ IF(Q28>0,S28,0)+ IF(X28>0,Z28,0)+ IF(AE28>0,AG28,0) -> 33353.773 | AU28: =AS28+AT28 -> 112229.36 | AV28: =N28+U28+AB28+AI28 -> 1929086.9 | AY28: Calendar Month | AZ28: 6
D29: =D28+1 -> 21 | E29: =IF(MONTH(EDATE($E$5,D29))<7,YEAR(EDATE($E$5,D29)),YEAR(EDATE($E$5,D29))+1) -> 2028 | F29: =EDATE($E$5,D29) -> 46842 | G29: =MONTH(F29) -> 3 | H29: =DAY(EOMONTH(F29,0)) -> 31 | I29: PI | J29: =IF(I29="PI",IF(N28<=0,0,N28),(IF(I29="IO",J28,"")))*IF(N28<=0,0,1) -> 56756.824 | K29: =(IF(I29="PI",J29,IF(ISNUMBER(N28),N28,J29))*$K$3/365*$H29*IF(J29>0,1,0)) -> 290.67269 | L29: =IF(I29="IO",0,$K$6-K29)*IF(J29>0,1,0) -> 1347.3273 | M29: =IF(I29="IO",$K$6-K29+IF(ISNUMBER(M28),M28,0),IF(ISNUMBER(M28),M28,0)) -> 0 | N29: =(J29+K29-$K$6-IF(I29="PI",0,M29))*IF(J29>0,1,0) -> 55409.496 | P29: PI | Q29: =IF(P29="PI",IF(U28<=0,0,U28),(IF(P29="IO",Q28,"")))*IF(U28<=0,0,1) -> 520540.67 | R29: =(IF(P29="PI",Q29,IF(ISNUMBER(U28),U28,Q29))*$R$3/365*$H29*IF(Q29>0,1,0)) -> 2736.6178 | S29: =IF(P29="IO",0,$R$6-R29)*IF(Q29>0,1,0) -> 1044.3822 | T29: =IF(P29="IO",$R$6-R29+IF(ISNUMBER(T28),T28,0),IF(ISNUMBER(T28),T28,0)) -> 0 | U29: =(Q29+R29-$R$6-IF(P29="PI",0,T29))*IF(Q29>0,1,0) -> 519496.29 | W29: PI | X29: =IF(W29="PI",IF(AB28<=0,0,AB28),(IF(W29="IO",X28,"")))*IF(AB28<=0,0,1) -> 446175.76 | Y29: =(IF(W29="PI",X29,IF(ISNUMBER(AB28),AB28,X29))*$Y$3/365*$H29*IF(X29>0,1,0)) -> 2345.6621 | Z29: =IF(W29="IO",0,$Y$6-Y29)*IF(X29>0,1,0) -> 538.33789 | AA29: =IF(W29="IO",$Y$6-Y29+IF(ISNUMBER(AA28),AA28,0),IF(ISNUMBER(AA28),AA28,0)) -> 0 | AB29: =(X29+Y29-$Y$6-IF(W29="PI",0,AA29))*IF(X29>0,1,0) -> 445637.42 | AD29: PI | AE29: =IF(AD29="PI",IF(AI28<=0,0,AI28),(IF(AD29="IO",AE28,"")))*IF(AI28<=0,0,1) -> 905613.63 | AF29: =(IF(AD29="PI",AE29,IF(ISNUMBER(AI28),AI28,AE29))*$AF$3/365*$H29*IF(AE29>0,1,0)) -> 4868.7277 | AG29: =IF(AD29="IO",0,$AF$6-AF29)*IF(AE29>0,1,0) -> 1173.2723 | AH29: =IF(AD29="IO",$AF$6-AF29+IF(ISNUMBER(AH28),AH28,0),IF(ISNUMBER(AH28),AH28,0)) -> 0 | AI29: =(AE29+AF29-$AF$6-IF(AD29="PI",0,AH29))*IF(AE29>0,1,0) -> 904440.35 | AK29: =E29 -> 2028 | AL29: =G29 -> 3 | AM29: =IF($AK29=$AK28,R29+AM28,R29) -> 24479.405 | AN29: =IF($AK29=$AK28,Y29+AN28,Y29) -> 20916.585 | AO29: =IF($AK29=$AK28,AF29+AO28,AF29) -> 43430.607 | AP29: =AM29+AN29 -> 45395.99 | AQ29: =IF(AK29=AK28,AQ28,0)+ IF(J29>0,$K$6,0)+ IF(Q29>0,$R$6,0)+ IF(X29>0,$Y$6,0) -> 74727 | AR29: =N29+U29+AB29 -> 1020543.2 | AS29: =AP29+AO29 -> 88826.597 | AT29: =IF(AK29=AK28,AT28,0)+ IF(J29>0,L29,0)+ IF(Q29>0,S29,0)+ IF(X29>0,Z29,0)+ IF(AE29>0,AG29,0) -> 37457.092 | AU29: =AS29+AT29 -> 126283.69 | AV29: =N29+U29+AB29+AI29 -> 1924983.6
D30: =D29+1 -> 22 | E30: =IF(MONTH(EDATE($E$5,D30))<7,YEAR(EDATE($E$5,D30)),YEAR(EDATE($E$5,D30))+1) -> 2028 | F30: =EDATE($E$5,D30) -> 46873 | G30: =MONTH(F30) -> 4 | H30: =DAY(EOMONTH(F30,0)) -> 30 | I30: PI | J30: =IF(I30="PI",IF(N29<=0,0,N29),(IF(I30="IO",J29,"")))*IF(N29<=0,0,1) -> 55409.496 | K30: =(IF(I30="PI",J30,IF(ISNUMBER(N29),N29,J30))*$K$3/365*$H30*IF(J30>0,1,0)) -> 274.61857 | L30: =IF(I30="IO",0,$K$6-K30)*IF(J30>0,1,0) -> 1363.3814 | M30: =IF(I30="IO",$K$6-K30+IF(ISNUMBER(M29),M29,0),IF(ISNUMBER(M29),M29,0)) -> 0 | N30: =(J30+K30-$K$6-IF(I30="PI",0,M30))*IF(J30>0,1,0) -> 54046.115 | P30: PI | Q30: =IF(P30="PI",IF(U29<=0,0,U29),(IF(P30="IO",Q29,"")))*IF(U29<=0,0,1) -> 519496.29 | R30: =(IF(P30="PI",Q30,IF(ISNUMBER(U29),U29,Q30))*$R$3/365*$H30*IF(Q30>0,1,0)) -> 2643.0263 | S30: =IF(P30="IO",0,$R$6-R30)*IF(Q30>0,1,0) -> 1137.9737 | T30: =IF(P30="IO",$R$6-R30+IF(ISNUMBER(T29),T29,0),IF(ISNUMBER(T29),T29,0)) -> 0 | U30: =(Q30+R30-$R$6-IF(P30="PI",0,T30))*IF(Q30>0,1,0) -> 518358.31 | W30: PI | X30: =IF(W30="PI",IF(AB29<=0,0,AB29),(IF(W30="IO",X29,"")))*IF(AB29<=0,0,1) -> 445637.42 | Y30: =(IF(W30="PI",X30,IF(ISNUMBER(AB29),AB29,X30))*$Y$3/365*$H30*IF(X30>0,1,0)) -> 2267.2567 | Z30: =IF(W30="IO",0,$Y$6-Y30)*IF(X30>0,1,0) -> 616.7433 | AA30: =IF(W30="IO",$Y$6-Y30+IF(ISNUMBER(AA29),AA29,0),IF(ISNUMBER(AA29),AA29,0)) -> 0 | AB30: =(X30+Y30-$Y$6-IF(W30="PI",0,AA30))*IF(X30>0,1,0) -> 445020.68 | AD30: PI | AE30: =IF(AD30="PI",IF(AI29<=0,0,AI29),(IF(AD30="IO",AE29,"")))*IF(AI29<=0,0,1) -> 904440.35 | AF30: =(IF(AD30="PI",AE30,IF(ISNUMBER(AI29),AI29,AE30))*$AF$3/365*$H30*IF(AE30>0,1,0)) -> 4705.5678 | AG30: =IF(AD30="IO",0,$AF$6-AF30)*IF(AE30>0,1,0) -> 1336.4322 | AH30: =IF(AD30="IO",$AF$6-AF30+IF(ISNUMBER(AH29),AH29,0),IF(ISNUMBER(AH29),AH29,0)) -> 0 | AI30: =(AE30+AF30-$AF$6-IF(AD30="PI",0,AH30))*IF(AE30>0,1,0) -> 903103.92 | AK30: =E30 -> 2028 | AL30: =G30 -> 4 | AM30: =IF($AK30=$AK29,R30+AM29,R30) -> 27122.431 | AN30: =IF($AK30=$AK29,Y30+AN29,Y30) -> 23183.841 | AO30: =IF($AK30=$AK29,AF30+AO29,AF30) -> 48136.174 | AP30: =AM30+AN30 -> 50306.273 | AQ30: =IF(AK30=AK29,AQ29,0)+ IF(J30>0,$K$6,0)+ IF(Q30>0,$R$6,0)+ IF(X30>0,$Y$6,0) -> 83030 | AR30: =N30+U30+AB30 -> 1017425.1 | AS30: =AP30+AO30 -> 98442.447 | AT30: =IF(AK30=AK29,AT29,0)+ IF(J30>0,L30,0)+ IF(Q30>0,S30,0)+ IF(X30>0,Z30,0)+ IF(AE30>0,AG30,0) -> 41911.623 | AU30: =AS30+AT30 -> 140354.07 | AV30: =N30+U30+AB30+AI30 -> 1920529 | AZ30: Column Labels
D31: =D30+1 -> 23 | E31: =IF(MONTH(EDATE($E$5,D31))<7,YEAR(EDATE($E$5,D31)),YEAR(EDATE($E$5,D31))+1) -> 2028 | F31: =EDATE($E$5,D31) -> 46903 | G31: =MONTH(F31) -> 5 | H31: =DAY(EOMONTH(F31,0)) -> 31 | I31: PI | J31: =IF(I31="PI",IF(N30<=0,0,N30),(IF(I31="IO",J30,"")))*IF(N30<=0,0,1) -> 54046.115 | K31: =(IF(I31="PI",J31,IF(ISNUMBER(N30),N30,J31))*$K$3/365*$H31*IF(J31>0,1,0)) -> 276.79014 | L31: =IF(I31="IO",0,$K$6-K31)*IF(J31>0,1,0) -> 1361.2099 | M31: =IF(I31="IO",$K$6-K31+IF(ISNUMBER(M30),M30,0),IF(ISNUMBER(M30),M30,0)) -> 0 | N31: =(J31+K31-$K$6-IF(I31="PI",0,M31))*IF(J31>0,1,0) -> 52684.905 | P31: PI | Q31: =IF(P31="PI",IF(U30<=0,0,U30),(IF(P31="IO",Q30,"")))*IF(U30<=0,0,1) -> 518358.31 | R31: =(IF(P31="PI",Q31,IF(ISNUMBER(U30),U30,Q31))*$R$3/365*$H31*IF(Q31>0,1,0)) -> 2725.1446 | S31: =IF(P31="IO",0,$R$6-R31)*IF(Q31>0,1,0) -> 1055.8554 | T31: =IF(P31="IO",$R$6-R31+IF(ISNUMBER(T30),T30,0),IF(ISNUMBER(T30),T30,0)) -> 0 | U31: =(Q31+R31-$R$6-IF(P31="PI",0,T31))*IF(Q31>0,1,0) -> 517302.46 | W31: PI | X31: =IF(W31="PI",IF(AB30<=0,0,AB30),(IF(W31="IO",X30,"")))*IF(AB30<=0,0,1) -> 445020.68 | Y31: =(IF(W31="PI",X31,IF(ISNUMBER(AB30),AB30,X31))*$Y$3/365*$H31*IF(X31>0,1,0)) -> 2339.5895 | Z31: =IF(W31="IO",0,$Y$6-Y31)*IF(X31>0,1,0) -> 544.41046 | AA31: =IF(W31="IO",$Y$6-Y31+IF(ISNUMBER(AA30),AA30,0),IF(ISNUMBER(AA30),AA30,0)) -> 0 | AB31: =(X31+Y31-$Y$6-IF(W31="PI",0,AA31))*IF(X31>0,1,0) -> 444476.27 | AD31: PI | AE31: =IF(AD31="PI",IF(AI30<=0,0,AI30),(IF(AD31="IO",AE30,"")))*IF(AI30<=0,0,1) -> 903103.92 | AF31: =(IF(AD31="PI",AE31,IF(ISNUMBER(AI30),AI30,AE31))*$AF$3/365*$H31*IF(AE31>0,1,0)) -> 4855.2351 | AG31: =IF(AD31="IO",0,$AF$6-AF31)*IF(AE31>0,1,0) -> 1186.7649 | AH31: =IF(AD31="IO",$AF$6-AF31+IF(ISNUMBER(AH30),AH30,0),IF(ISNUMBER(AH30),AH30,0)) -> 0 | AI31: =(AE31+AF31-$AF$6-IF(AD31="PI",0,AH31))*IF(AE31>0,1,0) -> 901917.16 | AK31: =E31 -> 2028 | AL31: =G31 -> 5 | AM31: =IF($AK31=$AK30,R31+AM30,R31) -> 29847.576 | AN31: =IF($AK31=$AK30,Y31+AN30,Y31) -> 25523.431 | AO31: =IF($AK31=$AK30,AF31+AO30,AF31) -> 52991.41 | AP31: =AM31+AN31 -> 55371.007 | AQ31: =IF(AK31=AK30,AQ30,0)+ IF(J31>0,$K$6,0)+ IF(Q31>0,$R$6,0)+ IF(X31>0,$Y$6,0) -> 91333 | AR31: =N31+U31+AB31 -> 1014463.6 | AS31: =AP31+AO31 -> 108362.42 | AT31: =IF(AK31=AK30,AT30,0)+ IF(J31>0,L31,0)+ IF(Q31>0,S31,0)+ IF(X31>0,Z31,0)+ IF(AE31>0,AG31,0) -> 46059.864 | AU31: =AS31+AT31 -> 154422.28 | AV31: =N31+U31+AB31+AI31 -> 1916380.8 | AZ31: 2027 | BA31: 2028 | BB31: 2029 | BC31: 2030 | BD31: 2031 | BE31: 2032 | BF31: 2033 | BG31: 2034 | BH31: 2035 | BI31: 2036 | BJ31: 2037 | BK31: 2038 | BL31: 2039 | BM31: 2040 | BN31: 2041 | BO31: 2042 | BP31: 2043 | BQ31: 2044 | BR31: 2045 | BS31: 2046 | BT31: 2047 | BU31: 2048 | BV31: 2049 | BW31: 2050 | BX31: 2051 | BY31: 2052 | BZ31: 2053 | CA31: 2054 | CB31: 2055
D32: =D31+1 -> 24 | E32: =IF(MONTH(EDATE($E$5,D32))<7,YEAR(EDATE($E$5,D32)),YEAR(EDATE($E$5,D32))+1) -> 2028 | F32: =EDATE($E$5,D32) -> 46934 | G32: =MONTH(F32) -> 6 | H32: =DAY(EOMONTH(F32,0)) -> 30 | I32: PI | J32: =IF(I32="PI",IF(N31<=0,0,N31),(IF(I32="IO",J31,"")))*IF(N31<=0,0,1) -> 52684.905 | K32: =(IF(I32="PI",J32,IF(ISNUMBER(N31),N31,J32))*$K$3/365*$H32*IF(J32>0,1,0)) -> 261.11505 | L32: =IF(I32="IO",0,$K$6-K32)*IF(J32>0,1,0) -> 1376.885 | M32: =IF(I32="IO",$K$6-K32+IF(ISNUMBER(M31),M31,0),IF(ISNUMBER(M31),M31,0)) -> 0 | N32: =(J32+K32-$K$6-IF(I32="PI",0,M32))*IF(J32>0,1,0) -> 51308.02 | P32: PI | Q32: =IF(P32="PI",IF(U31<=0,0,U31),(IF(P32="IO",Q31,"")))*IF(U31<=0,0,1) -> 517302.46 | R32: =(IF(P32="PI",Q32,IF(ISNUMBER(U31),U31,Q32))*$R$3/365*$H32*IF(Q32>0,1,0)) -> 2631.8648 | S32: =IF(P32="IO",0,$R$6-R32)*IF(Q32>0,1,0) -> 1149.1352 | T32: =IF(P32="IO",$R$6-R32+IF(ISNUMBER(T31),T31,0),IF(ISNUMBER(T31),T31,0)) -> 0 | U32: =(Q32+R32-$R$6-IF(P32="PI",0,T32))*IF(Q32>0,1,0) -> 516153.32 | W32: PI | X32: =IF(W32="PI",IF(AB31<=0,0,AB31),(IF(W32="IO",X31,"")))*IF(AB31<=0,0,1) -> 444476.27 | Y32: =(IF(W32="PI",X32,IF(ISNUMBER(AB31),AB31,X32))*$Y$3/365*$H32*IF(X32>0,1,0)) -> 2261.3491 | Z32: =IF(W32="IO",0,$Y$6-Y32)*IF(X32>0,1,0) -> 622.65087 | AA32: =IF(W32="IO",$Y$6-Y32+IF(ISNUMBER(AA31),AA31,0),IF(ISNUMBER(AA31),AA31,0)) -> 0 | AB32: =(X32+Y32-$Y$6-IF(W32="PI",0,AA32))*IF(X32>0,1,0) -> 443853.62 | AD32: PI | AE32: =IF(AD32="PI",IF(AI31<=0,0,AI31),(IF(AD32="IO",AE31,"")))*IF(AI31<=0,0,1) -> 901917.16 | AF32: =(IF(AD32="PI",AE32,IF(ISNUMBER(AI31),AI31,AE32))*$AF$3/365*$H32*IF(AE32>0,1,0)) -> 4692.4402 | AG32: =IF(AD32="IO",0,$AF$6-AF32)*IF(AE32>0,1,0) -> 1349.5598 | AH32: =IF(AD32="IO",$AF$6-AF32+IF(ISNUMBER(AH31),AH31,0),IF(ISNUMBER(AH31),AH31,0)) -> 0 | AI32: =(AE32+AF32-$AF$6-IF(AD32="PI",0,AH32))*IF(AE32>0,1,0) -> 900567.6 | AK32: =E32 -> 2028 | AL32: =G32 -> 6 | AM32: =IF($AK32=$AK31,R32+AM31,R32) -> 32479.441 | AN32: =IF($AK32=$AK31,Y32+AN31,Y32) -> 27784.78 | AO32: =IF($AK32=$AK31,AF32+AO31,AF32) -> 57683.85 | AP32: =AM32+AN32 -> 60264.221 | AQ32: =IF(AK32=AK31,AQ31,0)+ IF(J32>0,$K$6,0)+ IF(Q32>0,$R$6,0)+ IF(X32>0,$Y$6,0) -> 99636 | AR32: =N32+U32+AB32 -> 1011315 | AS32: =AP32+AO32 -> 117948.07 | AT32: =IF(AK32=AK31,AT31,0)+ IF(J32>0,L32,0)+ IF(Q32>0,S32,0)+ IF(X32>0,Z32,0)+ IF(AE32>0,AG32,0) -> 50558.094 | AU32: =AS32+AT32 -> 168506.17 | AV32: =N32+U32+AB32+AI32 -> 1911882.6 | AX32: 308 Interest | AY32: Sum of 308 Interest | AZ32: 33166.442 | BA32: 32479.441 | BB32: 31568.029 | BC32: 30688.901 | BD32: 29753.785 | BE32: 28839.211 | BF32: 27706.198 | BG32: 26581.124 | BH32: 25384.397 | BI32: 24178.449 | BJ32: 22761.711 | BK32: 21321.739 | BL32: 19790.061 | BM32: 18211.053 | BN32: 16431.047 | BO32: 14587.897 | BP32: 12627.363 | BQ32: 10570.71 | BR32: 8325.5952 | BS32: 5966.2367 | BT32: 3456.6189 | BU32: 852.16036 | BV32: 0 | BW32: 0 | BX32: 0 | BY32: 0 | BZ32: 0 | CA32: 0 | CB32: 0
D33: =D32+1 -> 25 | E33: =IF(MONTH(EDATE($E$5,D33))<7,YEAR(EDATE($E$5,D33)),YEAR(EDATE($E$5,D33))+1) -> 2029 | F33: =EDATE($E$5,D33) -> 46964 | G33: =MONTH(F33) -> 7 | H33: =DAY(EOMONTH(F33,0)) -> 31 | I33: PI | J33: =IF(I33="PI",IF(N32<=0,0,N32),(IF(I33="IO",J32,"")))*IF(N32<=0,0,1) -> 51308.02 | K33: =(IF(I33="PI",J33,IF(ISNUMBER(N32),N32,J33))*$K$3/365*$H33*IF(J33>0,1,0)) -> 262.76735 | L33: =IF(I33="IO",0,$K$6-K33)*IF(J33>0,1,0) -> 1375.2327 | M33: =IF(I33="IO",$K$6-K33+IF(ISNUMBER(M32),M32,0),IF(ISNUMBER(M32),M32,0)) -> 0 | N33: =(J33+K33-$K$6-IF(I33="PI",0,M33))*IF(J33>0,1,0) -> 49932.787 | P33: PI | Q33: =IF(P33="PI",IF(U32<=0,0,U32),(IF(P33="IO",Q32,"")))*IF(U32<=0,0,1) -> 516153.32 | R33: =(IF(P33="PI",Q33,IF(ISNUMBER(U32),U32,Q33))*$R$3/365*$H33*IF(Q33>0,1,0)) -> 2713.5524 | S33: =IF(P33="IO",0,$R$6-R33)*IF(Q33>0,1,0) -> 1067.4476 | T33: =IF(P33="IO",$R$6-R33+IF(ISNUMBER(T32),T32,0),IF(ISNUMBER(T32),T32,0)) -> 0 | U33: =(Q33+R33-$R$6-IF(P33="PI",0,T33))*IF(Q33>0,1,0) -> 515085.88 | W33: PI | X33: =IF(W33="PI",IF(AB32<=0,0,AB32),(IF(W33="IO",X32,"")))*IF(AB32<=0,0,1) -> 443853.62 | Y33: =(IF(W33="PI",X33,IF(ISNUMBER(AB32),AB32,X33))*$Y$3/365*$H33*IF(X33>0,1,0)) -> 2333.454 | Z33: =IF(W33="IO",0,$Y$6-Y33)*IF(X33>0,1,0) -> 550.546 | AA33: =IF(W33="IO",$Y$6-Y33+IF(ISNUMBER(AA32),AA32,0),IF(ISNUMBER(AA32),AA32,0)) -> 0 | AB33: =(X33+Y33-$Y$6-IF(W33="PI",0,AA33))*IF(X33>0,1,0) -> 443303.07 | AD33: PI | AE33: =IF(AD33="PI",IF(AI32<=0,0,AI32),(IF(AD33="IO",AE32,"")))*IF(AI32<=0,0,1) -> 900567.6 | AF33: =(IF(AD33="PI",AE33,IF(ISNUMBER(AI32),AI32,AE33))*$AF$3/365*$H33*IF(AE33>0,1,0)) -> 4841.5994 | AG33: =IF(AD33="IO",0,$AF$6-AF33)*IF(AE33>0,1,0) -> 1200.4006 | AH33: =IF(AD33="IO",$AF$6-AF33+IF(ISNUMBER(AH32),AH32,0),IF(ISNUMBER(AH32),AH32,0)) -> 0 | AI33: =(AE33+AF33-$AF$6-IF(AD33="PI",0,AH33))*IF(AE33>0,1,0) -> 899367.2 | AK33: =E33 -> 2029 | AL33: =G33 -> 7 | AM33: =IF($AK33=$AK32,R33+AM32,R33) -> 2713.5524 | AN33: =IF($AK33=$AK32,Y33+AN32,Y33) -> 2333.454 | AO33: =IF($AK33=$AK32,AF33+AO32,AF33) -> 4841.5994 | AP33: =AM33+AN33 -> 5047.0064 | AQ33: =IF(AK33=AK32,AQ32,0)+ IF(J33>0,$K$6,0)+ IF(Q33>0,$R$6,0)+ IF(X33>0,$Y$6,0) -> 8303 | AR33: =N33+U33+AB33 -> 1008321.7 | AS33: =AP33+AO33 -> 9888.6058 | AT33: =IF(AK33=AK32,AT32,0)+ IF(J33>0,L33,0)+ IF(Q33>0,S33,0)+ IF(X33>0,Z33,0)+ IF(AE33>0,AG33,0) -> 4193.6269 | AU33: =AS33+AT33 -> 14082.233 | AV33: =N33+U33+AB33+AI33 -> 1907688.9
D34: =D33+1 -> 26 | E34: =IF(MONTH(EDATE($E$5,D34))<7,YEAR(EDATE($E$5,D34)),YEAR(EDATE($E$5,D34))+1) -> 2029 | F34: =EDATE($E$5,D34) -> 46995 | G34: =MONTH(F34) -> 8 | H34: =DAY(EOMONTH(F34,0)) -> 31 | I34: PI | J34: =IF(I34="PI",IF(N33<=0,0,N33),(IF(I34="IO",J33,"")))*IF(N33<=0,0,1) -> 49932.787 | K34: =(IF(I34="PI",J34,IF(ISNUMBER(N33),N33,J34))*$K$3/365*$H34*IF(J34>0,1,0)) -> 255.72427 | L34: =IF(I34="IO",0,$K$6-K34)*IF(J34>0,1,0) -> 1382.2757 | M34: =IF(I34="IO",$K$6-K34+IF(ISNUMBER(M33),M33,0),IF(ISNUMBER(M33),M33,0)) -> 0 | N34: =(J34+K34-$K$6-IF(I34="PI",0,M34))*IF(J34>0,1,0) -> 48550.512 | P34: PI | Q34: =IF(P34="PI",IF(U33<=0,0,U33),(IF(P34="IO",Q33,"")))*IF(U33<=0,0,1) -> 515085.88 | R34: =(IF(P34="PI",Q34,IF(ISNUMBER(U33),U33,Q34))*$R$3/365*$H34*IF(Q34>0,1,0)) -> 2707.9405 | S34: =IF(P34="IO",0,$R$6-R34)*IF(Q34>0,1,0) -> 1073.0595 | T34: =IF(P34="IO",$R$6-R34+IF(ISNUMBER(T33),T33,0),IF(ISNUMBER(T33),T33,0)) -> 0 | U34: =(Q34+R34-$R$6-IF(P34="PI",0,T34))*IF(Q34>0,1,0) -> 514012.82 | W34: PI | X34: =IF(W34="PI",IF(AB33<=0,0,AB33),(IF(W34="IO",X33,"")))*IF(AB33<=0,0,1) -> 443303.07 | Y34: =(IF(W34="PI",X34,IF(ISNUMBER(AB33),AB33,X34))*$Y$3/365*$H34*IF(X34>0,1,0)) -> 2330.5596 | Z34: =IF(W34="IO",0,$Y$6-Y34)*IF(X34>0,1,0) -> 553.44037 | AA34: =IF(W34="IO",$Y$6-Y34+IF(ISNUMBER(AA33),AA33,0),IF(ISNUMBER(AA33),AA33,0)) -> 0 | AB34: =(X34+Y34-$Y$6-IF(W34="PI",0,AA34))*IF(X34>0,1,0) -> 442749.63 | AD34: PI | AE34: =IF(AD34="PI",IF(AI33<=0,0,AI33),(IF(AD34="IO",AE33,"")))*IF(AI33<=0,0,1) -> 899367.2 | AF34: =(IF(AD34="PI",AE34,IF(ISNUMBER(AI33),AI33,AE34))*$AF$3/365*$H34*IF(AE34>0,1,0)) -> 4835.1459 | AG34: =IF(AD34="IO",0,$AF$6-AF34)*IF(AE34>0,1,0) -> 1206.8541 | AH34: =IF(AD34="IO",$AF$6-AF34+IF(ISNUMBER(AH33),AH33,0),IF(ISNUMBER(AH33),AH33,0)) -> 0 | AI34: =(AE34+AF34-$AF$6-IF(AD34="PI",0,AH34))*IF(AE34>0,1,0) -> 898160.34 | AK34: =E34 -> 2029 | AL34: =G34 -> 8 | AM34: =IF($AK34=$AK33,R34+AM33,R34) -> 5421.4929 | AN34: =IF($AK34=$AK33,Y34+AN33,Y34) -> 4664.0136 | AO34: =IF($AK34=$AK33,AF34+AO33,AF34) -> 9676.7453 | AP34: =AM34+AN34 -> 10085.507 | AQ34: =IF(AK34=AK33,AQ33,0)+ IF(J34>0,$K$6,0)+ IF(Q34>0,$R$6,0)+ IF(X34>0,$Y$6,0) -> 16606 | AR34: =N34+U34+AB34 -> 1005313 | AS34: =AP34+AO34 -> 19762.252 | AT34: =IF(AK34=AK33,AT33,0)+ IF(J34>0,L34,0)+ IF(Q34>0,S34,0)+ IF(X34>0,Z34,0)+ IF(AE34>0,AG34,0) -> 8409.2566 | AU34: =AS34+AT34 -> 28171.508 | AV34: =N34+U34+AB34+AI34 -> 1903473.3 | AY34: Calendar Month | AZ34: 6
D35: =D34+1 -> 27 | E35: =IF(MONTH(EDATE($E$5,D35))<7,YEAR(EDATE($E$5,D35)),YEAR(EDATE($E$5,D35))+1) -> 2029 | F35: =EDATE($E$5,D35) -> 47026 | G35: =MONTH(F35) -> 9 | H35: =DAY(EOMONTH(F35,0)) -> 30 | I35: PI | J35: =IF(I35="PI",IF(N34<=0,0,N34),(IF(I35="IO",J34,"")))*IF(N34<=0,0,1) -> 48550.512 | K35: =(IF(I35="PI",J35,IF(ISNUMBER(N34),N34,J35))*$K$3/365*$H35*IF(J35>0,1,0)) -> 240.62432 | L35: =IF(I35="IO",0,$K$6-K35)*IF(J35>0,1,0) -> 1397.3757 | M35: =IF(I35="IO",$K$6-K35+IF(ISNUMBER(M34),M34,0),IF(ISNUMBER(M34),M34,0)) -> 0 | N35: =(J35+K35-$K$6-IF(I35="PI",0,M35))*IF(J35>0,1,0) -> 47153.136 | P35: PI | Q35: =IF(P35="PI",IF(U34<=0,0,U34),(IF(P35="IO",Q34,"")))*IF(U34<=0,0,1) -> 514012.82 | R35: =(IF(P35="PI",Q35,IF(ISNUMBER(U34),U34,Q35))*$R$3/365*$H35*IF(Q35>0,1,0)) -> 2615.1282 | S35: =IF(P35="IO",0,$R$6-R35)*IF(Q35>0,1,0) -> 1165.8718 | T35: =IF(P35="IO",$R$6-R35+IF(ISNUMBER(T34),T34,0),IF(ISNUMBER(T34),T34,0)) -> 0 | U35: =(Q35+R35-$R$6-IF(P35="PI",0,T35))*IF(Q35>0,1,0) -> 512846.94 | W35: PI | X35: =IF(W35="PI",IF(AB34<=0,0,AB34),(IF(W35="IO",X34,"")))*IF(AB34<=0,0,1) -> 442749.63 | Y35: =(IF(W35="PI",X35,IF(ISNUMBER(AB34),AB34,X35))*$Y$3/365*$H35*IF(X35>0,1,0)) -> 2252.5646 | Z35: =IF(W35="IO",0,$Y$6-Y35)*IF(X35>0,1,0) -> 631.43543 | AA35: =IF(W35="IO",$Y$6-Y35+IF(ISNUMBER(AA34),AA34,0),IF(ISNUMBER(AA34),AA34,0)) -> 0 | AB35: =(X35+Y35-$Y$6-IF(W35="PI",0,AA35))*IF(X35>0,1,0) -> 442118.2 | AD35: PI | AE35: =IF(AD35="PI",IF(AI34<=0,0,AI34),(IF(AD35="IO",AE34,"")))*IF(AI34<=0,0,1) -> 898160.34 | AF35: =(IF(AD35="PI",AE35,IF(ISNUMBER(AI34),AI34,AE35))*$AF$3/365*$H35*IF(AE35>0,1,0)) -> 4672.8945 | AG35: =IF(AD35="IO",0,$AF$6-AF35)*IF(AE35>0,1,0) -> 1369.1055 | AH35: =IF(AD35="IO",$AF$6-AF35+IF(ISNUMBER(AH34),AH34,0),IF(ISNUMBER(AH34),AH34,0)) -> 0 | AI35: =(AE35+AF35-$AF$6-IF(AD35="PI",0,AH35))*IF(AE35>0,1,0) -> 896791.24 | AK35: =E35 -> 2029 | AL35: =G35 -> 9 | AM35: =IF($AK35=$AK34,R35+AM34,R35) -> 8036.6211 | AN35: =IF($AK35=$AK34,Y35+AN34,Y35) -> 6916.5782 | AO35: =IF($AK35=$AK34,AF35+AO34,AF35) -> 14349.64 | AP35: =AM35+AN35 -> 14953.199 | AQ35: =IF(AK35=AK34,AQ34,0)+ IF(J35>0,$K$6,0)+ IF(Q35>0,$R$6,0)+ IF(X35>0,$Y$6,0) -> 24909 | AR35: =N35+U35+AB35 -> 1002118.3 | AS35: =AP35+AO35 -> 29302.839 | AT35: =IF(AK35=AK34,AT34,0)+ IF(J35>0,L35,0)+ IF(Q35>0,S35,0)+ IF(X35>0,Z35,0)+ IF(AE35>0,AG35,0) -> 12973.045 | AU35: =AS35+AT35 -> 42275.884 | AV35: =N35+U35+AB35+AI35 -> 1898909.5
D36: =D35+1 -> 28 | E36: =IF(MONTH(EDATE($E$5,D36))<7,YEAR(EDATE($E$5,D36)),YEAR(EDATE($E$5,D36))+1) -> 2029 | F36: =EDATE($E$5,D36) -> 47056 | G36: =MONTH(F36) -> 10 | H36: =DAY(EOMONTH(F36,0)) -> 31 | I36: PI | J36: =IF(I36="PI",IF(N35<=0,0,N35),(IF(I36="IO",J35,"")))*IF(N35<=0,0,1) -> 47153.136 | K36: =(IF(I36="PI",J36,IF(ISNUMBER(N35),N35,J36))*$K$3/365*$H36*IF(J36>0,1,0)) -> 241.48865 | L36: =IF(I36="IO",0,$K$6-K36)*IF(J36>0,1,0) -> 1396.5114 | M36: =IF(I36="IO",$K$6-K36+IF(ISNUMBER(M35),M35,0),IF(ISNUMBER(M35),M35,0)) -> 0 | N36: =(J36+K36-$K$6-IF(I36="PI",0,M36))*IF(J36>0,1,0) -> 45756.625 | P36: PI | Q36: =IF(P36="PI",IF(U35<=0,0,U35),(IF(P36="IO",Q35,"")))*IF(U35<=0,0,1) -> 512846.94 | R36: =(IF(P36="PI",Q36,IF(ISNUMBER(U35),U35,Q36))*$R$3/365*$H36*IF(Q36>0,1,0)) -> 2696.1699 | S36: =IF(P36="IO",0,$R$6-R36)*IF(Q36>0,1,0) -> 1084.8301 | T36: =IF(P36="IO",$R$6-R36+IF(ISNUMBER(T35),T35,0),IF(ISNUMBER(T35),T35,0)) -> 0 | U36: =(Q36+R36-$R$6-IF(P36="PI",0,T36))*IF(Q36>0,1,0) -> 511762.11 | W36: PI | X36: =IF(W36="PI",IF(AB35<=0,0,AB35),(IF(W36="IO",X35,"")))*IF(AB35<=0,0,1) -> 442118.2 | Y36: =(IF(W36="PI",X36,IF(ISNUMBER(AB35),AB35,X36))*$Y$3/365*$H36*IF(X36>0,1,0)) -> 2324.3304 | Z36: =IF(W36="IO",0,$Y$6-Y36)*IF(X36>0,1,0) -> 559.66957 | AA36: =IF(W36="IO",$Y$6-Y36+IF(ISNUMBER(AA35),AA35,0),IF(ISNUMBER(AA35),AA35,0)) -> 0 | AB36: =(X36+Y36-$Y$6-IF(W36="PI",0,AA36))*IF(X36>0,1,0) -> 441558.53 | AD36: PI | AE36: =IF(AD36="PI",IF(AI35<=0,0,AI35),(IF(AD36="IO",AE35,"")))*IF(AI35<=0,0,1) -> 896791.24 | AF36: =(IF(AD36="PI",AE36,IF(ISNUMBER(AI35),AI35,AE36))*$AF$3/365*$H36*IF(AE36>0,1,0)) -> 4821.2971 | AG36: =IF(AD36="IO",0,$AF$6-AF36)*IF(AE36>0,1,0) -> 1220.7029 | AH36: =IF(AD36="IO",$AF$6-AF36+IF(ISNUMBER(AH35),AH35,0),IF(ISNUMBER(AH35),AH35,0)) -> 0 | AI36: =(AE36+AF36-$AF$6-IF(AD36="PI",0,AH36))*IF(AE36>0,1,0) -> 895570.53 | AK36: =E36 -> 2029 | AL36: =G36 -> 10 | AM36: =IF($AK36=$AK35,R36+AM35,R36) -> 10732.791 | AN36: =IF($AK36=$AK35,Y36+AN35,Y36) -> 9240.9086 | AO36: =IF($AK36=$AK35,AF36+AO35,AF36) -> 19170.937 | AP36: =AM36+AN36 -> 19973.7 | AQ36: =IF(AK36=AK35,AQ35,0)+ IF(J36>0,$K$6,0)+ IF(Q36>0,$R$6,0)+ IF(X36>0,$Y$6,0) -> 33212 | AR36: =N36+U36+AB36 -> 999077.27 | AS36: =AP36+AO36 -> 39144.637 | AT36: =IF(AK36=AK35,AT35,0)+ IF(J36>0,L36,0)+ IF(Q36>0,S36,0)+ IF(X36>0,Z36,0)+ IF(AE36>0,AG36,0) -> 17234.759 | AU36: =AS36+AT36 -> 56379.395 | AV36: =N36+U36+AB36+AI36 -> 1894647.8 | AZ36: Column Labels
D37: =D36+1 -> 29 | E37: =IF(MONTH(EDATE($E$5,D37))<7,YEAR(EDATE($E$5,D37)),YEAR(EDATE($E$5,D37))+1) -> 2029 | F37: =EDATE($E$5,D37) -> 47087 | G37: =MONTH(F37) -> 11 | H37: =DAY(EOMONTH(F37,0)) -> 30 | I37: PI | J37: =IF(I37="PI",IF(N36<=0,0,N36),(IF(I37="IO",J36,"")))*IF(N36<=0,0,1) -> 45756.625 | K37: =(IF(I37="PI",J37,IF(ISNUMBER(N36),N36,J37))*$K$3/365*$H37*IF(J37>0,1,0)) -> 226.77735 | L37: =IF(I37="IO",0,$K$6-K37)*IF(J37>0,1,0) -> 1411.2226 | M37: =IF(I37="IO",$K$6-K37+IF(ISNUMBER(M36),M36,0),IF(ISNUMBER(M36),M36,0)) -> 0 | N37: =(J37+K37-$K$6-IF(I37="PI",0,M37))*IF(J37>0,1,0) -> 44345.402 | P37: PI | Q37: =IF(P37="PI",IF(U36<=0,0,U36),(IF(P37="IO",Q36,"")))*IF(U36<=0,0,1) -> 511762.11 | R37: =(IF(P37="PI",Q37,IF(ISNUMBER(U36),U36,Q37))*$R$3/365*$H37*IF(Q37>0,1,0)) -> 2603.6774 | S37: =IF(P37="IO",0,$R$6-R37)*IF(Q37>0,1,0) -> 1177.3226 | T37: =IF(P37="IO",$R$6-R37+IF(ISNUMBER(T36),T36,0),IF(ISNUMBER(T36),T36,0)) -> 0 | U37: =(Q37+R37-$R$6-IF(P37="PI",0,T37))*IF(Q37>0,1,0) -> 510584.79 | W37: PI | X37: =IF(W37="PI",IF(AB36<=0,0,AB36),(IF(W37="IO",X36,"")))*IF(AB36<=0,0,1) -> 441558.53 | Y37: =(IF(W37="PI",X37,IF(ISNUMBER(AB36),AB36,X37))*$Y$3/365*$H37*IF(X37>0,1,0)) -> 2246.5046 | Z37: =IF(W37="IO",0,$Y$6-Y37)*IF(X37>0,1,0) -> 637.49538 | AA37: =IF(W37="IO",$Y$6-Y37+IF(ISNUMBER(AA36),AA36,0),IF(ISNUMBER(AA36),AA36,0)) -> 0 | AB37: =(X37+Y37-$Y$6-IF(W37="PI",0,AA37))*IF(X37>0,1,0) -> 440921.03 | AD37: PI | AE37: =IF(AD37="PI",IF(AI36<=0,0,AI36),(IF(AD37="IO",AE36,"")))*IF(AI36<=0,0,1) -> 895570.53 | AF37: =(IF(AD37="PI",AE37,IF(ISNUMBER(AI36),AI36,AE37))*$AF$3/365*$H37*IF(AE37>0,1,0)) -> 4659.4204 | AG37: =IF(AD37="IO",0,$AF$6-AF37)*IF(AE37>0,1,0) -> 1382.5796 | AH37: =IF(AD37="IO",$AF$6-AF37+IF(ISNUMBER(AH36),AH36,0),IF(ISNUMBER(AH36),AH36,0)) -> 0 | AI37: =(AE37+AF37-$AF$6-IF(AD37="PI",0,AH37))*IF(AE37>0,1,0) -> 894187.95 | AK37: =E37 -> 2029 | AL37: =G37 -> 11 | AM37: =IF($AK37=$AK36,R37+AM36,R37) -> 13336.468 | AN37: =IF($AK37=$AK36,Y37+AN36,Y37) -> 11487.413 | AO37: =IF($AK37=$AK36,AF37+AO36,AF37) -> 23830.357 | AP37: =AM37+AN37 -> 24823.882 | AQ37: =IF(AK37=AK36,AQ36,0)+ IF(J37>0,$K$6,0)+ IF(Q37>0,$R$6,0)+ IF(X37>0,$Y$6,0) -> 41515 | AR37: =N37+U37+AB37 -> 995851.23 | AS37: =AP37+AO37 -> 48654.239 | AT37: =IF(AK37=AK36,AT36,0)+ IF(J37>0,L37,0)+ IF(Q37>0,S37,0)+ IF(X37>0,Z37,0)+ IF(AE37>0,AG37,0) -> 21843.379 | AU37: =AS37+AT37 -> 70497.618 | AV37: =N37+U37+AB37+AI37 -> 1890039.2 | AZ37: 2027 | BA37: 2028 | BB37: 2029 | BC37: 2030 | BD37: 2031 | BE37: 2032 | BF37: 2033 | BG37: 2034 | BH37: 2035 | BI37: 2036 | BJ37: 2037 | BK37: 2038 | BL37: 2039 | BM37: 2040 | BN37: 2041 | BO37: 2042 | BP37: 2043 | BQ37: 2044 | BR37: 2045 | BS37: 2046 | BT37: 2047 | BU37: 2048 | BV37: 2049 | BW37: 2050 | BX37: 2051 | BY37: 2052 | BZ37: 2053 | CA37: 2054 | CB37: 2055
D38: =D37+1 -> 30 | E38: =IF(MONTH(EDATE($E$5,D38))<7,YEAR(EDATE($E$5,D38)),YEAR(EDATE($E$5,D38))+1) -> 2029 | F38: =EDATE($E$5,D38) -> 47117 | G38: =MONTH(F38) -> 12 | H38: =DAY(EOMONTH(F38,0)) -> 31 | I38: PI | J38: =IF(I38="PI",IF(N37<=0,0,N37),(IF(I38="IO",J37,"")))*IF(N37<=0,0,1) -> 44345.402 | K38: =(IF(I38="PI",J38,IF(ISNUMBER(N37),N37,J38))*$K$3/365*$H38*IF(J38>0,1,0)) -> 227.1092 | L38: =IF(I38="IO",0,$K$6-K38)*IF(J38>0,1,0) -> 1410.8908 | M38: =IF(I38="IO",$K$6-K38+IF(ISNUMBER(M37),M37,0),IF(ISNUMBER(M37),M37,0)) -> 0 | N38: =(J38+K38-$K$6-IF(I38="PI",0,M38))*IF(J38>0,1,0) -> 42934.511 | P38: PI | Q38: =IF(P38="PI",IF(U37<=0,0,U37),(IF(P38="IO",Q37,"")))*IF(U37<=0,0,1) -> 510584.79 | R38: =(IF(P38="PI",Q38,IF(ISNUMBER(U37),U37,Q38))*$R$3/365*$H38*IF(Q38>0,1,0)) -> 2684.2771 | S38: =IF(P38="IO",0,$R$6-R38)*IF(Q38>0,1,0) -> 1096.7229 | T38: =IF(P38="IO",$R$6-R38+IF(ISNUMBER(T37),T37,0),IF(ISNUMBER(T37),T37,0)) -> 0 | U38: =(Q38+R38-$R$6-IF(P38="PI",0,T38))*IF(Q38>0,1,0) -> 509488.07 | W38: PI | X38: =IF(W38="PI",IF(AB37<=0,0,AB37),(IF(W38="IO",X37,"")))*IF(AB37<=0,0,1) -> 440921.03 | Y38: =(IF(W38="PI",X38,IF(ISNUMBER(AB37),AB37,X38))*$Y$3/365*$H38*IF(X38>0,1,0)) -> 2318.0366 | Z38: =IF(W38="IO",0,$Y$6-Y38)*IF(X38>0,1,0) -> 565.96337 | AA38: =IF(W38="IO",$Y$6-Y38+IF(ISNUMBER(AA37),AA37,0),IF(ISNUMBER(AA37),AA37,0)) -> 0 | AB38: =(X38+Y38-$Y$6-IF(W38="PI",0,AA38))*IF(X38>0,1,0) -> 440355.07 | AD38: PI | AE38: =IF(AD38="PI",IF(AI37<=0,0,AI37),(IF(AD38="IO",AE37,"")))*IF(AI37<=0,0,1) -> 894187.95 | AF38: =(IF(AD38="PI",AE38,IF(ISNUMBER(AI37),AI37,AE38))*$AF$3/365*$H38*IF(AE38>0,1,0)) -> 4807.3014 | AG38: =IF(AD38="IO",0,$AF$6-AF38)*IF(AE38>0,1,0) -> 1234.6986 | AH38: =IF(AD38="IO",$AF$6-AF38+IF(ISNUMBER(AH37),AH37,0),IF(ISNUMBER(AH37),AH37,0)) -> 0 | AI38: =(AE38+AF38-$AF$6-IF(AD38="PI",0,AH38))*IF(AE38>0,1,0) -> 892953.26 | AK38: =E38 -> 2029 | AL38: =G38 -> 12 | AM38: =IF($AK38=$AK37,R38+AM37,R38) -> 16020.745 | AN38: =IF($AK38=$AK37,Y38+AN37,Y38) -> 13805.45 | AO38: =IF($AK38=$AK37,AF38+AO37,AF38) -> 28637.659 | AP38: =AM38+AN38 -> 29826.195 | AQ38: =IF(AK38=AK37,AQ37,0)+ IF(J38>0,$K$6,0)+ IF(Q38>0,$R$6,0)+ IF(X38>0,$Y$6,0) -> 49818 | AR38: =N38+U38+AB38 -> 992777.65 | AS38: =AP38+AO38 -> 58463.854 | AT38: =IF(AK38=AK37,AT37,0)+ IF(J38>0,L38,0)+ IF(Q38>0,S38,0)+ IF(X38>0,Z38,0)+ IF(AE38>0,AG38,0) -> 26151.655 | AU38: =AS38+AT38 -> 84615.509 | AV38: =N38+U38+AB38+AI38 -> 1885730.9 | AX38: BD Interest | AY38: Sum of BD Interest | AZ38: 28120.579 | BA38: 27784.78 | BB38: 27272.87 | BC38: 26805.72 | BD38: 26308.82 | BE38: 25852.204 | BF38: 25222.647 | BG38: 24624.926 | BH38: 23989.138 | BI38: 23377.834 | BJ38: 22597.649 | BK38: 21832.751 | BL38: 21019.139 | BM38: 20209.779 | BN38: 19236.738 | BO38: 18257.795 | BP38: 17216.506 | BQ38: 16153.568 | BR38: 14933.602 | BS38: 13680.607 | BT38: 12347.813 | BU38: 10960.205 | BV38: 9424.0915 | BW38: 7820.2148 | BX38: 6114.1927 | BY38: 4310.8943 | BZ38: 2370.0011 | CA38: 448.52581 | CB38: 0
D39: =D38+1 -> 31 | E39: =IF(MONTH(EDATE($E$5,D39))<7,YEAR(EDATE($E$5,D39)),YEAR(EDATE($E$5,D39))+1) -> 2029 | F39: =EDATE($E$5,D39) -> 47148 | G39: =MONTH(F39) -> 1 | H39: =DAY(EOMONTH(F39,0)) -> 31 | I39: PI | J39: =IF(I39="PI",IF(N38<=0,0,N38),(IF(I39="IO",J38,"")))*IF(N38<=0,0,1) -> 42934.511 | K39: =(IF(I39="PI",J39,IF(ISNUMBER(N38),N38,J39))*$K$3/365*$H39*IF(J39>0,1,0)) -> 219.88351 | L39: =IF(I39="IO",0,$K$6-K39)*IF(J39>0,1,0) -> 1418.1165 | M39: =IF(I39="IO",$K$6-K39+IF(ISNUMBER(M38),M38,0),IF(ISNUMBER(M38),M38,0)) -> 0 | N39: =(J39+K39-$K$6-IF(I39="PI",0,M39))*IF(J39>0,1,0) -> 41516.395 | P39: PI | Q39: =IF(P39="PI",IF(U38<=0,0,U38),(IF(P39="IO",Q38,"")))*IF(U38<=0,0,1) -> 509488.07 | R39: =(IF(P39="PI",Q39,IF(ISNUMBER(U38),U38,Q39))*$R$3/365*$H39*IF(Q39>0,1,0)) -> 2678.5114 | S39: =IF(P39="IO",0,$R$6-R39)*IF(Q39>0,1,0) -> 1102.4886 | T39: =IF(P39="IO",$R$6-R39+IF(ISNUMBER(T38),T38,0),IF(ISNUMBER(T38),T38,0)) -> 0 | U39: =(Q39+R39-$R$6-IF(P39="PI",0,T39))*IF(Q39>0,1,0) -> 508385.58 | W39: PI | X39: =IF(W39="PI",IF(AB38<=0,0,AB38),(IF(W39="IO",X38,"")))*IF(AB38<=0,0,1) -> 440355.07 | Y39: =(IF(W39="PI",X39,IF(ISNUMBER(AB38),AB38,X39))*$Y$3/365*$H39*IF(X39>0,1,0)) -> 2315.0612 | Z39: =IF(W39="IO",0,$Y$6-Y39)*IF(X39>0,1,0) -> 568.93879 | AA39: =IF(W39="IO",$Y$6-Y39+IF(ISNUMBER(AA38),AA38,0),IF(ISNUMBER(AA38),AA38,0)) -> 0 | AB39: =(X39+Y39-$Y$6-IF(W39="PI",0,AA39))*IF(X39>0,1,0) -> 439786.13 | AD39: PI | AE39: =IF(AD39="PI",IF(AI38<=0,0,AI38),(IF(AD39="IO",AE38,"")))*IF(AI38<=0,0,1) -> 892953.26 | AF39: =(IF(AD39="PI",AE39,IF(ISNUMBER(AI38),AI38,AE39))*$AF$3/365*$H39*IF(AE39>0,1,0)) -> 4800.6635 | AG39: =IF(AD39="IO",0,$AF$6-AF39)*IF(AE39>0,1,0) -> 1241.3365 | AH39: =IF(AD39="IO",$AF$6-AF39+IF(ISNUMBER(AH38),AH38,0),IF(ISNUMBER(AH38),AH38,0)) -> 0 | AI39: =(AE39+AF39-$AF$6-IF(AD39="PI",0,AH39))*IF(AE39>0,1,0) -> 891711.92 | AK39: =E39 -> 2029 | AL39: =G39 -> 1 | AM39: =IF($AK39=$AK38,R39+AM38,R39) -> 18699.257 | AN39: =IF($AK39=$AK38,Y39+AN38,Y39) -> 16120.511 | AO39: =IF($AK39=$AK38,AF39+AO38,AF39) -> 33438.322 | AP39: =AM39+AN39 -> 34819.768 | AQ39: =IF(AK39=AK38,AQ38,0)+ IF(J39>0,$K$6,0)+ IF(Q39>0,$R$6,0)+ IF(X39>0,$Y$6,0) -> 58121 | AR39: =N39+U39+AB39 -> 989688.1 | AS39: =AP39+AO39 -> 68258.09 | AT39: =IF(AK39=AK38,AT38,0)+ IF(J39>0,L39,0)+ IF(Q39>0,S39,0)+ IF(X39>0,Z39,0)+ IF(AE39>0,AG39,0) -> 30482.535 | AU39: =AS39+AT39 -> 98740.625 | AV39: =N39+U39+AB39+AI39 -> 1881400
D40: =D39+1 -> 32 | E40: =IF(MONTH(EDATE($E$5,D40))<7,YEAR(EDATE($E$5,D40)),YEAR(EDATE($E$5,D40))+1) -> 2029 | F40: =EDATE($E$5,D40) -> 47177 | G40: =MONTH(F40) -> 2 | H40: =DAY(EOMONTH(F40,0)) -> 28 | I40: PI | J40: =IF(I40="PI",IF(N39<=0,0,N39),(IF(I40="IO",J39,"")))*IF(N39<=0,0,1) -> 41516.395 | K40: =(IF(I40="PI",J40,IF(ISNUMBER(N39),N39,J40))*$K$3/365*$H40*IF(J40>0,1,0)) -> 192.0446 | L40: =IF(I40="IO",0,$K$6-K40)*IF(J40>0,1,0) -> 1445.9554 | M40: =IF(I40="IO",$K$6-K40+IF(ISNUMBER(M39),M39,0),IF(ISNUMBER(M39),M39,0)) -> 0 | N40: =(J40+K40-$K$6-IF(I40="PI",0,M40))*IF(J40>0,1,0) -> 40070.439 | P40: PI | Q40: =IF(P40="PI",IF(U39<=0,0,U39),(IF(P40="IO",Q39,"")))*IF(U39<=0,0,1) -> 508385.58 | R40: =(IF(P40="PI",Q40,IF(ISNUMBER(U39),U39,Q40))*$R$3/365*$H40*IF(Q40>0,1,0)) -> 2414.0654 | S40: =IF(P40="IO",0,$R$6-R40)*IF(Q40>0,1,0) -> 1366.9346 | T40: =IF(P40="IO",$R$6-R40+IF(ISNUMBER(T39),T39,0),IF(ISNUMBER(T39),T39,0)) -> 0 | U40: =(Q40+R40-$R$6-IF(P40="PI",0,T40))*IF(Q40>0,1,0) -> 507018.65 | W40: PI | X40: =IF(W40="PI",IF(AB39<=0,0,AB39),(IF(W40="IO",X39,"")))*IF(AB39<=0,0,1) -> 439786.13 | Y40: =(IF(W40="PI",X40,IF(ISNUMBER(AB39),AB39,X40))*$Y$3/365*$H40*IF(X40>0,1,0)) -> 2088.3214 | Z40: =IF(W40="IO",0,$Y$6-Y40)*IF(X40>0,1,0) -> 795.67857 | AA40: =IF(W40="IO",$Y$6-Y40+IF(ISNUMBER(AA39),AA39,0),IF(ISNUMBER(AA39),AA39,0)) -> 0 | AB40: =(X40+Y40-$Y$6-IF(W40="PI",0,AA40))*IF(X40>0,1,0) -> 438990.45 | AD40: PI | AE40: =IF(AD40="PI",IF(AI39<=0,0,AI39),(IF(AD40="IO",AE39,"")))*IF(AI39<=0,0,1) -> 891711.92 | AF40: =(IF(AD40="PI",AE40,IF(ISNUMBER(AI39),AI39,AE40))*$AF$3/365*$H40*IF(AE40>0,1,0)) -> 4330.0554 | AG40: =IF(AD40="IO",0,$AF$6-AF40)*IF(AE40>0,1,0) -> 1711.9446 | AH40: =IF(AD40="IO",$AF$6-AF40+IF(ISNUMBER(AH39),AH39,0),IF(ISNUMBER(AH39),AH39,0)) -> 0 | AI40: =(AE40+AF40-$AF$6-IF(AD40="PI",0,AH40))*IF(AE40>0,1,0) -> 889999.97 | AK40: =E40 -> 2029 | AL40: =G40 -> 2 | AM40: =IF($AK40=$AK39,R40+AM39,R40) -> 21113.322 | AN40: =IF($AK40=$AK39,Y40+AN39,Y40) -> 18208.833 | AO40: =IF($AK40=$AK39,AF40+AO39,AF40) -> 37768.378 | AP40: =AM40+AN40 -> 39322.155 | AQ40: =IF(AK40=AK39,AQ39,0)+ IF(J40>0,$K$6,0)+ IF(Q40>0,$R$6,0)+ IF(X40>0,$Y$6,0) -> 66424 | AR40: =N40+U40+AB40 -> 986079.54 | AS40: =AP40+AO40 -> 77090.532 | AT40: =IF(AK40=AK39,AT39,0)+ IF(J40>0,L40,0)+ IF(Q40>0,S40,0)+ IF(X40>0,Z40,0)+ IF(AE40>0,AG40,0) -> 35803.048 | AU40: =AS40+AT40 -> 112893.58 | AV40: =N40+U40+AB40+AI40 -> 1876079.5 | AY40: Calendar Month | AZ40: 6
D41: =D40+1 -> 33 | E41: =IF(MONTH(EDATE($E$5,D41))<7,YEAR(EDATE($E$5,D41)),YEAR(EDATE($E$5,D41))+1) -> 2029 | F41: =EDATE($E$5,D41) -> 47207 | G41: =MONTH(F41) -> 3 | H41: =DAY(EOMONTH(F41,0)) -> 31 | I41: PI | J41: =IF(I41="PI",IF(N40<=0,0,N40),(IF(I41="IO",J40,"")))*IF(N40<=0,0,1) -> 40070.439 | K41: =(IF(I41="PI",J41,IF(ISNUMBER(N40),N40,J41))*$K$3/365*$H41*IF(J41>0,1,0)) -> 205.21554 | L41: =IF(I41="IO",0,$K$6-K41)*IF(J41>0,1,0) -> 1432.7845 | M41: =IF(I41="IO",$K$6-K41+IF(ISNUMBER(M40),M40,0),IF(ISNUMBER(M40),M40,0)) -> 0 | N41: =(J41+K41-$K$6-IF(I41="PI",0,M41))*IF(J41>0,1,0) -> 38637.655 | P41: PI | Q41: =IF(P41="PI",IF(U40<=0,0,U40),(IF(P41="IO",Q40,"")))*IF(U40<=0,0,1) -> 507018.65 | R41: =(IF(P41="PI",Q41,IF(ISNUMBER(U40),U40,Q41))*$R$3/365*$H41*IF(Q41>0,1,0)) -> 2665.529 | S41: =IF(P41="IO",0,$R$6-R41)*IF(Q41>0,1,0) -> 1115.471 | T41: =IF(P41="IO",$R$6-R41+IF(ISNUMBER(T40),T40,0),IF(ISNUMBER(T40),T40,0)) -> 0 | U41: =(Q41+R41-$R$6-IF(P41="PI",0,T41))*IF(Q41>0,1,0) -> 505903.17 | W41: PI | X41: =IF(W41="PI",IF(AB40<=0,0,AB40),(IF(W41="IO",X40,"")))*IF(AB40<=0,0,1) -> 438990.45 | Y41: =(IF(W41="PI",X41,IF(ISNUMBER(AB40),AB40,X41))*$Y$3/365*$H41*IF(X41>0,1,0)) -> 2307.8871 | Z41: =IF(W41="IO",0,$Y$6-Y41)*IF(X41>0,1,0) -> 576.11294 | AA41: =IF(W41="IO",$Y$6-Y41+IF(ISNUMBER(AA40),AA40,0),IF(ISNUMBER(AA40),AA40,0)) -> 0 | AB41: =(X41+Y41-$Y$6-IF(W41="PI",0,AA41))*IF(X41>0,1,0) -> 438414.34 | AD41: PI | AE41: =IF(AD41="PI",IF(AI40<=0,0,AI40),(IF(AD41="IO",AE40,"")))*IF(AI40<=0,0,1) -> 889999.97 | AF41: =(IF(AD41="PI",AE41,IF(ISNUMBER(AI40),AI40,AE41))*$AF$3/365*$H41*IF(AE41>0,1,0)) -> 4784.7862 | AG41: =IF(AD41="IO",0,$AF$6-AF41)*IF(AE41>0,1,0) -> 1257.2138 | AH41: =IF(AD41="IO",$AF$6-AF41+IF(ISNUMBER(AH40),AH40,0),IF(ISNUMBER(AH40),AH40,0)) -> 0 | AI41: =(AE41+AF41-$AF$6-IF(AD41="PI",0,AH41))*IF(AE41>0,1,0) -> 888742.76 | AK41: =E41 -> 2029 | AL41: =G41 -> 3 | AM41: =IF($AK41=$AK40,R41+AM40,R41) -> 23778.851 | AN41: =IF($AK41=$AK40,Y41+AN40,Y41) -> 20516.72 | AO41: =IF($AK41=$AK40,AF41+AO40,AF41) -> 42553.164 | AP41: =AM41+AN41 -> 44295.571 | AQ41: =IF(AK41=AK40,AQ40,0)+ IF(J41>0,$K$6,0)+ IF(Q41>0,$R$6,0)+ IF(X41>0,$Y$6,0) -> 74727 | AR41: =N41+U41+AB41 -> 982955.17 | AS41: =AP41+AO41 -> 86848.735 | AT41: =IF(AK41=AK40,AT40,0)+ IF(J41>0,L41,0)+ IF(Q41>0,S41,0)+ IF(X41>0,Z41,0)+ IF(AE41>0,AG41,0) -> 40184.631 | AU41: =AS41+AT41 -> 127033.37 | AV41: =N41+U41+AB41+AI41 -> 1871697.9
D42: =D41+1 -> 34 | E42: =IF(MONTH(EDATE($E$5,D42))<7,YEAR(EDATE($E$5,D42)),YEAR(EDATE($E$5,D42))+1) -> 2029 | F42: =EDATE($E$5,D42) -> 47238 | G42: =MONTH(F42) -> 4 | H42: =DAY(EOMONTH(F42,0)) -> 30 | I42: PI | J42: =IF(I42="PI",IF(N41<=0,0,N41),(IF(I42="IO",J41,"")))*IF(N41<=0,0,1) -> 38637.655 | K42: =(IF(I42="PI",J42,IF(ISNUMBER(N41),N41,J42))*$K$3/365*$H42*IF(J42>0,1,0)) -> 191.49457 | L42: =IF(I42="IO",0,$K$6-K42)*IF(J42>0,1,0) -> 1446.5054 | M42: =IF(I42="IO",$K$6-K42+IF(ISNUMBER(M41),M41,0),IF(ISNUMBER(M41),M41,0)) -> 0 | N42: =(J42+K42-$K$6-IF(I42="PI",0,M42))*IF(J42>0,1,0) -> 37191.149 | P42: PI | Q42: =IF(P42="PI",IF(U41<=0,0,U41),(IF(P42="IO",Q41,"")))*IF(U41<=0,0,1) -> 505903.17 | R42: =(IF(P42="PI",Q42,IF(ISNUMBER(U41),U41,Q42))*$R$3/365*$H42*IF(Q42>0,1,0)) -> 2573.869 | S42: =IF(P42="IO",0,$R$6-R42)*IF(Q42>0,1,0) -> 1207.131 | T42: =IF(P42="IO",$R$6-R42+IF(ISNUMBER(T41),T41,0),IF(ISNUMBER(T41),T41,0)) -> 0 | U42: =(Q42+R42-$R$6-IF(P42="PI",0,T42))*IF(Q42>0,1,0) -> 504696.04 | W42: PI | X42: =IF(W42="PI",IF(AB41<=0,0,AB41),(IF(W42="IO",X41,"")))*IF(AB41<=0,0,1) -> 438414.34 | Y42: =(IF(W42="PI",X42,IF(ISNUMBER(AB41),AB41,X42))*$Y$3/365*$H42*IF(X42>0,1,0)) -> 2230.508 | Z42: =IF(W42="IO",0,$Y$6-Y42)*IF(X42>0,1,0) -> 653.49198 | AA42: =IF(W42="IO",$Y$6-Y42+IF(ISNUMBER(AA41),AA41,0),IF(ISNUMBER(AA41),AA41,0)) -> 0 | AB42: =(X42+Y42-$Y$6-IF(W42="PI",0,AA42))*IF(X42>0,1,0) -> 437760.85 | AD42: PI | AE42: =IF(AD42="PI",IF(AI41<=0,0,AI41),(IF(AD42="IO",AE41,"")))*IF(AI41<=0,0,1) -> 888742.76 | AF42: =(IF(AD42="PI",AE42,IF(ISNUMBER(AI41),AI41,AE42))*$AF$3/365*$H42*IF(AE42>0,1,0)) -> 4623.8973 | AG42: =IF(AD42="IO",0,$AF$6-AF42)*IF(AE42>0,1,0) -> 1418.1027 | AH42: =IF(AD42="IO",$AF$6-AF42+IF(ISNUMBER(AH41),AH41,0),IF(ISNUMBER(AH41),AH41,0)) -> 0 | AI42: =(AE42+AF42-$AF$6-IF(AD42="PI",0,AH42))*IF(AE42>0,1,0) -> 887324.66 | AK42: =E42 -> 2029 | AL42: =G42 -> 4 | AM42: =IF($AK42=$AK41,R42+AM41,R42) -> 26352.72 | AN42: =IF($AK42=$AK41,Y42+AN41,Y42) -> 22747.228 | AO42: =IF($AK42=$AK41,AF42+AO41,AF42) -> 47177.061 | AP42: =AM42+AN42 -> 49099.948 | AQ42: =IF(AK42=AK41,AQ41,0)+ IF(J42>0,$K$6,0)+ IF(Q42>0,$R$6,0)+ IF(X42>0,$Y$6,0) -> 83030 | AR42: =N42+U42+AB42 -> 979648.04 | AS42: =AP42+AO42 -> 96277.009 | AT42: =IF(AK42=AK41,AT41,0)+ IF(J42>0,L42,0)+ IF(Q42>0,S42,0)+ IF(X42>0,Z42,0)+ IF(AE42>0,AG42,0) -> 44909.862 | AU42: =AS42+AT42 -> 141186.87 | AV42: =N42+U42+AB42+AI42 -> 1866972.7 | AZ42: Column Labels
D43: =D42+1 -> 35 | E43: =IF(MONTH(EDATE($E$5,D43))<7,YEAR(EDATE($E$5,D43)),YEAR(EDATE($E$5,D43))+1) -> 2029 | F43: =EDATE($E$5,D43) -> 47268 | G43: =MONTH(F43) -> 5 | H43: =DAY(EOMONTH(F43,0)) -> 31 | I43: PI | J43: =IF(I43="PI",IF(N42<=0,0,N42),(IF(I43="IO",J42,"")))*IF(N42<=0,0,1) -> 37191.149 | K43: =(IF(I43="PI",J43,IF(ISNUMBER(N42),N42,J43))*$K$3/365*$H43*IF(J43>0,1,0)) -> 190.46963 | L43: =IF(I43="IO",0,$K$6-K43)*IF(J43>0,1,0) -> 1447.5304 | M43: =IF(I43="IO",$K$6-K43+IF(ISNUMBER(M42),M42,0),IF(ISNUMBER(M42),M42,0)) -> 0 | N43: =(J43+K43-$K$6-IF(I43="PI",0,M43))*IF(J43>0,1,0) -> 35743.619 | P43: PI | Q43: =IF(P43="PI",IF(U42<=0,0,U42),(IF(P43="IO",Q42,"")))*IF(U42<=0,0,1) -> 504696.04 | R43: =(IF(P43="PI",Q43,IF(ISNUMBER(U42),U42,Q43))*$R$3/365*$H43*IF(Q43>0,1,0)) -> 2653.3185 | S43: =IF(P43="IO",0,$R$6-R43)*IF(Q43>0,1,0) -> 1127.6815 | T43: =IF(P43="IO",$R$6-R43+IF(ISNUMBER(T42),T42,0),IF(ISNUMBER(T42),T42,0)) -> 0 | U43: =(Q43+R43-$R$6-IF(P43="PI",0,T43))*IF(Q43>0,1,0) -> 503568.36 | W43: PI | X43: =IF(W43="PI",IF(AB42<=0,0,AB42),(IF(W43="IO",X42,"")))*IF(AB42<=0,0,1) -> 437760.85 | Y43: =(IF(W43="PI",X43,IF(ISNUMBER(AB42),AB42,X43))*$Y$3/365*$H43*IF(X43>0,1,0)) -> 2301.4227 | Z43: =IF(W43="IO",0,$Y$6-Y43)*IF(X43>0,1,0) -> 582.57729 | AA43: =IF(W43="IO",$Y$6-Y43+IF(ISNUMBER(AA42),AA42,0),IF(ISNUMBER(AA42),AA42,0)) -> 0 | AB43: =(X43+Y43-$Y$6-IF(W43="PI",0,AA43))*IF(X43>0,1,0) -> 437178.27 | AD43: PI | AE43: =IF(AD43="PI",IF(AI42<=0,0,AI42),(IF(AD43="IO",AE42,"")))*IF(AI42<=0,0,1) -> 887324.66 | AF43: =(IF(AD43="PI",AE43,IF(ISNUMBER(AI42),AI42,AE43))*$AF$3/365*$H43*IF(AE43>0,1,0)) -> 4770.4032 | AG43: =IF(AD43="IO",0,$AF$6-AF43)*IF(AE43>0,1,0) -> 1271.5968 | AH43: =IF(AD43="IO",$AF$6-AF43+IF(ISNUMBER(AH42),AH42,0),IF(ISNUMBER(AH42),AH42,0)) -> 0 | AI43: =(AE43+AF43-$AF$6-IF(AD43="PI",0,AH43))*IF(AE43>0,1,0) -> 886053.06 | AK43: =E43 -> 2029 | AL43: =G43 -> 5 | AM43: =IF($AK43=$AK42,R43+AM42,R43) -> 29006.039 | AN43: =IF($AK43=$AK42,Y43+AN42,Y43) -> 25048.65 | AO43: =IF($AK43=$AK42,AF43+AO42,AF43) -> 51947.464 | AP43: =AM43+AN43 -> 54054.689 | AQ43: =IF(AK43=AK42,AQ42,0)+ IF(J43>0,$K$6,0)+ IF(Q43>0,$R$6,0)+ IF(X43>0,$Y$6,0) -> 91333 | AR43: =N43+U43+AB43 -> 976490.25 | AS43: =AP43+AO43 -> 106002.15 | AT43: =IF(AK43=AK42,AT42,0)+ IF(J43>0,L43,0)+ IF(Q43>0,S43,0)+ IF(X43>0,Z43,0)+ IF(AE43>0,AG43,0) -> 49339.248 | AU43: =AS43+AT43 -> 155341.4 | AV43: =N43+U43+AB43+AI43 -> 1862543.3 | AZ43: 2027 | BA43: 2028 | BB43: 2029 | BC43: 2030 | BD43: 2031 | BE43: 2032 | BF43: 2033 | BG43: 2034 | BH43: 2035 | BI43: 2036 | BJ43: 2037 | BK43: 2038 | BL43: 2039 | BM43: 2040 | BN43: 2041 | BO43: 2042 | BP43: 2043 | BQ43: 2044 | BR43: 2045 | BS43: 2046 | BT43: 2047 | BU43: 2048 | BV43: 2049 | BW43: 2050 | BX43: 2051 | BY43: 2052 | BZ43: 2053 | CA43: 2054 | CB43: 2055
D44: =D43+1 -> 36 | E44: =IF(MONTH(EDATE($E$5,D44))<7,YEAR(EDATE($E$5,D44)),YEAR(EDATE($E$5,D44))+1) -> 2029 | F44: =EDATE($E$5,D44) -> 47299 | G44: =MONTH(F44) -> 6 | H44: =DAY(EOMONTH(F44,0)) -> 30 | I44: PI | J44: =IF(I44="PI",IF(N43<=0,0,N43),(IF(I44="IO",J43,"")))*IF(N43<=0,0,1) -> 35743.619 | K44: =(IF(I44="PI",J44,IF(ISNUMBER(N43),N43,J44))*$K$3/365*$H44*IF(J44>0,1,0)) -> 177.15125 | L44: =IF(I44="IO",0,$K$6-K44)*IF(J44>0,1,0) -> 1460.8487 | M44: =IF(I44="IO",$K$6-K44+IF(ISNUMBER(M43),M43,0),IF(ISNUMBER(M43),M43,0)) -> 0 | N44: =(J44+K44-$K$6-IF(I44="PI",0,M44))*IF(J44>0,1,0) -> 34282.77 | P44: PI | Q44: =IF(P44="PI",IF(U43<=0,0,U43),(IF(P44="IO",Q43,"")))*IF(U43<=0,0,1) -> 503568.36 | R44: =(IF(P44="PI",Q44,IF(ISNUMBER(U43),U43,Q44))*$R$3/365*$H44*IF(Q44>0,1,0)) -> 2561.9903 | S44: =IF(P44="IO",0,$R$6-R44)*IF(Q44>0,1,0) -> 1219.0097 | T44: =IF(P44="IO",$R$6-R44+IF(ISNUMBER(T43),T43,0),IF(ISNUMBER(T43),T43,0)) -> 0 | U44: =(Q44+R44-$R$6-IF(P44="PI",0,T44))*IF(Q44>0,1,0) -> 502349.35 | W44: PI | X44: =IF(W44="PI",IF(AB43<=0,0,AB43),(IF(W44="IO",X43,"")))*IF(AB43<=0,0,1) -> 437178.27 | Y44: =(IF(W44="PI",X44,IF(ISNUMBER(AB43),AB43,X44))*$Y$3/365*$H44*IF(X44>0,1,0)) -> 2224.2193 | Z44: =IF(W44="IO",0,$Y$6-Y44)*IF(X44>0,1,0) -> 659.7807 | AA44: =IF(W44="IO",$Y$6-Y44+IF(ISNUMBER(AA43),AA43,0),IF(ISNUMBER(AA43),AA43,0)) -> 0 | AB44: =(X44+Y44-$Y$6-IF(W44="PI",0,AA44))*IF(X44>0,1,0) -> 436518.49 | AD44: PI | AE44: =IF(AD44="PI",IF(AI43<=0,0,AI43),(IF(AD44="IO",AE43,"")))*IF(AI43<=0,0,1) -> 886053.06 | AF44: =(IF(AD44="PI",AE44,IF(ISNUMBER(AI43),AI43,AE44))*$AF$3/365*$H44*IF(AE44>0,1,0)) -> 4609.9035 | AG44: =IF(AD44="IO",0,$AF$6-AF44)*IF(AE44>0,1,0) -> 1432.0965 | AH44: =IF(AD44="IO",$AF$6-AF44+IF(ISNUMBER(AH43),AH43,0),IF(ISNUMBER(AH43),AH43,0)) -> 0 | AI44: =(AE44+AF44-$AF$6-IF(AD44="PI",0,AH44))*IF(AE44>0,1,0) -> 884620.96 | AK44: =E44 -> 2029 | AL44: =G44 -> 6 | AM44: =IF($AK44=$AK43,R44+AM43,R44) -> 31568.029 | AN44: =IF($AK44=$AK43,Y44+AN43,Y44) -> 27272.87 | AO44: =IF($AK44=$AK43,AF44+AO43,AF44) -> 56557.368 | AP44: =AM44+AN44 -> 58840.899 | AQ44: =IF(AK44=AK43,AQ43,0)+ IF(J44>0,$K$6,0)+ IF(Q44>0,$R$6,0)+ IF(X44>0,$Y$6,0) -> 99636 | AR44: =N44+U44+AB44 -> 973150.61 | AS44: =AP44+AO44 -> 115398.27 | AT44: =IF(AK44=AK43,AT43,0)+ IF(J44>0,L44,0)+ IF(Q44>0,S44,0)+ IF(X44>0,Z44,0)+ IF(AE44>0,AG44,0) -> 54110.983 | AU44: =AS44+AT44 -> 169509.25 | AV44: =N44+U44+AB44+AI44 -> 1857771.6 | AX44: Shane Interest | AY44: Sum of Shane Interest | AZ44: 58439.737 | BA44: 57683.85 | BB44: 56557.368 | BC44: 55518.141 | BD44: 54411.189 | BE44: 53380.661 | BF44: 51985.849 | BG44: 50648.701 | BH44: 49224.412 | BI44: 47840.282 | BJ44: 46099.994 | BK44: 44379.27 | BL44: 42546.409 | BM44: 40707.014 | BN44: 38521.923 | BO44: 36307.344 | BP44: 33948.444 | BQ44: 31522.893 | BR44: 28765.117 | BS44: 25914.696 | BT44: 22878.516 | BU44: 19698.288 | BV44: 16203.175 | BW44: 12534.105 | BX44: 8625.9251 | BY44: 4474.0441 | BZ44: 588.11623 | CA44: 0 | CB44: 0
D45: =D44+1 -> 37 | E45: =IF(MONTH(EDATE($E$5,D45))<7,YEAR(EDATE($E$5,D45)),YEAR(EDATE($E$5,D45))+1) -> 2030 | F45: =EDATE($E$5,D45) -> 47329 | G45: =MONTH(F45) -> 7 | H45: =DAY(EOMONTH(F45,0)) -> 31 | I45: PI | J45: =IF(I45="PI",IF(N44<=0,0,N44),(IF(I45="IO",J44,"")))*IF(N44<=0,0,1) -> 34282.77 | K45: =(IF(I45="PI",J45,IF(ISNUMBER(N44),N44,J45))*$K$3/365*$H45*IF(J45>0,1,0)) -> 175.57475 | L45: =IF(I45="IO",0,$K$6-K45)*IF(J45>0,1,0) -> 1462.4253 | M45: =IF(I45="IO",$K$6-K45+IF(ISNUMBER(M44),M44,0),IF(ISNUMBER(M44),M44,0)) -> 0 | N45: =(J45+K45-$K$6-IF(I45="PI",0,M45))*IF(J45>0,1,0) -> 32820.345 | P45: PI | Q45: =IF(P45="PI",IF(U44<=0,0,U44),(IF(P45="IO",Q44,"")))*IF(U44<=0,0,1) -> 502349.35 | R45: =(IF(P45="PI",Q45,IF(ISNUMBER(U44),U44,Q45))*$R$3/365*$H45*IF(Q45>0,1,0)) -> 2640.9813 | S45: =IF(P45="IO",0,$R$6-R45)*IF(Q45>0,1,0) -> 1140.0187 | T45: =IF(P45="IO",$R$6-R45+IF(ISNUMBER(T44),T44,0),IF(ISNUMBER(T44),T44,0)) -> 0 | U45: =(Q45+R45-$R$6-IF(P45="PI",0,T45))*IF(Q45>0,1,0) -> 501209.33 | W45: PI | X45: =IF(W45="PI",IF(AB44<=0,0,AB44),(IF(W45="IO",X44,"")))*IF(AB44<=0,0,1) -> 436518.49 | Y45: =(IF(W45="PI",X45,IF(ISNUMBER(AB44),AB44,X45))*$Y$3/365*$H45*IF(X45>0,1,0)) -> 2294.8913 | Z45: =IF(W45="IO",0,$Y$6-Y45)*IF(X45>0,1,0) -> 589.10869 | AA45: =IF(W45="IO",$Y$6-Y45+IF(ISNUMBER(AA44),AA44,0),IF(ISNUMBER(AA44),AA44,0)) -> 0 | AB45: =(X45+Y45-$Y$6-IF(W45="PI",0,AA45))*IF(X45>0,1,0) -> 435929.38 | AD45: PI | AE45: =IF(AD45="PI",IF(AI44<=0,0,AI44),(IF(AD45="IO",AE44,"")))*IF(AI44<=0,0,1) -> 884620.96 | AF45: =(IF(AD45="PI",AE45,IF(ISNUMBER(AI44),AI44,AE45))*$AF$3/365*$H45*IF(AE45>0,1,0)) -> 4755.8677 | AG45: =IF(AD45="IO",0,$AF$6-AF45)*IF(AE45>0,1,0) -> 1286.1323 | AH45: =IF(AD45="IO",$AF$6-AF45+IF(ISNUMBER(AH44),AH44,0),IF(ISNUMBER(AH44),AH44,0)) -> 0 | AI45: =(AE45+AF45-$AF$6-IF(AD45="PI",0,AH45))*IF(AE45>0,1,0) -> 883334.83 | AK45: =E45 -> 2030 | AL45: =G45 -> 7 | AM45: =IF($AK45=$AK44,R45+AM44,R45) -> 2640.9813 | AN45: =IF($AK45=$AK44,Y45+AN44,Y45) -> 2294.8913 | AO45: =IF($AK45=$AK44,AF45+AO44,AF45) -> 4755.8677 | AP45: =AM45+AN45 -> 4935.8726 | AQ45: =IF(AK45=AK44,AQ44,0)+ IF(J45>0,$K$6,0)+ IF(Q45>0,$R$6,0)+ IF(X45>0,$Y$6,0) -> 8303 | AR45: =N45+U45+AB45 -> 969959.06 | AS45: =AP45+AO45 -> 9691.7403 | AT45: =IF(AK45=AK44,AT44,0)+ IF(J45>0,L45,0)+ IF(Q45>0,S45,0)+ IF(X45>0,Z45,0)+ IF(AE45>0,AG45,0) -> 4477.6849 | AU45: =AS45+AT45 -> 14169.425 | AV45: =N45+U45+AB45+AI45 -> 1853293.9
D46: =D45+1 -> 38 | E46: =IF(MONTH(EDATE($E$5,D46))<7,YEAR(EDATE($E$5,D46)),YEAR(EDATE($E$5,D46))+1) -> 2030 | F46: =EDATE($E$5,D46) -> 47360 | G46: =MONTH(F46) -> 8 | H46: =DAY(EOMONTH(F46,0)) -> 31 | I46: PI | J46: =IF(I46="PI",IF(N45<=0,0,N45),(IF(I46="IO",J45,"")))*IF(N45<=0,0,1) -> 32820.345 | K46: =(IF(I46="PI",J46,IF(ISNUMBER(N45),N45,J46))*$K$3/365*$H46*IF(J46>0,1,0)) -> 168.08513 | L46: =IF(I46="IO",0,$K$6-K46)*IF(J46>0,1,0) -> 1469.9149 | M46: =IF(I46="IO",$K$6-K46+IF(ISNUMBER(M45),M45,0),IF(ISNUMBER(M45),M45,0)) -> 0 | N46: =(J46+K46-$K$6-IF(I46="PI",0,M46))*IF(J46>0,1,0) -> 31350.43 | P46: PI | Q46: =IF(P46="PI",IF(U45<=0,0,U45),(IF(P46="IO",Q45,"")))*IF(U45<=0,0,1) -> 501209.33 | R46: =(IF(P46="PI",Q46,IF(ISNUMBER(U45),U45,Q46))*$R$3/365*$H46*IF(Q46>0,1,0)) -> 2634.9879 | S46: =IF(P46="IO",0,$R$6-R46)*IF(Q46>0,1,0) -> 1146.0121 | T46: =IF(P46="IO",$R$6-R46+IF(ISNUMBER(T45),T45,0),IF(ISNUMBER(T45),T45,0)) -> 0 | U46: =(Q46+R46-$R$6-IF(P46="PI",0,T46))*IF(Q46>0,1,0) -> 500063.32 | W46: PI | X46: =IF(W46="PI",IF(AB45<=0,0,AB45),(IF(W46="IO",X45,"")))*IF(AB45<=0,0,1) -> 435929.38 | Y46: =(IF(W46="PI",X46,IF(ISNUMBER(AB45),AB45,X46))*$Y$3/365*$H46*IF(X46>0,1,0)) -> 2291.7942 | Z46: =IF(W46="IO",0,$Y$6-Y46)*IF(X46>0,1,0) -> 592.20579 | AA46: =IF(W46="IO",$Y$6-Y46+IF(ISNUMBER(AA45),AA45,0),IF(ISNUMBER(AA45),AA45,0)) -> 0 | AB46: =(X46+Y46-$Y$6-IF(W46="PI",0,AA46))*IF(X46>0,1,0) -> 435337.17 | AD46: PI | AE46: =IF(AD46="PI",IF(AI45<=0,0,AI45),(IF(AD46="IO",AE45,"")))*IF(AI45<=0,0,1) -> 883334.83 | AF46: =(IF(AD46="PI",AE46,IF(ISNUMBER(AI45),AI45,AE46))*$AF$3/365*$H46*IF(AE46>0,1,0)) -> 4748.9533 | AG46: =IF(AD46="IO",0,$AF$6-AF46)*IF(AE46>0,1,0) -> 1293.0467 | AH46: =IF(AD46="IO",$AF$6-AF46+IF(ISNUMBER(AH45),AH45,0),IF(ISNUMBER(AH45),AH45,0)) -> 0 | AI46: =(AE46+AF46-$AF$6-IF(AD46="PI",0,AH46))*IF(AE46>0,1,0) -> 882041.79 | AK46: =E46 -> 2030 | AL46: =G46 -> 8 | AM46: =IF($AK46=$AK45,R46+AM45,R46) -> 5275.9692 | AN46: =IF($AK46=$AK45,Y46+AN45,Y46) -> 4586.6855 | AO46: =IF($AK46=$AK45,AF46+AO45,AF46) -> 9504.821 | AP46: =AM46+AN46 -> 9862.6547 | AQ46: =IF(AK46=AK45,AQ45,0)+ IF(J46>0,$K$6,0)+ IF(Q46>0,$R$6,0)+ IF(X46>0,$Y$6,0) -> 16606 | AR46: =N46+U46+AB46 -> 966750.93 | AS46: =AP46+AO46 -> 19367.476 | AT46: =IF(AK46=AK45,AT45,0)+ IF(J46>0,L46,0)+ IF(Q46>0,S46,0)+ IF(X46>0,Z46,0)+ IF(AE46>0,AG46,0) -> 8978.8644 | AU46: =AS46+AT46 -> 28346.34 | AV46: =N46+U46+AB46+AI46 -> 1848792.7 | AY46: Calendar Month | AZ46: 6
D47: =D46+1 -> 39 | E47: =IF(MONTH(EDATE($E$5,D47))<7,YEAR(EDATE($E$5,D47)),YEAR(EDATE($E$5,D47))+1) -> 2030 | F47: =EDATE($E$5,D47) -> 47391 | G47: =MONTH(F47) -> 9 | H47: =DAY(EOMONTH(F47,0)) -> 30 | I47: PI | J47: =IF(I47="PI",IF(N46<=0,0,N46),(IF(I47="IO",J46,"")))*IF(N46<=0,0,1) -> 31350.43 | K47: =(IF(I47="PI",J47,IF(ISNUMBER(N46),N46,J47))*$K$3/365*$H47*IF(J47>0,1,0)) -> 155.37789 | L47: =IF(I47="IO",0,$K$6-K47)*IF(J47>0,1,0) -> 1482.6221 | M47: =IF(I47="IO",$K$6-K47+IF(ISNUMBER(M46),M46,0),IF(ISNUMBER(M46),M46,0)) -> 0 | N47: =(J47+K47-$K$6-IF(I47="PI",0,M47))*IF(J47>0,1,0) -> 29867.808 | P47: PI | Q47: =IF(P47="PI",IF(U46<=0,0,U46),(IF(P47="IO",Q46,"")))*IF(U46<=0,0,1) -> 500063.32 | R47: =(IF(P47="PI",Q47,IF(ISNUMBER(U46),U46,Q47))*$R$3/365*$H47*IF(Q47>0,1,0)) -> 2544.1578 | S47: =IF(P47="IO",0,$R$6-R47)*IF(Q47>0,1,0) -> 1236.8422 | T47: =IF(P47="IO",$R$6-R47+IF(ISNUMBER(T46),T46,0),IF(ISNUMBER(T46),T46,0)) -> 0 | U47: =(Q47+R47-$R$6-IF(P47="PI",0,T47))*IF(Q47>0,1,0) -> 498826.48 | W47: PI | X47: =IF(W47="PI",IF(AB46<=0,0,AB46),(IF(W47="IO",X46,"")))*IF(AB46<=0,0,1) -> 435337.17 | Y47: =(IF(W47="PI",X47,IF(ISNUMBER(AB46),AB46,X47))*$Y$3/365*$H47*IF(X47>0,1,0)) -> 2214.8524 | Z47: =IF(W47="IO",0,$Y$6-Y47)*IF(X47>0,1,0) -> 669.14758 | AA47: =IF(W47="IO",$Y$6-Y47+IF(ISNUMBER(AA46),AA46,0),IF(ISNUMBER(AA46),AA46,0)) -> 0 | AB47: =(X47+Y47-$Y$6-IF(W47="PI",0,AA47))*IF(X47>0,1,0) -> 434668.03 | AD47: PI | AE47: =IF(AD47="PI",IF(AI46<=0,0,AI46),(IF(AD47="IO",AE46,"")))*IF(AI46<=0,0,1) -> 882041.79 | AF47: =(IF(AD47="PI",AE47,IF(ISNUMBER(AI46),AI46,AE47))*$AF$3/365*$H47*IF(AE47>0,1,0)) -> 4589.0338 | AG47: =IF(AD47="IO",0,$AF$6-AF47)*IF(AE47>0,1,0) -> 1452.9662 | AH47: =IF(AD47="IO",$AF$6-AF47+IF(ISNUMBER(AH46),AH46,0),IF(ISNUMBER(AH46),AH46,0)) -> 0 | AI47: =(AE47+AF47-$AF$6-IF(AD47="PI",0,AH47))*IF(AE47>0,1,0) -> 880588.82 | AK47: =E47 -> 2030 | AL47: =G47 -> 9 | AM47: =IF($AK47=$AK46,R47+AM46,R47) -> 7820.127 | AN47: =IF($AK47=$AK46,Y47+AN46,Y47) -> 6801.5379 | AO47: =IF($AK47=$AK46,AF47+AO46,AF47) -> 14093.855 | AP47: =AM47+AN47 -> 14621.665 | AQ47: =IF(AK47=AK46,AQ46,0)+ IF(J47>0,$K$6,0)+ IF(Q47>0,$R$6,0)+ IF(X47>0,$Y$6,0) -> 24909 | AR47: =N47+U47+AB47 -> 963362.31 | AS47: =AP47+AO47 -> 28715.52 | AT47: =IF(AK47=AK46,AT46,0)+ IF(J47>0,L47,0)+ IF(Q47>0,S47,0)+ IF(X47>0,Z47,0)+ IF(AE47>0,AG47,0) -> 13820.443 | AU47: =AS47+AT47 -> 42535.962 | AV47: =N47+U47+AB47+AI47 -> 1843951.1
D48: =D47+1 -> 40 | E48: =IF(MONTH(EDATE($E$5,D48))<7,YEAR(EDATE($E$5,D48)),YEAR(EDATE($E$5,D48))+1) -> 2030 | F48: =EDATE($E$5,D48) -> 47421 | G48: =MONTH(F48) -> 10 | H48: =DAY(EOMONTH(F48,0)) -> 31 | I48: PI | J48: =IF(I48="PI",IF(N47<=0,0,N47),(IF(I48="IO",J47,"")))*IF(N47<=0,0,1) -> 29867.808 | K48: =(IF(I48="PI",J48,IF(ISNUMBER(N47),N47,J48))*$K$3/365*$H48*IF(J48>0,1,0)) -> 152.96409 | L48: =IF(I48="IO",0,$K$6-K48)*IF(J48>0,1,0) -> 1485.0359 | M48: =IF(I48="IO",$K$6-K48+IF(ISNUMBER(M47),M47,0),IF(ISNUMBER(M47),M47,0)) -> 0 | N48: =(J48+K48-$K$6-IF(I48="PI",0,M48))*IF(J48>0,1,0) -> 28382.772 | P48: PI | Q48: =IF(P48="PI",IF(U47<=0,0,U47),(IF(P48="IO",Q47,"")))*IF(U47<=0,0,1) -> 498826.48 | R48: =(IF(P48="PI",Q48,IF(ISNUMBER(U47),U47,Q48))*$R$3/365*$H48*IF(Q48>0,1,0)) -> 2622.4606 | S48: =IF(P48="IO",0,$R$6-R48)*IF(Q48>0,1,0) -> 1158.5394 | T48: =IF(P48="IO",$R$6-R48+IF(ISNUMBER(T47),T47,0),IF(ISNUMBER(T47),T47,0)) -> 0 | U48: =(Q48+R48-$R$6-IF(P48="PI",0,T48))*IF(Q48>0,1,0) -> 497667.94 | W48: PI | X48: =IF(W48="PI",IF(AB47<=0,0,AB47),(IF(W48="IO",X47,"")))*IF(AB47<=0,0,1) -> 434668.03 | Y48: =(IF(W48="PI",X48,IF(ISNUMBER(AB47),AB47,X48))*$Y$3/365*$H48*IF(X48>0,1,0)) -> 2285.1629 | Z48: =IF(W48="IO",0,$Y$6-Y48)*IF(X48>0,1,0) -> 598.83705 | AA48: =IF(W48="IO",$Y$6-Y48+IF(ISNUMBER(AA47),AA47,0),IF(ISNUMBER(AA47),AA47,0)) -> 0 | AB48: =(X48+Y48-$Y$6-IF(W48="PI",0,AA48))*IF(X48>0,1,0) -> 434069.19 | AD48: PI | AE48: =IF(AD48="PI",IF(AI47<=0,0,AI47),(IF(AD48="IO",AE47,"")))*IF(AI47<=0,0,1) -> 880588.82 | AF48: =(IF(AD48="PI",AE48,IF(ISNUMBER(AI47),AI47,AE48))*$AF$3/365*$H48*IF(AE48>0,1,0)) -> 4734.1902 | AG48: =IF(AD48="IO",0,$AF$6-AF48)*IF(AE48>0,1,0) -> 1307.8098 | AH48: =IF(AD48="IO",$AF$6-AF48+IF(ISNUMBER(AH47),AH47,0),IF(ISNUMBER(AH47),AH47,0)) -> 0 | AI48: =(AE48+AF48-$AF$6-IF(AD48="PI",0,AH48))*IF(AE48>0,1,0) -> 879281.01 | AK48: =E48 -> 2030 | AL48: =G48 -> 10 | AM48: =IF($AK48=$AK47,R48+AM47,R48) -> 10442.588 | AN48: =IF($AK48=$AK47,Y48+AN47,Y48) -> 9086.7009 | AO48: =IF($AK48=$AK47,AF48+AO47,AF48) -> 18828.045 | AP48: =AM48+AN48 -> 19529.288 | AQ48: =IF(AK48=AK47,AQ47,0)+ IF(J48>0,$K$6,0)+ IF(Q48>0,$R$6,0)+ IF(X48>0,$Y$6,0) -> 33212 | AR48: =N48+U48+AB48 -> 960119.9 | AS48: =AP48+AO48 -> 38357.334 | AT48: =IF(AK48=AK47,AT47,0)+ IF(J48>0,L48,0)+ IF(Q48>0,S48,0)+ IF(X48>0,Z48,0)+ IF(AE48>0,AG48,0) -> 18370.665 | AU48: =AS48+AT48 -> 56727.998 | AV48: =N48+U48+AB48+AI48 -> 1839400.9 | AZ48: Column Labels
D49: =D48+1 -> 41 | E49: =IF(MONTH(EDATE($E$5,D49))<7,YEAR(EDATE($E$5,D49)),YEAR(EDATE($E$5,D49))+1) -> 2030 | F49: =EDATE($E$5,D49) -> 47452 | G49: =MONTH(F49) -> 11 | H49: =DAY(EOMONTH(F49,0)) -> 30 | I49: PI | J49: =IF(I49="PI",IF(N48<=0,0,N48),(IF(I49="IO",J48,"")))*IF(N48<=0,0,1) -> 28382.772 | K49: =(IF(I49="PI",J49,IF(ISNUMBER(N48),N48,J49))*$K$3/365*$H49*IF(J49>0,1,0)) -> 140.66968 | L49: =IF(I49="IO",0,$K$6-K49)*IF(J49>0,1,0) -> 1497.3303 | M49: =IF(I49="IO",$K$6-K49+IF(ISNUMBER(M48),M48,0),IF(ISNUMBER(M48),M48,0)) -> 0 | N49: =(J49+K49-$K$6-IF(I49="PI",0,M49))*IF(J49>0,1,0) -> 26885.442 | P49: PI | Q49: =IF(P49="PI",IF(U48<=0,0,U48),(IF(P49="IO",Q48,"")))*IF(U48<=0,0,1) -> 497667.94 | R49: =(IF(P49="PI",Q49,IF(ISNUMBER(U48),U48,Q49))*$R$3/365*$H49*IF(Q49>0,1,0)) -> 2531.9709 | S49: =IF(P49="IO",0,$R$6-R49)*IF(Q49>0,1,0) -> 1249.0291 | T49: =IF(P49="IO",$R$6-R49+IF(ISNUMBER(T48),T48,0),IF(ISNUMBER(T48),T48,0)) -> 0 | U49: =(Q49+R49-$R$6-IF(P49="PI",0,T49))*IF(Q49>0,1,0) -> 496418.91 | W49: PI | X49: =IF(W49="PI",IF(AB48<=0,0,AB48),(IF(W49="IO",X48,"")))*IF(AB48<=0,0,1) -> 434069.19 | Y49: =(IF(W49="PI",X49,IF(ISNUMBER(AB48),AB48,X49))*$Y$3/365*$H49*IF(X49>0,1,0)) -> 2208.4013 | Z49: =IF(W49="IO",0,$Y$6-Y49)*IF(X49>0,1,0) -> 675.59867 | AA49: =IF(W49="IO",$Y$6-Y49+IF(ISNUMBER(AA48),AA48,0),IF(ISNUMBER(AA48),AA48,0)) -> 0 | AB49: =(X49+Y49-$Y$6-IF(W49="PI",0,AA49))*IF(X49>0,1,0) -> 433393.59 | AD49: PI | AE49: =IF(AD49="PI",IF(AI48<=0,0,AI48),(IF(AD49="IO",AE48,"")))*IF(AI48<=0,0,1) -> 879281.01 | AF49: =(IF(AD49="PI",AE49,IF(ISNUMBER(AI48),AI48,AE49))*$AF$3/365*$H49*IF(AE49>0,1,0)) -> 4574.6702 | AG49: =IF(AD49="IO",0,$AF$6-AF49)*IF(AE49>0,1,0) -> 1467.3298 | AH49: =IF(AD49="IO",$AF$6-AF49+IF(ISNUMBER(AH48),AH48,0),IF(ISNUMBER(AH48),AH48,0)) -> 0 | AI49: =(AE49+AF49-$AF$6-IF(AD49="PI",0,AH49))*IF(AE49>0,1,0) -> 877813.68 | AK49: =E49 -> 2030 | AL49: =G49 -> 11 | AM49: =IF($AK49=$AK48,R49+AM48,R49) -> 12974.558 | AN49: =IF($AK49=$AK48,Y49+AN48,Y49) -> 11295.102 | AO49: =IF($AK49=$AK48,AF49+AO48,AF49) -> 23402.715 | AP49: =AM49+AN49 -> 24269.661 | AQ49: =IF(AK49=AK48,AQ48,0)+ IF(J49>0,$K$6,0)+ IF(Q49>0,$R$6,0)+ IF(X49>0,$Y$6,0) -> 41515 | AR49: =N49+U49+AB49 -> 956697.94 | AS49: =AP49+AO49 -> 47672.376 | AT49: =IF(AK49=AK48,AT48,0)+ IF(J49>0,L49,0)+ IF(Q49>0,S49,0)+ IF(X49>0,Z49,0)+ IF(AE49>0,AG49,0) -> 23259.952 | AU49: =AS49+AT49 -> 70932.328 | AV49: =N49+U49+AB49+AI49 -> 1834511.6 | AZ49: 2027 | BA49: 2028 | BB49: 2029 | BC49: 2030 | BD49: 2031 | BE49: 2032 | BF49: 2033 | BG49: 2034 | BH49: 2035 | BI49: 2036 | BJ49: 2037 | BK49: 2038 | BL49: 2039 | BM49: 2040 | BN49: 2041 | BO49: 2042 | BP49: 2043 | BQ49: 2044 | BR49: 2045 | BS49: 2046 | BT49: 2047 | BU49: 2048 | BV49: 2049 | BW49: 2050 | BX49: 2051 | BY49: 2052 | BZ49: 2053 | CA49: 2054 | CB49: 2055
D50: =D49+1 -> 42 | E50: =IF(MONTH(EDATE($E$5,D50))<7,YEAR(EDATE($E$5,D50)),YEAR(EDATE($E$5,D50))+1) -> 2030 | F50: =EDATE($E$5,D50) -> 47482 | G50: =MONTH(F50) -> 12 | H50: =DAY(EOMONTH(F50,0)) -> 31 | I50: PI | J50: =IF(I50="PI",IF(N49<=0,0,N49),(IF(I50="IO",J49,"")))*IF(N49<=0,0,1) -> 26885.442 | K50: =(IF(I50="PI",J50,IF(ISNUMBER(N49),N49,J50))*$K$3/365*$H50*IF(J50>0,1,0)) -> 137.69029 | L50: =IF(I50="IO",0,$K$6-K50)*IF(J50>0,1,0) -> 1500.3097 | M50: =IF(I50="IO",$K$6-K50+IF(ISNUMBER(M49),M49,0),IF(ISNUMBER(M49),M49,0)) -> 0 | N50: =(J50+K50-$K$6-IF(I50="PI",0,M50))*IF(J50>0,1,0) -> 25385.132 | P50: PI | Q50: =IF(P50="PI",IF(U49<=0,0,U49),(IF(P50="IO",Q49,"")))*IF(U49<=0,0,1) -> 496418.91 | R50: =(IF(P50="PI",Q50,IF(ISNUMBER(U49),U49,Q50))*$R$3/365*$H50*IF(Q50>0,1,0)) -> 2609.8034 | S50: =IF(P50="IO",0,$R$6-R50)*IF(Q50>0,1,0) -> 1171.1966 | T50: =IF(P50="IO",$R$6-R50+IF(ISNUMBER(T49),T49,0),IF(ISNUMBER(T49),T49,0)) -> 0 | U50: =(Q50+R50-$R$6-IF(P50="PI",0,T50))*IF(Q50>0,1,0) -> 495247.71 | W50: PI | X50: =IF(W50="PI",IF(AB49<=0,0,AB49),(IF(W50="IO",X49,"")))*IF(AB49<=0,0,1) -> 433393.59 | Y50: =(IF(W50="PI",X50,IF(ISNUMBER(AB49),AB49,X50))*$Y$3/365*$H50*IF(X50>0,1,0)) -> 2278.4629 | Z50: =IF(W50="IO",0,$Y$6-Y50)*IF(X50>0,1,0) -> 605.53709 | AA50: =IF(W50="IO",$Y$6-Y50+IF(ISNUMBER(AA49),AA49,0),IF(ISNUMBER(AA49),AA49,0)) -> 0 | AB50: =(X50+Y50-$Y$6-IF(W50="PI",0,AA50))*IF(X50>0,1,0) -> 432788.05 | AD50: PI | AE50: =IF(AD50="PI",IF(AI49<=0,0,AI49),(IF(AD50="IO",AE49,"")))*IF(AI49<=0,0,1) -> 877813.68 | AF50: =(IF(AD50="PI",AE50,IF(ISNUMBER(AI49),AI49,AE50))*$AF$3/365*$H50*IF(AE50>0,1,0)) -> 4719.2706 | AG50: =IF(AD50="IO",0,$AF$6-AF50)*IF(AE50>0,1,0) -> 1322.7294 | AH50: =IF(AD50="IO",$AF$6-AF50+IF(ISNUMBER(AH49),AH49,0),IF(ISNUMBER(AH49),AH49,0)) -> 0 | AI50: =(AE50+AF50-$AF$6-IF(AD50="PI",0,AH50))*IF(AE50>0,1,0) -> 876490.95 | AK50: =E50 -> 2030 | AL50: =G50 -> 12 | AM50: =IF($AK50=$AK49,R50+AM49,R50) -> 15584.362 | AN50: =IF($AK50=$AK49,Y50+AN49,Y50) -> 13573.565 | AO50: =IF($AK50=$AK49,AF50+AO49,AF50) -> 28121.986 | AP50: =AM50+AN50 -> 29157.927 | AQ50: =IF(AK50=AK49,AQ49,0)+ IF(J50>0,$K$6,0)+ IF(Q50>0,$R$6,0)+ IF(X50>0,$Y$6,0) -> 49818 | AR50: =N50+U50+AB50 -> 953420.9 | AS50: =AP50+AO50 -> 57279.913 | AT50: =IF(AK50=AK49,AT49,0)+ IF(J50>0,L50,0)+ IF(Q50>0,S50,0)+ IF(X50>0,Z50,0)+ IF(AE50>0,AG50,0) -> 27859.725 | AU50: =AS50+AT50 -> 85139.638 | AV50: =N50+U50+AB50+AI50 -> 1829911.8 | AX50: Principal Repayments | AY50: Sum of Total Principal | AZ50: 47853.327 | BA50: 50558.094 | BB50: 54110.983 | BC50: 57551.961 | BD50: 59567.123 | BE50: 44411.925 | BF50: 47569.306 | BG50: 50629.249 | BH50: 53886.052 | BI50: 57087.435 | BJ50: 61024.646 | BK50: 64950.24 | BL50: 69128.391 | BM50: 73356.153 | BN50: 78294.292 | BO50: 83330.964 | BP50: 88691.687 | BQ50: 94236.829 | BR50: 100459.69 | BS50: 106922.46 | BT50: 113801.05 | BU50: 109630.35 | BV50: 81484.734 | BW50: 86757.68 | BX50: 92371.882 | BY50: 98327.062 | BZ50: 67901.883 | CA50: 22623.474 | CB50: 0
D51: =D50+1 -> 43 | E51: =IF(MONTH(EDATE($E$5,D51))<7,YEAR(EDATE($E$5,D51)),YEAR(EDATE($E$5,D51))+1) -> 2030 | F51: =EDATE($E$5,D51) -> 47513 | G51: =MONTH(F51) -> 1 | H51: =DAY(EOMONTH(F51,0)) -> 31 | I51: PI | J51: =IF(I51="PI",IF(N50<=0,0,N50),(IF(I51="IO",J50,"")))*IF(N50<=0,0,1) -> 25385.132 | K51: =(IF(I51="PI",J51,IF(ISNUMBER(N50),N50,J51))*$K$3/365*$H51*IF(J51>0,1,0)) -> 130.00665 | L51: =IF(I51="IO",0,$K$6-K51)*IF(J51>0,1,0) -> 1507.9933 | M51: =IF(I51="IO",$K$6-K51+IF(ISNUMBER(M50),M50,0),IF(ISNUMBER(M50),M50,0)) -> 0 | N51: =(J51+K51-$K$6-IF(I51="PI",0,M51))*IF(J51>0,1,0) -> 23877.139 | P51: PI | Q51: =IF(P51="PI",IF(U50<=0,0,U50),(IF(P51="IO",Q50,"")))*IF(U50<=0,0,1) -> 495247.71 | R51: =(IF(P51="PI",Q51,IF(ISNUMBER(U50),U50,Q51))*$R$3/365*$H51*IF(Q51>0,1,0)) -> 2603.6461 | S51: =IF(P51="IO",0,$R$6-R51)*IF(Q51>0,1,0) -> 1177.3539 | T51: =IF(P51="IO",$R$6-R51+IF(ISNUMBER(T50),T50,0),IF(ISNUMBER(T50),T50,0)) -> 0 | U51: =(Q51+R51-$R$6-IF(P51="PI",0,T51))*IF(Q51>0,1,0) -> 494070.36 | W51: PI | X51: =IF(W51="PI",IF(AB50<=0,0,AB50),(IF(W51="IO",X50,"")))*IF(AB50<=0,0,1) -> 432788.05 | Y51: =(IF(W51="PI",X51,IF(ISNUMBER(AB50),AB50,X51))*$Y$3/365*$H51*IF(X51>0,1,0)) -> 2275.2794 | Z51: =IF(W51="IO",0,$Y$6-Y51)*IF(X51>0,1,0) -> 608.72056 | AA51: =IF(W51="IO",$Y$6-Y51+IF(ISNUMBER(AA50),AA50,0),IF(ISNUMBER(AA50),AA50,0)) -> 0 | AB51: =(X51+Y51-$Y$6-IF(W51="PI",0,AA51))*IF(X51>0,1,0) -> 432179.33 | AD51: PI | AE51: =IF(AD51="PI",IF(AI50<=0,0,AI50),(IF(AD51="IO",AE50,"")))*IF(AI50<=0,0,1) -> 876490.95 | AF51: =(IF(AD51="PI",AE51,IF(ISNUMBER(AI50),AI50,AE51))*$AF$3/365*$H51*IF(AE51>0,1,0)) -> 4712.1594 | AG51: =IF(AD51="IO",0,$AF$6-AF51)*IF(AE51>0,1,0) -> 1329.8406 | AH51: =IF(AD51="IO",$AF$6-AF51+IF(ISNUMBER(AH50),AH50,0),IF(ISNUMBER(AH50),AH50,0)) -> 0 | AI51: =(AE51+AF51-$AF$6-IF(AD51="PI",0,AH51))*IF(AE51>0,1,0) -> 875161.11 | AK51: =E51 -> 2030 | AL51: =G51 -> 1 | AM51: =IF($AK51=$AK50,R51+AM50,R51) -> 18188.008 | AN51: =IF($AK51=$AK50,Y51+AN50,Y51) -> 15848.845 | AO51: =IF($AK51=$AK50,AF51+AO50,AF51) -> 32834.145 | AP51: =AM51+AN51 -> 34036.853 | AQ51: =IF(AK51=AK50,AQ50,0)+ IF(J51>0,$K$6,0)+ IF(Q51>0,$R$6,0)+ IF(X51>0,$Y$6,0) -> 58121 | AR51: =N51+U51+AB51 -> 950126.83 | AS51: =AP51+AO51 -> 66870.998 | AT51: =IF(AK51=AK50,AT50,0)+ IF(J51>0,L51,0)+ IF(Q51>0,S51,0)+ IF(X51>0,Z51,0)+ IF(AE51>0,AG51,0) -> 32483.634 | AU51: =AS51+AT51 -> 99354.632 | AV51: =N51+U51+AB51+AI51 -> 1825287.9
D52: =D51+1 -> 44 | E52: =IF(MONTH(EDATE($E$5,D52))<7,YEAR(EDATE($E$5,D52)),YEAR(EDATE($E$5,D52))+1) -> 2030 | F52: =EDATE($E$5,D52) -> 47542 | G52: =MONTH(F52) -> 2 | H52: =DAY(EOMONTH(F52,0)) -> 28 | I52: PI | J52: =IF(I52="PI",IF(N51<=0,0,N51),(IF(I52="IO",J51,"")))*IF(N51<=0,0,1) -> 23877.139 | K52: =(IF(I52="PI",J52,IF(ISNUMBER(N51),N51,J52))*$K$3/365*$H52*IF(J52>0,1,0)) -> 110.44976 | L52: =IF(I52="IO",0,$K$6-K52)*IF(J52>0,1,0) -> 1527.5502 | M52: =IF(I52="IO",$K$6-K52+IF(ISNUMBER(M51),M51,0),IF(ISNUMBER(M51),M51,0)) -> 0 | N52: =(J52+K52-$K$6-IF(I52="PI",0,M52))*IF(J52>0,1,0) -> 22349.588 | P52: PI | Q52: =IF(P52="PI",IF(U51<=0,0,U51),(IF(P52="IO",Q51,"")))*IF(U51<=0,0,1) -> 494070.36 | R52: =(IF(P52="PI",Q52,IF(ISNUMBER(U51),U51,Q52))*$R$3/365*$H52*IF(Q52>0,1,0)) -> 2346.0897 | S52: =IF(P52="IO",0,$R$6-R52)*IF(Q52>0,1,0) -> 1434.9103 | T52: =IF(P52="IO",$R$6-R52+IF(ISNUMBER(T51),T51,0),IF(ISNUMBER(T51),T51,0)) -> 0 | U52: =(Q52+R52-$R$6-IF(P52="PI",0,T52))*IF(Q52>0,1,0) -> 492635.45 | W52: PI | X52: =IF(W52="PI",IF(AB51<=0,0,AB51),(IF(W52="IO",X51,"")))*IF(AB51<=0,0,1) -> 432179.33 | Y52: =(IF(W52="PI",X52,IF(ISNUMBER(AB51),AB51,X52))*$Y$3/365*$H52*IF(X52>0,1,0)) -> 2052.2006 | Z52: =IF(W52="IO",0,$Y$6-Y52)*IF(X52>0,1,0) -> 831.7994 | AA52: =IF(W52="IO",$Y$6-Y52+IF(ISNUMBER(AA51),AA51,0),IF(ISNUMBER(AA51),AA51,0)) -> 0 | AB52: =(X52+Y52-$Y$6-IF(W52="PI",0,AA52))*IF(X52>0,1,0) -> 431347.53 | AD52: PI | AE52: =IF(AD52="PI",IF(AI51<=0,0,AI51),(IF(AD52="IO",AE51,"")))*IF(AI51<=0,0,1) -> 875161.11 | AF52: =(IF(AD52="PI",AE52,IF(ISNUMBER(AI51),AI51,AE52))*$AF$3/365*$H52*IF(AE52>0,1,0)) -> 4249.6864 | AG52: =IF(AD52="IO",0,$AF$6-AF52)*IF(AE52>0,1,0) -> 1792.3136 | AH52: =IF(AD52="IO",$AF$6-AF52+IF(ISNUMBER(AH51),AH51,0),IF(ISNUMBER(AH51),AH51,0)) -> 0 | AI52: =(AE52+AF52-$AF$6-IF(AD52="PI",0,AH52))*IF(AE52>0,1,0) -> 873368.8 | AK52: =E52 -> 2030 | AL52: =G52 -> 2 | AM52: =IF($AK52=$AK51,R52+AM51,R52) -> 20534.098 | AN52: =IF($AK52=$AK51,Y52+AN51,Y52) -> 17901.045 | AO52: =IF($AK52=$AK51,AF52+AO51,AF52) -> 37083.832 | AP52: =AM52+AN52 -> 38435.143 | AQ52: =IF(AK52=AK51,AQ51,0)+ IF(J52>0,$K$6,0)+ IF(Q52>0,$R$6,0)+ IF(X52>0,$Y$6,0) -> 66424 | AR52: =N52+U52+AB52 -> 946332.57 | AS52: =AP52+AO52 -> 75518.975 | AT52: =IF(AK52=AK51,AT51,0)+ IF(J52>0,L52,0)+ IF(Q52>0,S52,0)+ IF(X52>0,Z52,0)+ IF(AE52>0,AG52,0) -> 38070.207 | AU52: =AS52+AT52 -> 113589.18 | AV52: =N52+U52+AB52+AI52 -> 1819701.4
D53: =D52+1 -> 45 | E53: =IF(MONTH(EDATE($E$5,D53))<7,YEAR(EDATE($E$5,D53)),YEAR(EDATE($E$5,D53))+1) -> 2030 | F53: =EDATE($E$5,D53) -> 47572 | G53: =MONTH(F53) -> 3 | H53: =DAY(EOMONTH(F53,0)) -> 31 | I53: PI | J53: =IF(I53="PI",IF(N52<=0,0,N52),(IF(I53="IO",J52,"")))*IF(N52<=0,0,1) -> 22349.588 | K53: =(IF(I53="PI",J53,IF(ISNUMBER(N52),N52,J53))*$K$3/365*$H53*IF(J53>0,1,0)) -> 114.46051 | L53: =IF(I53="IO",0,$K$6-K53)*IF(J53>0,1,0) -> 1523.5395 | M53: =IF(I53="IO",$K$6-K53+IF(ISNUMBER(M52),M52,0),IF(ISNUMBER(M52),M52,0)) -> 0 | N53: =(J53+K53-$K$6-IF(I53="PI",0,M53))*IF(J53>0,1,0) -> 20826.049 | P53: PI | Q53: =IF(P53="PI",IF(U52<=0,0,U52),(IF(P53="IO",Q52,"")))*IF(U52<=0,0,1) -> 492635.45 | R53: =(IF(P53="PI",Q53,IF(ISNUMBER(U52),U52,Q53))*$R$3/365*$H53*IF(Q53>0,1,0)) -> 2589.9128 | S53: =IF(P53="IO",0,$R$6-R53)*IF(Q53>0,1,0) -> 1191.0872 | T53: =IF(P53="IO",$R$6-R53+IF(ISNUMBER(T52),T52,0),IF(ISNUMBER(T52),T52,0)) -> 0 | U53: =(Q53+R53-$R$6-IF(P53="PI",0,T53))*IF(Q53>0,1,0) -> 491444.36 | W53: PI | X53: =IF(W53="PI",IF(AB52<=0,0,AB52),(IF(W53="IO",X52,"")))*IF(AB52<=0,0,1) -> 431347.53 | Y53: =(IF(W53="PI",X53,IF(ISNUMBER(AB52),AB52,X53))*$Y$3/365*$H53*IF(X53>0,1,0)) -> 2267.7063 | Z53: =IF(W53="IO",0,$Y$6-Y53)*IF(X53>0,1,0) -> 616.29375 | AA53: =IF(W53="IO",$Y$6-Y53+IF(ISNUMBER(AA52),AA52,0),IF(ISNUMBER(AA52),AA52,0)) -> 0 | AB53: =(X53+Y53-$Y$6-IF(W53="PI",0,AA53))*IF(X53>0,1,0) -> 430731.24 | AD53: PI | AE53: =IF(AD53="PI",IF(AI52<=0,0,AI52),(IF(AD53="IO",AE52,"")))*IF(AI52<=0,0,1) -> 873368.8 | AF53: =(IF(AD53="PI",AE53,IF(ISNUMBER(AI52),AI52,AE53))*$AF$3/365*$H53*IF(AE53>0,1,0)) -> 4695.3742 | AG53: =IF(AD53="IO",0,$AF$6-AF53)*IF(AE53>0,1,0) -> 1346.6258 | AH53: =IF(AD53="IO",$AF$6-AF53+IF(ISNUMBER(AH52),AH52,0),IF(ISNUMBER(AH52),AH52,0)) -> 0 | AI53: =(AE53+AF53-$AF$6-IF(AD53="PI",0,AH53))*IF(AE53>0,1,0) -> 872022.17 | AK53: =E53 -> 2030 | AL53: =G53 -> 3 | AM53: =IF($AK53=$AK52,R53+AM52,R53) -> 23124.011 | AN53: =IF($AK53=$AK52,Y53+AN52,Y53) -> 20168.751 | AO53: =IF($AK53=$AK52,AF53+AO52,AF53) -> 41779.206 | AP53: =AM53+AN53 -> 43292.762 | AQ53: =IF(AK53=AK52,AQ52,0)+ IF(J53>0,$K$6,0)+ IF(Q53>0,$R$6,0)+ IF(X53>0,$Y$6,0) -> 74727 | AR53: =N53+U53+AB53 -> 943001.65 | AS53: =AP53+AO53 -> 85071.968 | AT53: =IF(AK53=AK52,AT52,0)+ IF(J53>0,L53,0)+ IF(Q53>0,S53,0)+ IF(X53>0,Z53,0)+ IF(AE53>0,AG53,0) -> 42747.753 | AU53: =AS53+AT53 -> 127819.72 | AV53: =N53+U53+AB53+AI53 -> 1815023.8
D54: =D53+1 -> 46 | E54: =IF(MONTH(EDATE($E$5,D54))<7,YEAR(EDATE($E$5,D54)),YEAR(EDATE($E$5,D54))+1) -> 2030 | F54: =EDATE($E$5,D54) -> 47603 | G54: =MONTH(F54) -> 4 | H54: =DAY(EOMONTH(F54,0)) -> 30 | I54: PI | J54: =IF(I54="PI",IF(N53<=0,0,N53),(IF(I54="IO",J53,"")))*IF(N53<=0,0,1) -> 20826.049 | K54: =(IF(I54="PI",J54,IF(ISNUMBER(N53),N53,J54))*$K$3/365*$H54*IF(J54>0,1,0)) -> 103.21732 | L54: =IF(I54="IO",0,$K$6-K54)*IF(J54>0,1,0) -> 1534.7827 | M54: =IF(I54="IO",$K$6-K54+IF(ISNUMBER(M53),M53,0),IF(ISNUMBER(M53),M53,0)) -> 0 | N54: =(J54+K54-$K$6-IF(I54="PI",0,M54))*IF(J54>0,1,0) -> 19291.266 | P54: PI | Q54: =IF(P54="PI",IF(U53<=0,0,U53),(IF(P54="IO",Q53,"")))*IF(U53<=0,0,1) -> 491444.36 | R54: =(IF(P54="PI",Q54,IF(ISNUMBER(U53),U53,Q54))*$R$3/365*$H54*IF(Q54>0,1,0)) -> 2500.3073 | S54: =IF(P54="IO",0,$R$6-R54)*IF(Q54>0,1,0) -> 1280.6927 | T54: =IF(P54="IO",$R$6-R54+IF(ISNUMBER(T53),T53,0),IF(ISNUMBER(T53),T53,0)) -> 0 | U54: =(Q54+R54-$R$6-IF(P54="PI",0,T54))*IF(Q54>0,1,0) -> 490163.67 | W54: PI | X54: =IF(W54="PI",IF(AB53<=0,0,AB53),(IF(W54="IO",X53,"")))*IF(AB53<=0,0,1) -> 430731.24 | Y54: =(IF(W54="PI",X54,IF(ISNUMBER(AB53),AB53,X54))*$Y$3/365*$H54*IF(X54>0,1,0)) -> 2191.4189 | Z54: =IF(W54="IO",0,$Y$6-Y54)*IF(X54>0,1,0) -> 692.58106 | AA54: =IF(W54="IO",$Y$6-Y54+IF(ISNUMBER(AA53),AA53,0),IF(ISNUMBER(AA53),AA53,0)) -> 0 | AB54: =(X54+Y54-$Y$6-IF(W54="PI",0,AA54))*IF(X54>0,1,0) -> 430038.66 | AD54: PI | AE54: =IF(AD54="PI",IF(AI53<=0,0,AI53),(IF(AD54="IO",AE53,"")))*IF(AI53<=0,0,1) -> 872022.17 | AF54: =(IF(AD54="PI",AE54,IF(ISNUMBER(AI53),AI53,AE54))*$AF$3/365*$H54*IF(AE54>0,1,0)) -> 4536.9044 | AG54: =IF(AD54="IO",0,$AF$6-AF54)*IF(AE54>0,1,0) -> 1505.0956 | AH54: =IF(AD54="IO",$AF$6-AF54+IF(ISNUMBER(AH53),AH53,0),IF(ISNUMBER(AH53),AH53,0)) -> 0 | AI54: =(AE54+AF54-$AF$6-IF(AD54="PI",0,AH54))*IF(AE54>0,1,0) -> 870517.07 | AK54: =E54 -> 2030 | AL54: =G54 -> 4 | AM54: =IF($AK54=$AK53,R54+AM53,R54) -> 25624.318 | AN54: =IF($AK54=$AK53,Y54+AN53,Y54) -> 22360.17 | AO54: =IF($AK54=$AK53,AF54+AO53,AF54) -> 46316.11 | AP54: =AM54+AN54 -> 47984.488 | AQ54: =IF(AK54=AK53,AQ53,0)+ IF(J54>0,$K$6,0)+ IF(Q54>0,$R$6,0)+ IF(X54>0,$Y$6,0) -> 83030 | AR54: =N54+U54+AB54 -> 939493.59 | AS54: =AP54+AO54 -> 94300.599 | AT54: =IF(AK54=AK53,AT53,0)+ IF(J54>0,L54,0)+ IF(Q54>0,S54,0)+ IF(X54>0,Z54,0)+ IF(AE54>0,AG54,0) -> 47760.905 | AU54: =AS54+AT54 -> 142061.5 | AV54: =N54+U54+AB54+AI54 -> 1810010.7
D55: =D54+1 -> 47 | E55: =IF(MONTH(EDATE($E$5,D55))<7,YEAR(EDATE($E$5,D55)),YEAR(EDATE($E$5,D55))+1) -> 2030 | F55: =EDATE($E$5,D55) -> 47633 | G55: =MONTH(F55) -> 5 | H55: =DAY(EOMONTH(F55,0)) -> 31 | I55: PI | J55: =IF(I55="PI",IF(N54<=0,0,N54),(IF(I55="IO",J54,"")))*IF(N54<=0,0,1) -> 19291.266 | K55: =(IF(I55="PI",J55,IF(ISNUMBER(N54),N54,J55))*$K$3/365*$H55*IF(J55>0,1,0)) -> 98.79771 | L55: =IF(I55="IO",0,$K$6-K55)*IF(J55>0,1,0) -> 1539.2023 | M55: =IF(I55="IO",$K$6-K55+IF(ISNUMBER(M54),M54,0),IF(ISNUMBER(M54),M54,0)) -> 0 | N55: =(J55+K55-$K$6-IF(I55="PI",0,M55))*IF(J55>0,1,0) -> 17752.064 | P55: PI | Q55: =IF(P55="PI",IF(U54<=0,0,U54),(IF(P55="IO",Q54,"")))*IF(U54<=0,0,1) -> 490163.67 | R55: =(IF(P55="PI",Q55,IF(ISNUMBER(U54),U54,Q55))*$R$3/365*$H55*IF(Q55>0,1,0)) -> 2576.918 | S55: =IF(P55="IO",0,$R$6-R55)*IF(Q55>0,1,0) -> 1204.082 | T55: =IF(P55="IO",$R$6-R55+IF(ISNUMBER(T54),T54,0),IF(ISNUMBER(T54),T54,0)) -> 0 | U55: =(Q55+R55-$R$6-IF(P55="PI",0,T55))*IF(Q55>0,1,0) -> 488959.59 | W55: PI | X55: =IF(W55="PI",IF(AB54<=0,0,AB54),(IF(W55="IO",X54,"")))*IF(AB54<=0,0,1) -> 430038.66 | Y55: =(IF(W55="PI",X55,IF(ISNUMBER(AB54),AB54,X55))*$Y$3/365*$H55*IF(X55>0,1,0)) -> 2260.8252 | Z55: =IF(W55="IO",0,$Y$6-Y55)*IF(X55>0,1,0) -> 623.17484 | AA55: =IF(W55="IO",$Y$6-Y55+IF(ISNUMBER(AA54),AA54,0),IF(ISNUMBER(AA54),AA54,0)) -> 0 | AB55: =(X55+Y55-$Y$6-IF(W55="PI",0,AA55))*IF(X55>0,1,0) -> 429415.48 | AD55: PI | AE55: =IF(AD55="PI",IF(AI54<=0,0,AI54),(IF(AD55="IO",AE54,"")))*IF(AI54<=0,0,1) -> 870517.07 | AF55: =(IF(AD55="PI",AE55,IF(ISNUMBER(AI54),AI54,AE55))*$AF$3/365*$H55*IF(AE55>0,1,0)) -> 4680.0429 | AG55: =IF(AD55="IO",0,$AF$6-AF55)*IF(AE55>0,1,0) -> 1361.9571 | AH55: =IF(AD55="IO",$AF$6-AF55+IF(ISNUMBER(AH54),AH54,0),IF(ISNUMBER(AH54),AH54,0)) -> 0 | AI55: =(AE55+AF55-$AF$6-IF(AD55="PI",0,AH55))*IF(AE55>0,1,0) -> 869155.12 | AK55: =E55 -> 2030 | AL55: =G55 -> 5 | AM55: =IF($AK55=$AK54,R55+AM54,R55) -> 28201.236 | AN55: =IF($AK55=$AK54,Y55+AN54,Y55) -> 24620.996 | AO55: =IF($AK55=$AK54,AF55+AO54,AF55) -> 50996.153 | AP55: =AM55+AN55 -> 52822.231 | AQ55: =IF(AK55=AK54,AQ54,0)+ IF(J55>0,$K$6,0)+ IF(Q55>0,$R$6,0)+ IF(X55>0,$Y$6,0) -> 91333 | AR55: =N55+U55+AB55 -> 936127.14 | AS55: =AP55+AO55 -> 103818.38 | AT55: =IF(AK55=AK54,AT54,0)+ IF(J55>0,L55,0)+ IF(Q55>0,S55,0)+ IF(X55>0,Z55,0)+ IF(AE55>0,AG55,0) -> 52489.322 | AU55: =AS55+AT55 -> 156307.71 | AV55: =N55+U55+AB55+AI55 -> 1805282.3
D56: =D55+1 -> 48 | E56: =IF(MONTH(EDATE($E$5,D56))<7,YEAR(EDATE($E$5,D56)),YEAR(EDATE($E$5,D56))+1) -> 2030 | F56: =EDATE($E$5,D56) -> 47664 | G56: =MONTH(F56) -> 6 | H56: =DAY(EOMONTH(F56,0)) -> 30 | I56: PI | J56: =IF(I56="PI",IF(N55<=0,0,N55),(IF(I56="IO",J55,"")))*IF(N55<=0,0,1) -> 17752.064 | K56: =(IF(I56="PI",J56,IF(ISNUMBER(N55),N55,J56))*$K$3/365*$H56*IF(J56>0,1,0)) -> 87.982147 | L56: =IF(I56="IO",0,$K$6-K56)*IF(J56>0,1,0) -> 1550.0179 | M56: =IF(I56="IO",$K$6-K56+IF(ISNUMBER(M55),M55,0),IF(ISNUMBER(M55),M55,0)) -> 0 | N56: =(J56+K56-$K$6-IF(I56="PI",0,M56))*IF(J56>0,1,0) -> 16202.046 | P56: PI | Q56: =IF(P56="PI",IF(U55<=0,0,U55),(IF(P56="IO",Q55,"")))*IF(U55<=0,0,1) -> 488959.59 | R56: =(IF(P56="PI",Q56,IF(ISNUMBER(U55),U55,Q56))*$R$3/365*$H56*IF(Q56>0,1,0)) -> 2487.6656 | S56: =IF(P56="IO",0,$R$6-R56)*IF(Q56>0,1,0) -> 1293.3344 | T56: =IF(P56="IO",$R$6-R56+IF(ISNUMBER(T55),T55,0),IF(ISNUMBER(T55),T55,0)) -> 0 | U56: =(Q56+R56-$R$6-IF(P56="PI",0,T56))*IF(Q56>0,1,0) -> 487666.25 | W56: PI | X56: =IF(W56="PI",IF(AB55<=0,0,AB55),(IF(W56="IO",X55,"")))*IF(AB55<=0,0,1) -> 429415.48 | Y56: =(IF(W56="PI",X56,IF(ISNUMBER(AB55),AB55,X56))*$Y$3/365*$H56*IF(X56>0,1,0)) -> 2184.7248 | Z56: =IF(W56="IO",0,$Y$6-Y56)*IF(X56>0,1,0) -> 699.2752 | AA56: =IF(W56="IO",$Y$6-Y56+IF(ISNUMBER(AA55),AA55,0),IF(ISNUMBER(AA55),AA55,0)) -> 0 | AB56: =(X56+Y56-$Y$6-IF(W56="PI",0,AA56))*IF(X56>0,1,0) -> 428716.21 | AD56: PI | AE56: =IF(AD56="PI",IF(AI55<=0,0,AI55),(IF(AD56="IO",AE55,"")))*IF(AI55<=0,0,1) -> 869155.12 | AF56: =(IF(AD56="PI",AE56,IF(ISNUMBER(AI55),AI55,AE56))*$AF$3/365*$H56*IF(AE56>0,1,0)) -> 4521.9879 | AG56: =IF(AD56="IO",0,$AF$6-AF56)*IF(AE56>0,1,0) -> 1520.0121 | AH56: =IF(AD56="IO",$AF$6-AF56+IF(ISNUMBER(AH55),AH55,0),IF(ISNUMBER(AH55),AH55,0)) -> 0 | AI56: =(AE56+AF56-$AF$6-IF(AD56="PI",0,AH56))*IF(AE56>0,1,0) -> 867635.11 | AK56: =E56 -> 2030 | AL56: =G56 -> 6 | AM56: =IF($AK56=$AK55,R56+AM55,R56) -> 30688.901 | AN56: =IF($AK56=$AK55,Y56+AN55,Y56) -> 26805.72 | AO56: =IF($AK56=$AK55,AF56+AO55,AF56) -> 55518.141 | AP56: =AM56+AN56 -> 57494.622 | AQ56: =IF(AK56=AK55,AQ55,0)+ IF(J56>0,$K$6,0)+ IF(Q56>0,$R$6,0)+ IF(X56>0,$Y$6,0) -> 99636 | AR56: =N56+U56+AB56 -> 932584.51 | AS56: =AP56+AO56 -> 113012.76 | AT56: =IF(AK56=AK55,AT55,0)+ IF(J56>0,L56,0)+ IF(Q56>0,S56,0)+ IF(X56>0,Z56,0)+ IF(AE56>0,AG56,0) -> 57551.961 | AU56: =AS56+AT56 -> 170564.72 | AV56: =N56+U56+AB56+AI56 -> 1800219.6
D57: =D56+1 -> 49 | E57: =IF(MONTH(EDATE($E$5,D57))<7,YEAR(EDATE($E$5,D57)),YEAR(EDATE($E$5,D57))+1) -> 2031 | F57: =EDATE($E$5,D57) -> 47694 | G57: =MONTH(F57) -> 7 | H57: =DAY(EOMONTH(F57,0)) -> 31 | I57: PI | J57: =IF(I57="PI",IF(N56<=0,0,N56),(IF(I57="IO",J56,"")))*IF(N56<=0,0,1) -> 16202.046 | K57: =(IF(I57="PI",J57,IF(ISNUMBER(N56),N56,J57))*$K$3/365*$H57*IF(J57>0,1,0)) -> 82.976671 | L57: =IF(I57="IO",0,$K$6-K57)*IF(J57>0,1,0) -> 1555.0233 | M57: =IF(I57="IO",$K$6-K57+IF(ISNUMBER(M56),M56,0),IF(ISNUMBER(M56),M56,0)) -> 0 | N57: =(J57+K57-$K$6-IF(I57="PI",0,M57))*IF(J57>0,1,0) -> 14647.023 | P57: PI | Q57: =IF(P57="PI",IF(U56<=0,0,U56),(IF(P57="IO",Q56,"")))*IF(U56<=0,0,1) -> 487666.25 | R57: =(IF(P57="PI",Q57,IF(ISNUMBER(U56),U56,Q57))*$R$3/365*$H57*IF(Q57>0,1,0)) -> 2563.7884 | S57: =IF(P57="IO",0,$R$6-R57)*IF(Q57>0,1,0) -> 1217.2116 | T57: =IF(P57="IO",$R$6-R57+IF(ISNUMBER(T56),T56,0),IF(ISNUMBER(T56),T56,0)) -> 0 | U57: =(Q57+R57-$R$6-IF(P57="PI",0,T57))*IF(Q57>0,1,0) -> 486449.04 | W57: PI | X57: =IF(W57="PI",IF(AB56<=0,0,AB56),(IF(W57="IO",X56,"")))*IF(AB56<=0,0,1) -> 428716.21 | Y57: =(IF(W57="PI",X57,IF(ISNUMBER(AB56),AB56,X57))*$Y$3/365*$H57*IF(X57>0,1,0)) -> 2253.8727 | Z57: =IF(W57="IO",0,$Y$6-Y57)*IF(X57>0,1,0) -> 630.12731 | AA57: =IF(W57="IO",$Y$6-Y57+IF(ISNUMBER(AA56),AA56,0),IF(ISNUMBER(AA56),AA56,0)) -> 0 | AB57: =(X57+Y57-$Y$6-IF(W57="PI",0,AA57))*IF(X57>0,1,0) -> 428086.08 | AD57: PI | AE57: =IF(AD57="PI",IF(AI56<=0,0,AI56),(IF(AD57="IO",AE56,"")))*IF(AI56<=0,0,1) -> 867635.11 | AF57: =(IF(AD57="PI",AE57,IF(ISNUMBER(AI56),AI56,AE57))*$AF$3/365*$H57*IF(AE57>0,1,0)) -> 4664.549 | AG57: =IF(AD57="IO",0,$AF$6-AF57)*IF(AE57>0,1,0) -> 1377.451 | AH57: =IF(AD57="IO",$AF$6-AF57+IF(ISNUMBER(AH56),AH56,0),IF(ISNUMBER(AH56),AH56,0)) -> 0 | AI57: =(AE57+AF57-$AF$6-IF(AD57="PI",0,AH57))*IF(AE57>0,1,0) -> 866257.65 | AK57: =E57 -> 2031 | AL57: =G57 -> 7 | AM57: =IF($AK57=$AK56,R57+AM56,R57) -> 2563.7884 | AN57: =IF($AK57=$AK56,Y57+AN56,Y57) -> 2253.8727 | AO57: =IF($AK57=$AK56,AF57+AO56,AF57) -> 4664.549 | AP57: =AM57+AN57 -> 4817.6611 | AQ57: =IF(AK57=AK56,AQ56,0)+ IF(J57>0,$K$6,0)+ IF(Q57>0,$R$6,0)+ IF(X57>0,$Y$6,0) -> 8303 | AR57: =N57+U57+AB57 -> 929182.15 | AS57: =AP57+AO57 -> 9482.2101 | AT57: =IF(AK57=AK56,AT56,0)+ IF(J57>0,L57,0)+ IF(Q57>0,S57,0)+ IF(X57>0,Z57,0)+ IF(AE57>0,AG57,0) -> 4779.8133 | AU57: =AS57+AT57 -> 14262.023 | AV57: =N57+U57+AB57+AI57 -> 1795439.8
D58: =D57+1 -> 50 | E58: =IF(MONTH(EDATE($E$5,D58))<7,YEAR(EDATE($E$5,D58)),YEAR(EDATE($E$5,D58))+1) -> 2031 | F58: =EDATE($E$5,D58) -> 47725 | G58: =MONTH(F58) -> 8 | H58: =DAY(EOMONTH(F58,0)) -> 31 | I58: PI | J58: =IF(I58="PI",IF(N57<=0,0,N57),(IF(I58="IO",J57,"")))*IF(N57<=0,0,1) -> 14647.023 | K58: =(IF(I58="PI",J58,IF(ISNUMBER(N57),N57,J58))*$K$3/365*$H58*IF(J58>0,1,0)) -> 75.012821 | L58: =IF(I58="IO",0,$K$6-K58)*IF(J58>0,1,0) -> 1562.9872 | M58: =IF(I58="IO",$K$6-K58+IF(ISNUMBER(M57),M57,0),IF(ISNUMBER(M57),M57,0)) -> 0 | N58: =(J58+K58-$K$6-IF(I58="PI",0,M58))*IF(J58>0,1,0) -> 13084.036 | P58: PI | Q58: =IF(P58="PI",IF(U57<=0,0,U57),(IF(P58="IO",Q57,"")))*IF(U57<=0,0,1) -> 486449.04 | R58: =(IF(P58="PI",Q58,IF(ISNUMBER(U57),U57,Q58))*$R$3/365*$H58*IF(Q58>0,1,0)) -> 2557.3892 | S58: =IF(P58="IO",0,$R$6-R58)*IF(Q58>0,1,0) -> 1223.6108 | T58: =IF(P58="IO",$R$6-R58+IF(ISNUMBER(T57),T57,0),IF(ISNUMBER(T57),T57,0)) -> 0 | U58: =(Q58+R58-$R$6-IF(P58="PI",0,T58))*IF(Q58>0,1,0) -> 485225.43 | W58: PI | X58: =IF(W58="PI",IF(AB57<=0,0,AB57),(IF(W58="IO",X57,"")))*IF(AB57<=0,0,1) -> 428086.08 | Y58: =(IF(W58="PI",X58,IF(ISNUMBER(AB57),AB57,X58))*$Y$3/365*$H58*IF(X58>0,1,0)) -> 2250.5599 | Z58: =IF(W58="IO",0,$Y$6-Y58)*IF(X58>0,1,0) -> 633.44005 | AA58: =IF(W58="IO",$Y$6-Y58+IF(ISNUMBER(AA57),AA57,0),IF(ISNUMBER(AA57),AA57,0)) -> 0 | AB58: =(X58+Y58-$Y$6-IF(W58="PI",0,AA58))*IF(X58>0,1,0) -> 427452.64 | AD58: PI | AE58: =IF(AD58="PI",IF(AI57<=0,0,AI57),(IF(AD58="IO",AE57,"")))*IF(AI57<=0,0,1) -> 866257.65 | AF58: =(IF(AD58="PI",AE58,IF(ISNUMBER(AI57),AI57,AE58))*$AF$3/365*$H58*IF(AE58>0,1,0)) -> 4657.1435 | AG58: =IF(AD58="IO",0,$AF$6-AF58)*IF(AE58>0,1,0) -> 1384.8565 | AH58: =IF(AD58="IO",$AF$6-AF58+IF(ISNUMBER(AH57),AH57,0),IF(ISNUMBER(AH57),AH57,0)) -> 0 | AI58: =(AE58+AF58-$AF$6-IF(AD58="PI",0,AH58))*IF(AE58>0,1,0) -> 864872.8 | AK58: =E58 -> 2031 | AL58: =G58 -> 8 | AM58: =IF($AK58=$AK57,R58+AM57,R58) -> 5121.1776 | AN58: =IF($AK58=$AK57,Y58+AN57,Y58) -> 4504.4326 | AO58: =IF($AK58=$AK57,AF58+AO57,AF58) -> 9321.6925 | AP58: =AM58+AN58 -> 9625.6103 | AQ58: =IF(AK58=AK57,AQ57,0)+ IF(J58>0,$K$6,0)+ IF(Q58>0,$R$6,0)+ IF(X58>0,$Y$6,0) -> 16606 | AR58: =N58+U58+AB58 -> 925762.11 | AS58: =AP58+AO58 -> 18947.303 | AT58: =IF(AK58=AK57,AT57,0)+ IF(J58>0,L58,0)+ IF(Q58>0,S58,0)+ IF(X58>0,Z58,0)+ IF(AE58>0,AG58,0) -> 9584.7077 | AU58: =AS58+AT58 -> 28532.011 | AV58: =N58+U58+AB58+AI58 -> 1790634.9
D59: =D58+1 -> 51 | E59: =IF(MONTH(EDATE($E$5,D59))<7,YEAR(EDATE($E$5,D59)),YEAR(EDATE($E$5,D59))+1) -> 2031 | F59: =EDATE($E$5,D59) -> 47756 | G59: =MONTH(F59) -> 9 | H59: =DAY(EOMONTH(F59,0)) -> 30 | I59: PI | J59: =IF(I59="PI",IF(N58<=0,0,N58),(IF(I59="IO",J58,"")))*IF(N58<=0,0,1) -> 13084.036 | K59: =(IF(I59="PI",J59,IF(ISNUMBER(N58),N58,J59))*$K$3/365*$H59*IF(J59>0,1,0)) -> 64.846631 | L59: =IF(I59="IO",0,$K$6-K59)*IF(J59>0,1,0) -> 1573.1534 | M59: =IF(I59="IO",$K$6-K59+IF(ISNUMBER(M58),M58,0),IF(ISNUMBER(M58),M58,0)) -> 0 | N59: =(J59+K59-$K$6-IF(I59="PI",0,M59))*IF(J59>0,1,0) -> 11510.882 | P59: PI | Q59: =IF(P59="PI",IF(U58<=0,0,U58),(IF(P59="IO",Q58,"")))*IF(U58<=0,0,1) -> 485225.43 | R59: =(IF(P59="PI",Q59,IF(ISNUMBER(U58),U58,Q59))*$R$3/365*$H59*IF(Q59>0,1,0)) -> 2468.6675 | S59: =IF(P59="IO",0,$R$6-R59)*IF(Q59>0,1,0) -> 1312.3325 | T59: =IF(P59="IO",$R$6-R59+IF(ISNUMBER(T58),T58,0),IF(ISNUMBER(T58),T58,0)) -> 0 | U59: =(Q59+R59-$R$6-IF(P59="PI",0,T59))*IF(Q59>0,1,0) -> 483913.1 | W59: PI | X59: =IF(W59="PI",IF(AB58<=0,0,AB58),(IF(W59="IO",X58,"")))*IF(AB58<=0,0,1) -> 427452.64 | Y59: =(IF(W59="PI",X59,IF(ISNUMBER(AB58),AB58,X59))*$Y$3/365*$H59*IF(X59>0,1,0)) -> 2174.7385 | Z59: =IF(W59="IO",0,$Y$6-Y59)*IF(X59>0,1,0) -> 709.26149 | AA59: =IF(W59="IO",$Y$6-Y59+IF(ISNUMBER(AA58),AA58,0),IF(ISNUMBER(AA58),AA58,0)) -> 0 | AB59: =(X59+Y59-$Y$6-IF(W59="PI",0,AA59))*IF(X59>0,1,0) -> 426743.38 | AD59: PI | AE59: =IF(AD59="PI",IF(AI58<=0,0,AI58),(IF(AD59="IO",AE58,"")))*IF(AI58<=0,0,1) -> 864872.8 | AF59: =(IF(AD59="PI",AE59,IF(ISNUMBER(AI58),AI58,AE59))*$AF$3/365*$H59*IF(AE59>0,1,0)) -> 4499.7081 | AG59: =IF(AD59="IO",0,$AF$6-AF59)*IF(AE59>0,1,0) -> 1542.2919 | AH59: =IF(AD59="IO",$AF$6-AF59+IF(ISNUMBER(AH58),AH58,0),IF(ISNUMBER(AH58),AH58,0)) -> 0 | AI59: =(AE59+AF59-$AF$6-IF(AD59="PI",0,AH59))*IF(AE59>0,1,0) -> 863330.51 | AK59: =E59 -> 2031 | AL59: =G59 -> 9 | AM59: =IF($AK59=$AK58,R59+AM58,R59) -> 7589.8451 | AN59: =IF($AK59=$AK58,Y59+AN58,Y59) -> 6679.1711 | AO59: =IF($AK59=$AK58,AF59+AO58,AF59) -> 13821.401 | AP59: =AM59+AN59 -> 14269.016 | AQ59: =IF(AK59=AK58,AQ58,0)+ IF(J59>0,$K$6,0)+ IF(Q59>0,$R$6,0)+ IF(X59>0,$Y$6,0) -> 24909 | AR59: =N59+U59+AB59 -> 922167.36 | AS59: =AP59+AO59 -> 28090.417 | AT59: =IF(AK59=AK58,AT58,0)+ IF(J59>0,L59,0)+ IF(Q59>0,S59,0)+ IF(X59>0,Z59,0)+ IF(AE59>0,AG59,0) -> 14721.747 | AU59: =AS59+AT59 -> 42812.164 | AV59: =N59+U59+AB59+AI59 -> 1785497.9
D60: =D59+1 -> 52 | E60: =IF(MONTH(EDATE($E$5,D60))<7,YEAR(EDATE($E$5,D60)),YEAR(EDATE($E$5,D60))+1) -> 2031 | F60: =EDATE($E$5,D60) -> 47786 | G60: =MONTH(F60) -> 10 | H60: =DAY(EOMONTH(F60,0)) -> 31 | I60: PI | J60: =IF(I60="PI",IF(N59<=0,0,N59),(IF(I60="IO",J59,"")))*IF(N59<=0,0,1) -> 11510.882 | K60: =(IF(I60="PI",J60,IF(ISNUMBER(N59),N59,J60))*$K$3/365*$H60*IF(J60>0,1,0)) -> 58.951486 | L60: =IF(I60="IO",0,$K$6-K60)*IF(J60>0,1,0) -> 1579.0485 | M60: =IF(I60="IO",$K$6-K60+IF(ISNUMBER(M59),M59,0),IF(ISNUMBER(M59),M59,0)) -> 0 | N60: =(J60+K60-$K$6-IF(I60="PI",0,M60))*IF(J60>0,1,0) -> 9931.8338 | P60: PI | Q60: =IF(P60="PI",IF(U59<=0,0,U59),(IF(P60="IO",Q59,"")))*IF(U59<=0,0,1) -> 483913.1 | R60: =(IF(P60="PI",Q60,IF(ISNUMBER(U59),U59,Q60))*$R$3/365*$H60*IF(Q60>0,1,0)) -> 2544.0571 | S60: =IF(P60="IO",0,$R$6-R60)*IF(Q60>0,1,0) -> 1236.9429 | T60: =IF(P60="IO",$R$6-R60+IF(ISNUMBER(T59),T59,0),IF(ISNUMBER(T59),T59,0)) -> 0 | U60: =(Q60+R60-$R$6-IF(P60="PI",0,T60))*IF(Q60>0,1,0) -> 482676.16 | W60: PI | X60: =IF(W60="PI",IF(AB59<=0,0,AB59),(IF(W60="IO",X59,"")))*IF(AB59<=0,0,1) -> 426743.38 | Y60: =(IF(W60="PI",X60,IF(ISNUMBER(AB59),AB59,X60))*$Y$3/365*$H60*IF(X60>0,1,0)) -> 2243.501 | Z60: =IF(W60="IO",0,$Y$6-Y60)*IF(X60>0,1,0) -> 640.49898 | AA60: =IF(W60="IO",$Y$6-Y60+IF(ISNUMBER(AA59),AA59,0),IF(ISNUMBER(AA59),AA59,0)) -> 0 | AB60: =(X60+Y60-$Y$6-IF(W60="PI",0,AA60))*IF(X60>0,1,0) -> 426102.88 | AD60: PI | AE60: =IF(AD60="PI",IF(AI59<=0,0,AI59),(IF(AD60="IO",AE59,"")))*IF(AI59<=0,0,1) -> 863330.51 | AF60: =(IF(AD60="PI",AE60,IF(ISNUMBER(AI59),AI59,AE60))*$AF$3/365*$H60*IF(AE60>0,1,0)) -> 4641.4067 | AG60: =IF(AD60="IO",0,$AF$6-AF60)*IF(AE60>0,1,0) -> 1400.5933 | AH60: =IF(AD60="IO",$AF$6-AF60+IF(ISNUMBER(AH59),AH59,0),IF(ISNUMBER(AH59),AH59,0)) -> 0 | AI60: =(AE60+AF60-$AF$6-IF(AD60="PI",0,AH60))*IF(AE60>0,1,0) -> 861929.91 | AK60: =E60 -> 2031 | AL60: =G60 -> 10 | AM60: =IF($AK60=$AK59,R60+AM59,R60) -> 10133.902 | AN60: =IF($AK60=$AK59,Y60+AN59,Y60) -> 8922.6722 | AO60: =IF($AK60=$AK59,AF60+AO59,AF60) -> 18462.807 | AP60: =AM60+AN60 -> 19056.574 | AQ60: =IF(AK60=AK59,AQ59,0)+ IF(J60>0,$K$6,0)+ IF(Q60>0,$R$6,0)+ IF(X60>0,$Y$6,0) -> 33212 | AR60: =N60+U60+AB60 -> 918710.87 | AS60: =AP60+AO60 -> 37519.382 | AT60: =IF(AK60=AK59,AT59,0)+ IF(J60>0,L60,0)+ IF(Q60>0,S60,0)+ IF(X60>0,Z60,0)+ IF(AE60>0,AG60,0) -> 19578.831 | AU60: =AS60+AT60 -> 57098.212 | AV60: =N60+U60+AB60+AI60 -> 1780640.8
D61: =D60+1 -> 53 | E61: =IF(MONTH(EDATE($E$5,D61))<7,YEAR(EDATE($E$5,D61)),YEAR(EDATE($E$5,D61))+1) -> 2031 | F61: =EDATE($E$5,D61) -> 47817 | G61: =MONTH(F61) -> 11 | H61: =DAY(EOMONTH(F61,0)) -> 30 | I61: PI | J61: =IF(I61="PI",IF(N60<=0,0,N60),(IF(I61="IO",J60,"")))*IF(N60<=0,0,1) -> 9931.8338 | K61: =(IF(I61="PI",J61,IF(ISNUMBER(N60),N60,J61))*$K$3/365*$H61*IF(J61>0,1,0)) -> 49.223801 | L61: =IF(I61="IO",0,$K$6-K61)*IF(J61>0,1,0) -> 1588.7762 | M61: =IF(I61="IO",$K$6-K61+IF(ISNUMBER(M60),M60,0),IF(ISNUMBER(M60),M60,0)) -> 0 | N61: =(J61+K61-$K$6-IF(I61="PI",0,M61))*IF(J61>0,1,0) -> 8343.0576 | P61: PI | Q61: =IF(P61="PI",IF(U60<=0,0,U60),(IF(P61="IO",Q60,"")))*IF(U60<=0,0,1) -> 482676.16 | R61: =(IF(P61="PI",Q61,IF(ISNUMBER(U60),U60,Q61))*$R$3/365*$H61*IF(Q61>0,1,0)) -> 2455.6976 | S61: =IF(P61="IO",0,$R$6-R61)*IF(Q61>0,1,0) -> 1325.3024 | T61: =IF(P61="IO",$R$6-R61+IF(ISNUMBER(T60),T60,0),IF(ISNUMBER(T60),T60,0)) -> 0 | U61: =(Q61+R61-$R$6-IF(P61="PI",0,T61))*IF(Q61>0,1,0) -> 481350.85 | W61: PI | X61: =IF(W61="PI",IF(AB60<=0,0,AB60),(IF(W61="IO",X60,"")))*IF(AB60<=0,0,1) -> 426102.88 | Y61: =(IF(W61="PI",X61,IF(ISNUMBER(AB60),AB60,X61))*$Y$3/365*$H61*IF(X61>0,1,0)) -> 2167.8714 | Z61: =IF(W61="IO",0,$Y$6-Y61)*IF(X61>0,1,0) -> 716.12863 | AA61: =IF(W61="IO",$Y$6-Y61+IF(ISNUMBER(AA60),AA60,0),IF(ISNUMBER(AA60),AA60,0)) -> 0 | AB61: =(X61+Y61-$Y$6-IF(W61="PI",0,AA61))*IF(X61>0,1,0) -> 425386.75 | AD61: PI | AE61: =IF(AD61="PI",IF(AI60<=0,0,AI60),(IF(AD61="IO",AE60,"")))*IF(AI60<=0,0,1) -> 861929.91 | AF61: =(IF(AD61="PI",AE61,IF(ISNUMBER(AI60),AI60,AE61))*$AF$3/365*$H61*IF(AE61>0,1,0)) -> 4484.397 | AG61: =IF(AD61="IO",0,$AF$6-AF61)*IF(AE61>0,1,0) -> 1557.603 | AH61: =IF(AD61="IO",$AF$6-AF61+IF(ISNUMBER(AH60),AH60,0),IF(ISNUMBER(AH60),AH60,0)) -> 0 | AI61: =(AE61+AF61-$AF$6-IF(AD61="PI",0,AH61))*IF(AE61>0,1,0) -> 860372.31 | AK61: =E61 -> 2031 | AL61: =G61 -> 11 | AM61: =IF($AK61=$AK60,R61+AM60,R61) -> 12589.6 | AN61: =IF($AK61=$AK60,Y61+AN60,Y61) -> 11090.544 | AO61: =IF($AK61=$AK60,AF61+AO60,AF61) -> 22947.204 | AP61: =AM61+AN61 -> 23680.143 | AQ61: =IF(AK61=AK60,AQ60,0)+ IF(J61>0,$K$6,0)+ IF(Q61>0,$R$6,0)+ IF(X61>0,$Y$6,0) -> 41515 | AR61: =N61+U61+AB61 -> 915080.66 | AS61: =AP61+AO61 -> 46627.348 | AT61: =IF(AK61=AK60,AT60,0)+ IF(J61>0,L61,0)+ IF(Q61>0,S61,0)+ IF(X61>0,Z61,0)+ IF(AE61>0,AG61,0) -> 24766.641 | AU61: =AS61+AT61 -> 71393.989 | AV61: =N61+U61+AB61+AI61 -> 1775453
D62: =D61+1 -> 54 | E62: =IF(MONTH(EDATE($E$5,D62))<7,YEAR(EDATE($E$5,D62)),YEAR(EDATE($E$5,D62))+1) -> 2031 | F62: =EDATE($E$5,D62) -> 47847 | G62: =MONTH(F62) -> 12 | H62: =DAY(EOMONTH(F62,0)) -> 31 | I62: PI | J62: =IF(I62="PI",IF(N61<=0,0,N61),(IF(I62="IO",J61,"")))*IF(N61<=0,0,1) -> 8343.0576 | K62: =(IF(I62="PI",J62,IF(ISNUMBER(N61),N61,J62))*$K$3/365*$H62*IF(J62>0,1,0)) -> 42.727884 | L62: =IF(I62="IO",0,$K$6-K62)*IF(J62>0,1,0) -> 1595.2721 | M62: =IF(I62="IO",$K$6-K62+IF(ISNUMBER(M61),M61,0),IF(ISNUMBER(M61),M61,0)) -> 0 | N62: =(J62+K62-$K$6-IF(I62="PI",0,M62))*IF(J62>0,1,0) -> 6747.7854 | P62: PI | Q62: =IF(P62="PI",IF(U61<=0,0,U61),(IF(P62="IO",Q61,"")))*IF(U61<=0,0,1) -> 481350.85 | R62: =(IF(P62="PI",Q62,IF(ISNUMBER(U61),U61,Q62))*$R$3/365*$H62*IF(Q62>0,1,0)) -> 2530.5867 | S62: =IF(P62="IO",0,$R$6-R62)*IF(Q62>0,1,0) -> 1250.4133 | T62: =IF(P62="IO",$R$6-R62+IF(ISNUMBER(T61),T61,0),IF(ISNUMBER(T61),T61,0)) -> 0 | U62: =(Q62+R62-$R$6-IF(P62="PI",0,T62))*IF(Q62>0,1,0) -> 480100.44 | W62: PI | X62: =IF(W62="PI",IF(AB61<=0,0,AB61),(IF(W62="IO",X61,"")))*IF(AB61<=0,0,1) -> 425386.75 | Y62: =(IF(W62="PI",X62,IF(ISNUMBER(AB61),AB61,X62))*$Y$3/365*$H62*IF(X62>0,1,0)) -> 2236.3689 | Z62: =IF(W62="IO",0,$Y$6-Y62)*IF(X62>0,1,0) -> 647.63113 | AA62: =IF(W62="IO",$Y$6-Y62+IF(ISNUMBER(AA61),AA61,0),IF(ISNUMBER(AA61),AA61,0)) -> 0 | AB62: =(X62+Y62-$Y$6-IF(W62="PI",0,AA62))*IF(X62>0,1,0) -> 424739.12 | AD62: PI | AE62: =IF(AD62="PI",IF(AI61<=0,0,AI61),(IF(AD62="IO",AE61,"")))*IF(AI61<=0,0,1) -> 860372.31 | AF62: =(IF(AD62="PI",AE62,IF(ISNUMBER(AI61),AI61,AE62))*$AF$3/365*$H62*IF(AE62>0,1,0)) -> 4625.503 | AG62: =IF(AD62="IO",0,$AF$6-AF62)*IF(AE62>0,1,0) -> 1416.497 | AH62: =IF(AD62="IO",$AF$6-AF62+IF(ISNUMBER(AH61),AH61,0),IF(ISNUMBER(AH61),AH61,0)) -> 0 | AI62: =(AE62+AF62-$AF$6-IF(AD62="PI",0,AH62))*IF(AE62>0,1,0) -> 858955.81 | AK62: =E62 -> 2031 | AL62: =G62 -> 12 | AM62: =IF($AK62=$AK61,R62+AM61,R62) -> 15120.187 | AN62: =IF($AK62=$AK61,Y62+AN61,Y62) -> 13326.912 | AO62: =IF($AK62=$AK61,AF62+AO61,AF62) -> 27572.707 | AP62: =AM62+AN62 -> 28447.099 | AQ62: =IF(AK62=AK61,AQ61,0)+ IF(J62>0,$K$6,0)+ IF(Q62>0,$R$6,0)+ IF(X62>0,$Y$6,0) -> 49818 | AR62: =N62+U62+AB62 -> 911587.35 | AS62: =AP62+AO62 -> 56019.806 | AT62: =IF(AK62=AK61,AT61,0)+ IF(J62>0,L62,0)+ IF(Q62>0,S62,0)+ IF(X62>0,Z62,0)+ IF(AE62>0,AG62,0) -> 29676.455 | AU62: =AS62+AT62 -> 85696.261 | AV62: =N62+U62+AB62+AI62 -> 1770543.2
... D367: =D366+1 -> 359 | E367: =IF(MONTH(EDATE($E$5,D367))<7,YEAR(EDATE($E$5,D367)),YEAR(EDATE($E$5,D367))+1) -> 2056 | F367: =EDATE($E$5,D367) -> 57130 | G367: =MONTH(F367) -> 5 | H367: =DAY(EOMONTH(F367,0)) -> 31 | I367: PI | J367: =IF(I367="PI",IF(N366<=0,0,N366),(IF(I367="IO",J366,"")))*IF(N366<=0,0,1) -> 0 | K367: =(IF(I367="PI",J367,IF(ISNUMBER(N366),N366,J367))*$K$3/365*$H367*IF(J367>0,1,0)) -> 0 | L367: =IF(I367="IO",0,$K$6-K367)*IF(J367>0,1,0) -> 0 | M367: =IF(I367="IO",$K$6-K367+IF(ISNUMBER(M366),M366,0),IF(ISNUMBER(M366),M366,0)) -> 0 | N367: =(J367+K367-$K$6-IF(I367="PI",0,M367))*IF(J367>0,1,0) -> 0 | P367: PI | Q367: =IF(P367="PI",IF(U366<=0,0,U366),(IF(P367="IO",Q366,"")))*IF(U366<=0,0,1) -> 0 | R367: =(IF(P367="PI",Q367,IF(ISNUMBER(U366),U366,Q367))*$R$3/365*$H367*IF(Q367>0,1,0)) -> 0 | S367: =IF(P367="IO",0,$R$6-R367)*IF(Q367>0,1,0) -> 0 | T367: =IF(P367="IO",$R$6-R367+IF(ISNUMBER(T366),T366,0),IF(ISNUMBER(T366),T366,0)) -> 0 | U367: =(Q367+R367-$R$6-IF(P367="PI",0,T367))*IF(Q367>0,1,0) -> 0 | W367: PI | X367: =IF(W367="PI",IF(AB366<=0,0,AB366),(IF(W367="IO",X366,"")))*IF(AB366<=0,0,1) -> 0 | Y367: =(IF(W367="PI",X367,IF(ISNUMBER(AB366),AB366,X367))*$Y$3/365*$H367*IF(X367>0,1,0)) -> 0 | Z367: =IF(W367="IO",0,$Y$6-Y367)*IF(X367>0,1,0) -> 0 | AA367: =IF(W367="IO",$Y$6-Y367+IF(ISNUMBER(AA366),AA366,0),IF(ISNUMBER(AA366),AA366,0)) -> 0 | AB367: =(X367+Y367-$Y$6-IF(W367="PI",0,AA367))*IF(X367>0,1,0) -> 0 | AD367: PI | AE367: =IF(AD367="PI",IF(AI366<=0,0,AI366),(IF(AD367="IO",AE366,"")))*IF(AI366<=0,0,1) -> 0 | AF367: =(IF(AD367="PI",AE367,IF(ISNUMBER(AI366),AI366,AE367))*$AF$3/365*$H367*IF(AE367>0,1,0)) -> 0 | AG367: =IF(AD367="IO",0,$AF$6-AF367)*IF(AE367>0,1,0) -> 0 | AH367: =IF(AD367="IO",$AF$6-AF367+IF(ISNUMBER(AH366),AH366,0),IF(ISNUMBER(AH366),AH366,0)) -> 0 | AI367: =(AE367+AF367-$AF$6-IF(AD367="PI",0,AH367))*IF(AE367>0,1,0) -> 0 | AK367: =E367 -> 2056 | AL367: =G367 -> 5 | AM367: =IF($AK367=$AK366,R367+AM366,R367) -> 0 | AN367: =IF($AK367=$AK366,Y367+AN366,Y367) -> 0 | AO367: =IF($AK367=$AK366,AF367+AO366,AF367) -> 0 | AP367: =AM367+AN367 -> 0 | AQ367: =IF(AK367=AK366,AQ366,0)+ IF(J367>0,$K$6,0)+ IF(Q367>0,$R$6,0)+ IF(X367>0,$Y$6,0) -> 0 | AR367: =N367+U367+AB367 -> 0 | AS367: =AP367+AO367 -> 0 | AT367: =IF(AK367=AK366,AT366,0)+ IF(J367>0,L367,0)+ IF(Q367>0,S367,0)+ IF(X367>0,Z367,0)+ IF(AE367>0,AG367,0) -> 0 | AU367: =AS367+AT367 -> 0 | AV367: =N367+U367+AB367+AI367 -> 0

Sheet Depreciation

Sheet WizdomActuals
B1: 45413 | I1: 45717 | P1: 45992 | W1: 46204
B2: Description | C2: Purchase Price | D2: Current Value | E2: Owned By | F2: Acquisition Date | G2: Notes | I2: Description | J2: Purchase Price | K2: Current Value | L2: Owned By | M2: Acquisition Date | N2: Notes | P2: Description | Q2: Purchase Price | R2: Current Value | S2: Owned By | T2: Acquisition Date | U2: Notes | W2: Description | X2: Purchase Price | Y2: Current Value | Z2: Owned By | AA2: Acquisition Date | AB2: Notes | AD2: Description | AE2: Purchase Price | AF2: Current Value | AG2: Owned By | AH2: Acquisition Date | AI2: Notes
B3: Eg: Property, Cars, Investments, SMSF, Superannuation, Cash in Bank, Shares | I3: Eg: Property, Cars, Investments, SMSF, Superannuation, Cash in Bank, Shares | P3: Eg: Property, Cars, Investments, SMSF, Superannuation, Cash in Bank, Shares | W3: Eg: Property, Cars, Investments, SMSF, Superannuation, Cash in Bank, Shares | AD3: Eg: Property, Cars, Investments, SMSF, Superannuation, Cash in Bank, Shares
B4: 4/10 Abraham Street, Rooty Hill, New South Wales, 2766 | D4: 701000 | E4: Jeffrey Hernandez, Cristina Hernandez | I4: 4/10 Abraham Street, Rooty Hill, New South Wales, 2766 | K4: 740000 | L4: Jeffrey Hernandez, Cristina Hernandez | P4: 4/10 Abraham Street, Rooty Hill, New South Wales, 2766 | R4: 740000 | S4: Jeffrey Hernandez, Cristina Hernandez | W4: 4/10 Abraham Street, Rooty Hill, New South Wales, 2766 | Y4: 740000 | Z4: Jeffrey Hernandez, Cristina Hernandez | AD4: 4/10 Abraham Street, Rooty Hill, New South Wales, 2766 | AF4: 850000 | AG4: Jeffrey Hernandez, Cristina Hernandez
B5: 4/304 Great Western Highway Way, Wentworthville, New South Wales, 2145 | D5: 570000 | E5: Jeffrey Hernandez, Cristina Hernandez | I5: 4/304 Great Western Highway Way, Wentworthville, New South Wales, 2145 | K5: 570000 | L5: Jeffrey Hernandez, Cristina Hernandez | P5: 4/304 Great Western Highway Way, Wentworthville, New South Wales, 2145 | R5: 570000 | S5: Jeffrey Hernandez, Cristina Hernandez | W5: 4/304 Great Western Highway Way, Wentworthville, New South Wales, 2145 | Y5: 570000 | Z5: Jeffrey Hernandez, Cristina Hernandez | AD5: 4/304 Great Western Highway Way, Wentworthville, New South Wales, 2145 | AF5: 565000 | AG5: Jeffrey Hernandez, Cristina Hernandez
B6: 403/335 Anketell Street, Greenway, Australian Capital Territory, 2900 | D6: 500000 | E6: Jeffrey Hernandez, Cristina Hernandez | I6: 403/335 Anketell Street, Greenway, Australian Capital Territory, 2900 | K6: 500000 | L6: Jeffrey Hernandez, Cristina Hernandez | P6: 403/335 Anketell Street, Greenway, Australian Capital Territory, 2900 | R6: 500000 | S6: Jeffrey Hernandez, Cristina Hernandez | W6: 403/335 Anketell Street, Greenway, Australian Capital Territory, 2900 | Y6: 500000 | Z6: Jeffrey Hernandez, Cristina Hernandez | AD6: 403/335 Anketell Street, Greenway, Australian Capital Territory, 2900 | AF6: 515000 | AG6: Jeffrey Hernandez, Cristina Hernandez
B7: 8 Shane Street, Colyton, New South Wales, 2760 | D7: 960000 | E7: Magiting Investments Pty Ltd | I7: 8 Shane Street, Colyton, New South Wales, 2760 | K7: 960000 | L7: Magiting Investments Pty Ltd | P7: 8 Shane Street, Colyton, New South Wales, 2760 | R7: 960000 | S7: Magiting Investments Pty Ltd | W7: 8 Shane Street, Colyton, New South Wales, 2760 | Y7: 960000 | Z7: Magiting Investments Pty Ltd | AD7: 8 Shane Street, Colyton, New South Wales, 2760 | AF7: 1200000 | AG7: Magiting Investments Pty Ltd
B8: Futurity / ASG Education Bond Fund | D8: 33406 | E8: Jeffrey Hernandez, Cristina Hernandez | F8: 41791 | I8: Futurity / ASG Education Bond Fund | K8: 33406 | L8: Jeffrey Hernandez, Cristina Hernandez | M8: 41791 | P8: Futurity / ASG Education Bond Fund | R8: 33406 | S8: Jeffrey Hernandez, Cristina Hernandez | T8: 41791 | W8: Futurity / ASG Education Bond Fund | Y8: 33406 | Z8: Jeffrey Hernandez, Cristina Hernandez | AA8: 41791 | AD8: Futurity / ASG Education Bond Fund xx3689 | AF8: 51148.45 | AG8: Jeffrey Hernandez, Cristina Hernandez | AH8: 41791
B9: CBA Shares (Tradeable) | D9: 16281 | E9: Jeffrey Hernandez | I9: CBA Shares (Tradeable) | K9: 16281 | L9: Jeffrey Hernandez | P9: CBA Shares (Tradeable) | R9: 16281 | S9: Jeffrey Hernandez | W9: CBA Shares (Tradeable) | Y9: 16281 | Z9: Jeffrey Hernandez | AD9: WBC Shares (Tradeable) | AF9: 6617 | AG9: Jeffrey Hernandez
B10: WBC Shares (Tradeable) | D10: 4628 | E10: Jeffrey Hernandez | I10: WBC Shares (Tradeable) | K10: 4628 | L10: Jeffrey Hernandez | P10: WBC Shares (Tradeable) | R10: 4628 | S10: Jeffrey Hernandez | W10: WBC Shares (Tradeable) | Y10: 4628 | Z10: Jeffrey Hernandez | AD10: Jeff Offset WW xx9474 | AF10: 38331.49 | AG10: Jeffrey Hernandez
B11: Jeff - Cash xx1534 | D11: 1076 | E11: Jeffrey Hernandez | I11: Jeff - Cash xx1534 | K11: 1076 | L11: Jeffrey Hernandez | P11: Jeff - Cash xx1534 | R11: 1076 | S11: Jeffrey Hernandez | W11: Jeff - Cash xx1534 | Y11: 1076 | Z11: Jeffrey Hernandez | AD11: RH Offset xx5182 | AF11: 60679.23 | AG11: Jeffrey Hernandez, Cristina Hernandez
B12: RH Offset xx5182 | D12: 40600 | E12: Jeffrey Hernandez, Cristina Hernandez | I12: RH Offset xx5182 | K12: 83053 | L12: Jeffrey Hernandez, Cristina Hernandez | P12: RH Offset xx5182 | R12: 83053 | S12: Jeffrey Hernandez, Cristina Hernandez | W12: RH Offset xx5182 | Y12: 83053 | Z12: Jeffrey Hernandez, Cristina Hernandez | AD12: RH Offset xx5190 | AF12: 21747.04 | AG12: Jeffrey Hernandez, Cristina Hernandez
B13: RH Offset xx5190 | D13: 25994 | E13: Jeffrey Hernandez, Cristina Hernandez | I13: RH Offset xx5190 | K13: 24321 | L13: Jeffrey Hernandez, Cristina Hernandez | P13: RH Offset xx5190 | R13: 24321 | S13: Jeffrey Hernandez, Cristina Hernandez | W13: RH Offset xx5190 | Y13: 24321 | Z13: Jeffrey Hernandez, Cristina Hernandez | AD13: Tin - Cash xx5865 | AF13: 936.68 | AG13: Cristina Hernandez
B14: Tin - Cash xx5865 | D14: 167 | E14: Cristina Hernandez | I14: Tin - Cash xx5865 | K14: 167 | L14: Cristina Hernandez | P14: Tin - Cash xx5865 | R14: 167 | S14: Cristina Hernandez | W14: Tin - Cash xx5865 | Y14: 167 | Z14: Cristina Hernandez | AD14: CBA Shares (ESS) | AF14: 30123 | AG14: Jeffrey Hernandez
B15: ING - Savings and Repayments | D15: 3000 | E15: Cristina Hernandez | I15: CBA Shares (In Plan) | K15: 3402 | L15: Jeffrey Hernandez | P15: CBA Shares (In Plan) | R15: 3402 | S15: Jeffrey Hernandez | W15: CBA Shares (In Plan) | Y15: 3402 | Z15: Jeffrey Hernandez | AD15: CBA Shares (Renounceable Rights Allotment) | AF15: 325 | AG15: Jeffrey Hernandez | AH15: 42265
B16: CBA Shares (In Plan) | D16: 3402 | E16: Jeffrey Hernandez | I16: CBA Shares (Renounceable Rights Allotment) | K16: 243 | L16: Jeffrey Hernandez | M16: 42265 | P16: CBA Shares (Renounceable Rights Allotment) | R16: 243 | S16: Jeffrey Hernandez | T16: 42265 | W16: CBA Shares (Renounceable Rights Allotment) | Y16: 243 | Z16: Jeffrey Hernandez | AA16: 42265 | AD16: Tin - Rent and Salary xx1575 | AF16: 3323 | AG16: Cristina Hernandez
B17: CBA Shares (Renounceable Rights Allotment) | D17: 243 | E17: Jeffrey Hernandez | F17: 42265 | I17: Tin - Rent and Salary xx1575 | K17: 3323 | L17: Cristina Hernandez | P17: Tin - Rent and Salary xx1575 | R17: 3323 | S17: Cristina Hernandez | W17: Tin - Rent and Salary xx1575 | Y17: 3323 | Z17: Cristina Hernandez | AD17: WW Offset xx6867 | AF17: 47864.37 | AG17: Cristina Hernandez, Jeffrey Hernandez
B18: Jeff - Australian Retirement Trust | D18: 176000 | E18: Jeffrey Hernandez | I18: WW Offset xx4508 | K18: 12502 | L18: Jeffrey Hernandez, Cristina Hernandez | P18: WW Offset xx4508 | R18: 12502 | S18: Jeffrey Hernandez, Cristina Hernandez | W18: WW Offset xx4508 | Y18: 12502 | Z18: Jeffrey Hernandez, Cristina Hernandez | AD18: BD Offset xx1893 | AF18: 36081.46 | AG18: Jeffrey Hernandez, Cristina Hernandez
B19: Jeff - Mercer Super | D19: 175000 | E19: Jeffrey Hernandez | I19: Jeff - Australian Retirement Trust | K19: 185769 | L19: Jeffrey Hernandez | P19: Jeff - Australian Retirement Trust | R19: 185769 | S19: Jeffrey Hernandez | W19: Jeff - Australian Retirement Trust | Y19: 185769 | Z19: Jeffrey Hernandez | AD19: Magiting Inv Trustee xx2243 | AF19: 979.42 | AG19: Magiting Investments Pty Ltd
I20: Jeff - Mercer Super | K20: 184799 | L20: Jeffrey Hernandez | P20: Jeff - Mercer Super | R20: 184799 | S20: Jeffrey Hernandez | W20: Jeff - Mercer Super | Y20: 184799 | Z20: Jeffrey Hernandez | AD20: Douglas
AD21: Jeff - Australian Retirement Trust | AF21: 213239 | AG21: Jeffrey Hernandez
AD22: Jeff - Mercer Super | AF22: 213549 | AG22: Jeffrey Hernandez

Sheet ToDo
B2: Adjust repayments sheet so that each liability has its own start date (for use in next property purchase scenario)
B3: Simplify calculation for personal and non-personal interest/principal/repayment calculations
B4: How do you handle scenarios - separate worksheet or add to income? Or add to forecast (since it's planning anyway)?
